Workbook

Sheet 00_Instruções_Básicas
A1: ='01_Preço'!A1
A2: GUIA DE INFORMAÇÕES BÁSICAS
A4: ='01_Preço'!A4 | D4: =_xlfn.CONCAT('01_Preço'!M4," ",'01_Preço'!O4)
A5: NOME EMPRESA PROPONENTE: | C5: ='01_Preço'!C5
A6: Nº CNPJ: | B6: ='01_Preço'!L5 | C6: Nº INSCRIÇÃO ESTADUAL: | D6: ='01_Preço'!Q5
A7: NOME REPRESENTANTE LEGAL: | C7: ='01_Preço'!C6
A8: Nº CPF: | B8: ='01_Preço'!L6 | C8: Nº DA IDENTIDADE: | D8: ='01_Preço'!Q6
A9: DATA DE EMISSÃO: | B9: ='01_Preço'!V5 | C9: BASE ECONÔMICA TRIBUTÁRIA: | D9: ='01_Preço'!V4
A10: ASSINATURA DO REPRESENTANTE LEGAL DA EMPRESA: | C10: ='01_Preço'!E7
A12: REFERE-SE A DISCIPLINA | B12: NOME DA ABA NA PLANILHA | C12: DESCRIÇÃO DA PLANILHA | D12: ORIENTAÇÕES BASICAS PARA O PREENCHIMENTO
A13: REFERE-SE A TODAS AS DISCIPLINAS E PLANILHAS | B13: 00_Instruções.Básicas | C13: Esta aba, a "00_Instruções.Básicas", é um guia com as informações e instruções básicas para o preenchimento da planilha de preço e eventogramas. Além desta, o arquivo Excel, inclui as seguintes abas: "01_Preço" com campos disponíveis para entrada dos dados da empresa bem como campos para preenchimento de valores unitários das disciplinas e demais dados solicitados, conforme regras do edital. "02_Sobressalent_Especif_CEMIG_D" com campos disponíveis para preenchimento de valores unitários dos itens sobressalentes listados. "03_Eventos.pagamentos" esta aba apresenta as informações sobre a distribuição dos valores em eventos de pagamento, é destinada a entrada da informação do referido mês de cumprimento de cada evento individualmente. "04_TOTALIZADORA" esta aba apresenta uma totalizadora com o gráfico da curva de distribuição de valores no tempo, PREÇO GLOBAL e campo disponível para preenchimento do valor da antecipação solicitada. | D13: Esta aba da planilha contém orientações básicas para o preenchimento das demais abas da planilha de preços e eventos. Para facilitar o preenchimento, as células que requerem informações, de acordo com as instruções do EDITAL, estão na cor amarela nas planilhas, as demais células que não necessitam de preenchimento neste momento / fase do edital estão bloqueadas. Além do preenchimento dos campos em amarelo, a empresa proponente deverá providenciar a assinatura das planilhas pelo representante legal da empresa.
A15: PREÇO | B15: 01_Preço | C15: É uma tabela destinada ao lançamento dos preços e impostos, correspondentes aos equipamentos, materiais e serviços do fornecimento. | D15: Preencher os campos em amarelo "LICITAÇÃO Nº", "BASE ECONÔMICA TRIBUTÁRIA:", "EMPRESA PROPONENTE", "Nº CNPJ", "Nº INSCRIÇÃO ESTADUAL", "REPRESENTANTE LEGAL", "Nº CPF", "Nº IDENTIDADE", "DATA DE EMISSÃO",com o número da licitação e os respectivos dados da empresa bem como a data da proposta e data da base econômica tributária. Tais dados serão automaticamente transferidos às demais abas. Preencher também, os campos das colunas "PREÇO UNITÁRIO (com todos os tributos) (R$)", "Identificação do Fornecedor ou Sub Fornecedor" e "CNAE" com os valores unitários respectivamente ofertados para os materiais e serviços das disciplinas, bem como os dados dos fornecedores, conforme requeridos. ATENÇÃO! Os campos das colunas de impostos, devem ser preenchidos somente após a adjudicação do vencedor do certame, em outro momento, conforme instruções do edital e demais documentação.
A17: PREÇO SOBRESSALENTES ATIVOS CEMIG D | B17: 02_Sobressalent_Especif_CEMIG_D | C17: É uma tabela destinada ao lançamento dos preços e impostos, correspondentes aos materiais sobressalente do escopo Cemig D. | D17: Preencher os campos em amarelo "VALOR TOTAL DO ITEM (R$) (com todos os Impostos, já incluso o ICMS a ser recolhido no Estado de destino.)",com o valor dos respectivos itens sobresssalentes listados na tabela. ATENÇÃO! Os campos das colunas de impostos, devem ser preenchidos somente após a adjudicação do vencedor do certame, em outro momento, conforme instruções do edital e demais documentação.
A19: Todas | B19: 02_Evento.pagamentos | C19: É uma tabela que apresenta os eventos, seus valores e coluna para lançamento do mês de conclusão para cada um dos eventos. | D19: Preencher os campos da coluna "Mês da proposta" com o mês de conclusão dos respectivos eventos, de acordo com as instruções do edital e demais documentações.
A21: Ambas Disciplinas | B21: 03_TOTALIZADORA | C21: É uma tabela destinada a apresentação do VALOR GLOBAL e da curva de desembolso mensal com o quantitativo de eventos e seus valores mensais. Apresenta também o campo para preenchimento do VALOR DE ANTECIPAÇÃO SOLICITADA, conforme regras definidas na documentação do edital. | D21: Planilha para apresentação dos valores, quantidades de eventos e da curva de desembolso. Preencher somente o campo "ANTECIPAÇÃO SOLICITADA" com o valor percentual solicitado de antecipação, sendo este limitado a 5% do valor do PREÇO GLOBAL da proposta, demais campos são carregados de forma automática de acordo com as planilhas de preços e eventos.

Sheet BM
A5: REFORMA E MODERNIZAÇÃO DE SALTO GRANDE
A7: BOLETIM DE MEDIÇÃO - Nº 03/2026
A8: Data de apresentação: | R8: 46037
A9: Nº do Contrato | D9: 4680007320 - 7321
A10: Mês de Referência | D10: 46037
A11: Empresa Contratada | D11: INSIGHT ENERGY
A12: Empresa Contratante | D12: CEMIG GERAÇÃO E TRANSMISSÃO SA
A13: Empresas Subcontratadas | D13: n/a
A15: DESCRIÇÃO DOS EVENTOS | M15: HISTÓRICO DE MEDIÇÃO | N15: MEDIÇÃO | P15: CONTA CORRENTE | T15: Para uso da CEMIG GT
A16: Mês do Evento | B16: Especificação Técnica | C16: Nº Evento | D16: Descrição do Evento (Conforme Contrato) | I16: Fornecedor | J16: Valor do Evento (P0) | K16: Valor do Reajuste | L16: Valor (P0 + Reajuste) | M16: Medições anteriores | N16: Valor cumprido | O16: Saldo do Evento | P16: Utilização de Conta Corrente | Q16: Evento Cedente | R16: Saldo do Evendo Cedente | T16: Análise Técnica de Cumprimento | U16: Comentário
A18: =IF(C18="","",_xlfn.XLOOKUP(C18,'03_Eventos_pagamentos'!$G$10:$G$901,'03_Eventos_pagamentos'!$E$10:$E$901)) | B18: 2.21 - Interferências civis | C18: ='03_Eventos_pagamentos'!G629 | D18: =IF(C18="","",_xlfn.XLOOKUP(C18,'[1]03_Eventos_pagamentos'!$F$10:$F$495,'[1]03_Eventos_pagamentos'!$G$10:$G$495)) | I18: INSIGHT | J18: ='03_Eventos_pagamentos'!O629 | K18: 0 | L18: =J18+K18 | M18: 0 | N18: =L18*0.3 | O18: =L18-N18
A19: =IF(C19="","",_xlfn.XLOOKUP(C19,'03_Eventos_pagamentos'!$G$10:$G$901,'03_Eventos_pagamentos'!$E$10:$E$901)) | B19: 2.21 - Interferências civis | C19: ='03_Eventos_pagamentos'!G643 | D19: =IF(C19="","",_xlfn.XLOOKUP(C19,'[1]03_Eventos_pagamentos'!$F$10:$F$495,'[1]03_Eventos_pagamentos'!$G$10:$G$495)) | I19: INSIGHT | J19: ='03_Eventos_pagamentos'!O643 | K19: 0 | L19: =J19+K19 | M19: 0 | N19: =L19
M20: 0
M21: 0
A22: Total | J22: =SUM(J18:J21) | K22: =SUM(K18:K21) | L22: =SUM(L18:L21) | M22: =SUM(M18:M21)
A24: VALOR TOTAL CUMPRIDO | N24: =SUM(N18:N21)
A27: Evidências de Cumprimento
A28: INSIGHT ENERGY - Relatório de Medição 003 - BM03
A30: Apresentado por:
C35: RICARDO FERREIRA PINTO | H35: Data:
A40: Para uso da CEMIG GT
A41: Parecer da CONTRATANTE (observações):
A42: Comentários no campo de análise da Engenhaira do Proprietário.
A49: Aferido por:
H54: Data:
A58: Aprovado por:
H63: Data:

Sheet 01_Preço
A1: PLANILHA DE PREÇOS E EVENTOGRAMAS EXECUÇÃO DAS OBRAS DE REFORMA E MODERNIZAÇÃO DA UHE SALTO GRANDE E MODERNIZAÇÃO E DIGITALIZAÇÃO DA SE UHE SALTO GRANDE – ATIVOS CEMIG D
A2: TABELA DE PREÇOS DOS EQUIPAMENTOS, MATERIAIS E SERVIÇOS DA REFORMA E MODERNIZAÇÃO DA UHE SALTO GRANDE E MODERNIZAÇÃO E DIGITALIZAÇÃO DA SE UHE SALTO GRANDE – ATIVOS CEMIG D
A4: OBJETO: CONTRATAÇÃO DE SERVIÇOS PARA EXECUÇÃO DA MODERNIZAÇÃO DA UHE SALTO GRANDE E MODERNIZAÇÃO E DIGITALIZAÇÂO DA SE UHE SALTO GRANDE | M4: LICITAÇÃO Nº | O4: 500-TK20335 | Q4: BASE ECONÔMICA TRIBUTÁRIA: | V4: Lucro Real
A5: EMPRESA PROPONENTE: | C5: INSIGHT ENERGIA SERVIÇOS ELETROMECÂNICOS LTDA. | K5: Nº CNPJ: | L5: 14.162.225/0001-59 | N5: Nº INSC ESTADUAL: | Q5: 90.698.627-29 | U5: DATA DE EMISSÃO: | V5: 45414
A6: REPRESENTANTE LEGAL: | C6: Fernanda Fagundes Hernandes | K6: Nº CPF: | L6: 078.184.519-00 | N6: Nº IDENTIDADE: | Q6: 104585167
A7: ASSINATURA DO REPRESENTANTE LEGAL:
K9: SERVIÇOS | O9: MATERIAIS/EQUIPAMENTOS
A10: ITEM / Nº | B10: TIPO DO ITEM (MATERIAL / SERVIÇO) | C10: BM | D10: MÊS/ANO CRONOGRAMA | E10: DESCRITIVO DOS MATERIAL / SERVIÇOS | F10: UNID. | G10: QUANT. | H10: PREÇO UNITÁRIO (com todos tributos) (R$) | I10: % | J10: R$ BM/Concluído | K10: Código de Tributação (LC 116/2003) | L10: ISS (%) | M10: Identificação do Fornecedor ou Sub Fornecedor | N10: CNAE | O10: Classif. Fiscal (NCM) | P10: Revenda (Sim / Não) | Q10: II (%) | R10: IPI (%) | S10: ICMS origem (%) | T10: ICMS destino (%) | U10: ICMS Substit. Tributária (%) | V10: PREÇO TOTAL (R$)
A11: 2.01 - Sistema de Supervisão e Controle e 2.10 - Sistema de Sincronismo | U11: =_xlfn.CONCAT("VALOR TOTAL DA ET ",A11,) | V11: =SUM(V12:V40)
A12: 2.01.01 | B12: SERVIÇO | E12: Engenharia e projeto executivo | F12: VB. | G12: 1 | H12: 1093825.5 | M12: INSIGHT/LCS LINK | V12: =G12*H12
C13: .
A14: 2.01.02 | B14: SERVIÇO | E14: Desmontagem e adequação dos painéis de controle existentes e respectiva infraestrutura de interligação, incluindo a execução de arranjos provisórios | F14: VB. | G14: 1 | H14: 1202760.3 | M14: INSIGHT ENERGY | V14: =G14*H14
C15: .
A16: 2.01.03 | B16: SERVIÇO | E16: Montagem eletromecânica completa | F16: VB. | G16: 1 | H16: 1433220.4 | M16: INSIGHT ENERGY | V16: =G16*H16
C17: .
A18: 2.01.04 | B18: SERVIÇO | E18: Supervisão, ensaios de campo e comissionamento | F18: VB. | G18: 1 | H18: 1944620.5 | M18: LCS LINK | V18: =G18*H18
C19: .
A20: 2.01.05 | B20: MATERIAL | E20: Painéis completos (+#UC) contendo a unidades de aquisição e controle para supervisão, comando e controle da Unidade Geradora, incluído sistema de parada de emergência | F20: CJ. | G20: 4 | H20: 996595.78 | M20: INSIGHT ENERGY | V20: =G20*H20 | W20: 3473818
C21: .
A22: 2.01.06 | B22: MATERIAL | E22: Painel completo (+AUC) para supervisão, comando e controle dos serviços auxiliares elétricos e mecânicos da casa de força e tomada d´água de Santo Antônio | F22: CJ. | G22: 1 | H22: 797753.84 | M22: INSIGHT ENERGY | V22: =G22*H22
C23: .
A24: 2.01.07 | B24: MATERIAL | E24: Painel completo (+VUC1) contendo a unidade de aquisição e controle (UAC) para supervisão do nível do reservatório de Santo Antônio | F24: CJ. | G24: 1 | H24: 328307.6 | M24: INSIGHT ENERGY | V24: =G24*H24
C25: .
A26: 2.01.08 | B26: MATERIAL | E26: Painel completo (+VUC2) contendo a unidade de aquisição e controle (UAC) para supervisão do nível do reservatório de Guanhães | F26: CJ. | G26: 1 | H26: 328307.6 | M26: INSIGHT ENERGY | V26: =G26*H26
C27: .
A28: 2.01.09 | B28: MATERIAL | E28: Painel completo (+VUC3) contendo a unidade de aquisição e controle (UAC) para supervisão, comando e controle das comportas de tomada d’água Santo Antônio e aquisição de nível dos reservatórios (Santo Antônio e Guanhães) | F28: CJ. | G28: 1 | H28: 328307.6 | M28: INSIGHT ENERGY | V28: =G28*H28
C29: .
A30: 2.01.10 | B30: MATERIAL | E30: Painel completo (+SUC) contendo a unidade de aquisição e controle (UAC) para a supervisão, comando e controle da subestação Salto Grande | F30: CJ. | G30: 1 | H30: 785598.22 | M30: INSIGHT ENERGY | V30: =G30*H30
C31: .
A32: 2.01.11 | B32: MATERIAL | E32: Painel completo contendo o módulo de comunicação (MCO) com o centro de operação, os equipamentos da rede de dados e os equipamentos do sistema de sincronismo de tempo - GPS | F32: CJ. | G32: 1 | H32: 485003.49 | M32: INSIGHT ENERGY | V32: =G32*H32
C33: .
A34: 2.01.12 | B34: MATERIAL | E34: Mobiliário completo para o Sistema Digital de Supervisão e Controle | F34: CJ. | G34: 1 | H34: 41647.43 | M34: INSIGHT ENERGY | V34: =G34*H34
C35: .
A36: 2.01.13 | B36: MATERIAL | E36: Estação de operação (EOP), Módulos de configuração e desenvolvimento (MCD) e impressora multifuncional | F36: CJ. | G36: 1 | H36: 113080.49 | M36: INSIGHT ENERGY | V36: =G36*H36
C37: .
A38: 2.01.14 | B38: MATERIAL | E38: Cópias e licenças dos diversos softwares, para o funcionamento integral, operação, visualização, configuração e manutenção do Sistema Digital de Supervisão e Controle | F38: CJ. | G38: 1 | H38: 218550.51 | M38: INSIGHT ENERGY | V38: =G38*H38
C39: .
A40: 2.01.15 | B40: MATERIAL | E40: Sistema de energia para alimentação ininterrupta em 220Vca | F40: CJ. | G40: 1 | H40: 39367.8 | M40: INSIGHT ENERGY | V40: =G40*H40
C41: .
A42: 2.02 - Sistema de Proteção | U42: =_xlfn.CONCAT("VALOR TOTAL DA ET ",A42,) | V42: =SUM(V43:V63)
A43: 2.02.01 | B43: SERVIÇO | E43: Engenharia e projeto executivo | F43: VB. | G43: 1 | H43: 894779.14 | M43: INSIGHT ENERGYERZEG | V43: =G43*H43
A45: 2.02.02 | B45: SERVIÇO | E45: Desmontagem e adequação dos painéis de proteção existentes e respectiva infraestrutura de interligação, incluindo a execução de arranjos provisórios | F45: VB. | G45: 1 | H45: 1267578.3 | M45: INSIGHT ENERGY | V45: =G45*H45
C46: .
A47: 2.02.03 | B47: SERVIÇO | E47: Montagem eletromecânica completa | F47: VB. | G47: 1 | H47: 1267578.3 | M47: INSIGHT ENERGY | V47: =G47*H47
C48: .
A49: 2.02.04 | B49: SERVIÇO | E49: Supervisão, ensaios de campo e comissionamento | F49: VB. | G49: 1 | H49: 213763.96 | M49: INSIGHT ENERGY | V49: =G49*H49
A51: 2.02.05 | B51: MATERIAL | E51: Painéis completos do Sistema de Proteção da Unidade Geradora | F51: CJ. | G51: 4 | H51: 987138.46 | M51: INSIGHT ENERGYERZEG | V51: =G51*H51
C52: .
A53: 2.02.06 | B53: MATERIAL | E53: Dispositivos para trip capacitivo ou bobina de mínima tensão para disjuntores | F53: CJ. | G53: 8 | H53: 18698.77 | M53: INSIGHT ENERGYERZEG | V53: =G53*H53
C54: .
A55: 2.02.07 | B55: MATERIAL | E55: Painel completo contendo o Registrador Digital de Perturbações (RDP) | F55: CJ. | G55: 1 | H55: 985036.9 | M55: INSIGHT ENERGYERZEG | V55: =G55*H55
A57: 2.02.08 | B57: MATERIAL | E57: Rede de dados para aquisição de oscilografia e parametrização dos relés, para comunicação entre os relés de proteção e SDSC, e para sincronismo de tempo | F57: CJ. | G57: 1 | H57: 123392.36 | M57: INSIGHT ENERGYERZEG | V57: =G57*H57
A59: 2.02.09 | B59: MATERIAL | E59: Estações de configuração portáteis, incluindo cabos de comunicação entre relés e computadores | F59: CJ. | G59: 2 | H59: 159700.19 | M59: INSIGHT ENERGY | V59: =G59*H59
A61: 2.02.10 | B61: MATERIAL | E61: Softwares com suas respectivas licenças para as estações de operação | F61: CJ. | G61: 2 | H61: 159700.19 | M61: INSIGHT ENERGY | V61: =G61*H61
A63: 2.02.11 | B63: MATERIAL | E63: Cabos de controle e de força para interligação entre os painéis de proteção e os diversos sistemas | F63: CJ. | G63: 1 | H63: 159700.2 | M63: INSIGHT ENERGY | V63: =G63*H63
A65: 2.03 - Sistema Regulação de Velocidade e 2.06 - Sistema de Excitação | U65: =_xlfn.CONCAT("VALOR TOTAL DA ET ",A65,) | V65: =SUM(V66:V99)
A66: 2.03.01 | B66: SERVIÇO | E66: Engenharia e projeto executivo | F66: VB. | G66: 1 | H66: 1223788.1 | M66: INSIGHT/REIVAX | V66: =G66*H66
C67: .
A68: 2.03.02 | B68: SERVIÇO | E68: Desmontagem dos painéis, materiais e equipamentos do sistema de regulação de velocidade e Sistema de excitação existente e respectiva infraestrutura | F68: VB. | G68: 1 | H68: 1415876.3 | M68: INSIGHT ENERGY | V68: =G68*H68
C69: .
A70: 2.03.03 | B70: SERVIÇO | E70: Montagem eletromecânica completa | F70: VB. | G70: 1 | H70: 1415876.3 | M70: INSIGHT ENERGY | V70: =G70*H70
C71: .
A72: 2.03.04 | B72: SERVIÇO | E72: Supervisão, ensaios de campo e comissionamento | F72: VB. | G72: 1 | H72: 393117 | M72: REIVAX | V72: =G72*H72
C73: .
A74: 2.03.05 | B74: MATERIAL | E74: Painel completo contendo o Regulador de Velocidade Digital da Unidade Geradora, incluindo IHM | F74: CJ. | G74: 4 | H74: 92196.62 | M74: REIVAX | V74: =G74*H74
C75: .
A76: 2.03.06 | B76: MATERIAL | E76: Instrumentação e demais dispositivos elétricos e mecânicos necessários à operação e integração do SRV da Unidade Geradora (chaves fim de curso, válvulas, solenóides, sensores, pêndulos de sobrevelocidade, sistemas de medição de velocidade, transdutores, geradores de sinal de velocidade tipo roda dentada, dentre outros) | F76: CJ. | G76: 4 | H76: 193933.29 | M76: REIVAX | V76: =G76*H76
C77: .
A78: 2.03.07 | B78: MATERIAL | E78: Sistema de excitação estática completos com tecnologia de controle digital, incluindo todos equipamentos, materiais e acessórios | F78: CJ. | G78: 4 | H78: 434194.87 | M78: REIVAX | V78: =G78*H78
C79: .
A80: 2.03.08 | B80: MATERIAL | E80: Transformadores de excitação trifásicos a seco com enrolamentos em cobre, proteções e acessórios | F80: CJ. | G80: 4 | H80: 299120 | M80: INSIGHT ENERGY | V80: =G80*H80
C81: .
A82: 2.03.09 | B82: MATERIAL | E82: Cubículos, disjuntores de campo, sistemas de excitação inicial e circuitos de desexcitação | F82: CJ. | G82: 4 | H82: 135361.62 | M82: REIVAX | V82: =G82*H82
C83: .
A84: 2.03.10 | B84: MATERIAL | E84: Micro computador do tipo notebook, com a configuração adequada aos programas e aplicativos dos equipamentos do SRT e do SRV | F84: CJ. | G84: 1 | H84: 20232.38 | M84: REIVAX | V84: =G84*H84
C85: .
A86: 2.03.11 | B86: MATERIAL | E86: Licenças de softwares de todos os componentes que necessitem delas para uso completo tais como IHM, PLC e todos aqueles que dependam de software para alteração, bem como os hardlocks e licenças de uso irrestrito para todos os softwares e hardwares aplicados | F86: CJ. | G86: 2 | H86: 25290.39 | M86: REIVAX | V86: =G86*H86
C87: .
A88: 2.03.12 | B88: MATERIAL | E88: Servomotores principais da turbina hidráulica da unidade geradora, completos | F88: CJ. | G88: 8 | H88: =163564.35/2 | M88: HINE | V88: =G88*H88
C89: .
A90: 2.03.13 | B90: MATERIAL | E90: Unidade Hidráulica completa da Unidade Geradora, contendo acumulador de pressão com nitrogênio-óleo, tanque de armazenamento de óleo, moto-bombas, eletroválvulas de controle, sensores, transdutores, sistemas de controle, trocadores de calor, filtros, painel local de comando e controle, etc. | F90: CJ. | G90: 4 | H90: 718915.07 | M90: HINE | V90: =G90*H90
C91: .
A92: 2.03.14 | B92: MATERIAL | E92: Motobomba portátil com filtro para esgotar as unidades hidráulicas e os servomotores em manutenção | F92: CJ. | G92: 1 | H92: 11467.31 | M92: HINE | V92: =G92*H92
C93: .
A94: 2.03.15 | B94: MATERIAL | E94: Cabos de força e de controle para interligação entre os cubículos novos e para adaptação com os circuitos atualmente existentes | F94: CJ. | G94: 4 | H94: 119119.13 | M94: INSIGHT ENERGY | V94: =G94*H94
C95: .
A96: 2.03.16 | B96: MATERIAL | E96: Carga de óleo completa e graxas para o Sistema de Regulação de Velocidade da Unidade Geradora | F96: CJ. | G96: 4 | H96: 210526.54 | M96: INSIGHT ENERGY | V96: =G96*H96
C97: .
A98: 2.03.17 | B98: MATERIAL | E98: Tubulações, suportes, adaptações e acessórios para o SRV | F98: CJ. | G98: 4 | H98: 49587.74 | M98: INSIGHT ENERGY | V98: =G98*H98
C99: .
A100: 2.04 - Serviços Auxiliares CA | U100: =_xlfn.CONCAT("VALOR TOTAL DA ET ",A100,) | V100: =SUM(V101:V121)
A101: 2.04.01 | B101: SERVIÇO | E101: Engenharia e projeto executivo | F101: VB. | G101: 1 | H101: 444468.68 | M101: INSIGHT ENERGYERZEG | V101: =G101*H101
C102: .
A103: 2.04.02 | B103: SERVIÇO | E103: Desmontagem e adequação dos equipamentos e painéis dos serviços auxiliares elétricos existentes e respectiva infraestrutura de interligação, incluindo a execução de arranjos provisórios | F103: VB. | G103: 1 | H103: 239759.52 | M103: INSIGHT ENERGY | V103: =G103*H103
C104: .
A105: 2.04.03 | B105: SERVIÇO | E105: Montagem eletromecânica completa | F105: VB. | G105: 1 | H105: 239759.52 | M105: INSIGHT ENERGY | V105: =G105*H105
C106: .
A107: 2.04.04 | B107: SERVIÇO | E107: Supervisão, ensaios de campo e comissionamento | F107: VB. | G107: 1 | H107: 44082.68 | M107: INSIGHT ENERGY | V107: =G107*H107
C108: .
A109: 2.04.05 | B109: MATERIAL | D109: contrafo | E109: Transformador de Serviços Auxiliares +T102/+T104 | F109: CJ. | G109: 2 | H109: 206760 | M109: INSIGHT ENERGY | V109: =G109*H109
...

Sheet Tabela de mês
A1: 1 | B1: 45474
A2: 2 | B2: 45505
A3: 3 | B3: 45536
A4: 4 | B4: 45566
A5: 5 | B5: 45597
A6: 6 | B6: 45627
A7: 7 | B7: 45658
A8: 8 | B8: 45689
A9: 9 | B9: 45717
A10: 10 | B10: 45748
A11: 11 | B11: 45778
A12: 12 | B12: 45809
... A68: 68 | B68: 47515
B69: 47543
B70: 47574
B71: 47604

Sheet 03_Eventos_pagamentos
A1: ='01_Preço'!A1
A2: TABELA DE EVENTOS DOS EQUIPAMENTOS, MATERIAIS E SERVIÇOS DA REFORMA E MODERNIZAÇÃO DA UHE SALTO GRANDE E MODERNIZAÇÃO E DIGITALIZAÇÃO DA SE UHE SALTO GRANDE – ATIVOS CEMIG D
A4: =_xlfn.CONCAT('01_Preço'!M4," ",'01_Preço'!O4) | B4: ='01_Preço'!A4 | L4: BASE ECONÔMICA TRIBUTÁRIA | M4: ='01_Preço'!V4
A5: EMPRESA PROPONENTE: | B5: ='01_Preço'!C5 | E5: INSC ESTADUAL: | L5: ='01_Preço'!Q5 | M5: Nº CNPJ: | O5: ='01_Preço'!L5
A6: REPRESENTANTE LEGAL: | B6: ='01_Preço'!C6 | E6: Nº IDENTIDADE: | L6: ='01_Preço'!Q6 | M6: Nº CPF: | O6: ='01_Preço'!L6
A7: ASSINATURA REPRESENTANTE LEGAL EMPRESA: | D7: ='01_Preço'!E7 | L7: DATA DE EMISSÃO | M7: ='01_Preço'!V5
A9: Especificação Técnica | B9: Item da Tab. Preços | C9: Tipo | D9: Descritivo do Item | E9: Mês Proposta | G9: Evento nº | H9: Execução | I9: Faturamento | J9: Código de nota | K9: Item segurado | L9: Descrição do Marco Principais / Evento | M9: % referente a ET | N9: Valor da ET | O9: Valor do Marco / Evento | P9: Mês de desembolso | Q9: Desembolso financeiro | S9: Faturamento realizado
A10: 2.01 - Sistema de Supervisão e Controle e 2.10 - Sincronismo | N10: =SUM(O11,O26,O31,O39,O51,O56,O57,O59,O58,O60,O61,O62,O63,O65,O64)
A11: ='01_Preço'!$A$11 | B11: ='01_Preço'!$A$12 | C11: ='01_Preço'!$B$12 | D11: ='01_Preço'!$E$12 | L11: ='01_Preço'!$E$12 | M11: =O11/$N$10 | O11: =SUM(O12:O25) | U11: LEGENDA
A12: ='01_Preço'!$A$11 | B12: ='01_Preço'!$A$12 | C12: ='01_Preço'!$B$12 | D12: ='01_Preço'!$E$12 | E12: 16 | F12: =VLOOKUP(E12,'Tabela de mês'!$A$1:$B$70,2,TRUE) | G12: 001-SER | H12: INSIGHT | I12: INSIGHT | J12: 7.01 | L12: Aprovação do Plano de Emissão de Documentos do Sistema de Supervisão e Controle | M12: =O12/$O$11 | O12: 21492.17 | S12: SIM | U12: VERDE | V12: EVENTO SEM ALTERAÇÃO
A13: ='01_Preço'!$A$11 | B13: ='01_Preço'!$A$12 | C13: ='01_Preço'!$B$12 | D13: ='01_Preço'!$E$12 | E13: 16 | F13: =VLOOKUP(E13,'Tabela de mês'!$A$1:$B$70,2,TRUE) | G13: 233-SER | H13: INSIGHT | I13: INSIGHT | L13: Aprovação do Plano de Emissão de Documentos do Sistema de Sincronismo | M13: =O13/$O$11 | O13: 21599.39 | S13: SIM | U13: AMARELO | V13: EVENTO ALTERADO
A14: ='01_Preço'!$A$11 | B14: ='01_Preço'!$A$12 | C14: ='01_Preço'!$B$12 | D14: ='01_Preço'!$E$12 | E14: 21 | F14: =VLOOKUP(E14,'Tabela de mês'!$A$1:$B$70,2,TRUE) | G14: 002-SER | H14: LCS LINK | I14: FAT. DIRETO | J14: 7.01 | L14: Aprovação da arquitetura e do Workstatement do Sistema de Supervisão e Controle | M14: =O14/$O$11 | O14: 64476.52 | U14: AZUL | V14: FATURAMENTO DIRETO
A15: ='01_Preço'!$A$11 | B15: ='01_Preço'!$A$12 | C15: ='01_Preço'!$B$12 | D15: ='01_Preço'!$E$12 | E15: 21 | F15: =VLOOKUP(E15,'Tabela de mês'!$A$1:$B$70,2,TRUE) | G15: 003-SER | H15: LCS LINK | I15: FAT. DIRETO | J15: 7.01 | L15: Aprovação dos Diagramas Lógicos das Unidades Funcionais | M15: =O15/$O$11 | O15: 64476.52
A16: ='01_Preço'!$A$11 | B16: ='01_Preço'!$A$12 | C16: ='01_Preço'!$B$12 | D16: ='01_Preço'!$E$12 | E16: 24 | F16: =VLOOKUP(E16,'Tabela de mês'!$A$1:$B$70,2,TRUE) | G16: 004-SER - A | H16: LCS LINK | I16: FAT. DIRETO | J16: 7.01 | L16: Aprovação completa dos Documentos do Projeto Executivo e de Fabricação do Sistema de Supervisão e Controle 1ª UF com paineis +AUC, +#UC, SUC e MCO | M16: =O16/$O$11 | O16: 103162.43
A17: ='01_Preço'!$A$11 | B17: ='01_Preço'!$A$12 | C17: ='01_Preço'!$B$12 | D17: ='01_Preço'!$E$12 | E17: 24 | F17: =VLOOKUP(E17,'Tabela de mês'!$A$1:$B$70,2,TRUE) | G17: 234-SER -A | H17: INSIGHT | I17: INSIGHT | J17: 7.01 | L17: Aprovação completa dos Documentos do Projeto Executivo e de Fabricação do Sistema de Sincronismo 1ª UF | M17: =O17/$O$11 | O17: 144476.52
A18: ='01_Preço'!$A$11 | B18: ='01_Preço'!$A$12 | C18: ='01_Preço'!$B$12 | D18: ='01_Preço'!$E$12 | E18: 35 | F18: =VLOOKUP(E18,'Tabela de mês'!$A$1:$B$70,2,TRUE) | G18: 004-SER - B | H18: LCS LINK | I18: FAT. DIRETO | J18: 7.01 | L18: Aprovação completa dos Documentos do Projeto Executivo e de Fabricação do Sistema de Supervisão e Controle 2ª UF com paineis +#UC | M18: =O18/$O$11 | O18: 51581.22
A19: ='01_Preço'!$A$11 | B19: ='01_Preço'!$A$12 | C19: ='01_Preço'!$B$12 | D19: ='01_Preço'!$E$12 | E19: 35 | F19: =VLOOKUP(E19,'Tabela de mês'!$A$1:$B$70,2,TRUE) | G19: 234-SER -B | H19: INSIGHT | I19: INSIGHT | J19: 7.01 | L19: Aprovação completa dos Documentos do Projeto Executivo e de Fabricação do Sistema de Sincronismo 2ª UF | M19: =O19/$O$11 | O19: 144476.52
A20: ='01_Preço'!$A$11 | B20: ='01_Preço'!$A$12 | C20: ='01_Preço'!$B$12 | D20: ='01_Preço'!$E$12 | E20: 48 | F20: =VLOOKUP(E20,'Tabela de mês'!$A$1:$B$70,2,TRUE) | G20: 004-SER - C | H20: LCS LINK | I20: FAT. DIRETO | J20: 7.01 | L20: Aprovação completa dos Documentos do Projeto Executivo e de Fabricação do Sistema de Supervisão e Controle 3ª UFcom paineis +#UC | M20: =O20/$O$11 | O20: 51581.22
A21: ='01_Preço'!$A$11 | B21: ='01_Preço'!$A$12 | C21: ='01_Preço'!$B$12 | D21: ='01_Preço'!$E$12 | E21: 48 | F21: =VLOOKUP(E21,'Tabela de mês'!$A$1:$B$70,2,TRUE) | G21: 234-SER -C | H21: INSIGHT | I21: INSIGHT | J21: 7.01 | L21: Aprovação completa dos Documentos do Projeto Executivo e de Fabricação do Sistema de Sincronismo 3ª UF | M21: =O21/$O$11 | O21: 144476.52
A22: ='01_Preço'!$A$11 | B22: ='01_Preço'!$A$12 | C22: ='01_Preço'!$B$12 | D22: ='01_Preço'!$E$12 | E22: 59 | F22: =VLOOKUP(E22,'Tabela de mês'!$A$1:$B$70,2,TRUE) | G22: 004-SER - D | H22: LCS LINK | I22: FAT. DIRETO | J22: 7.01 | L22: Aprovação completa dos Documentos do Projeto Executivo e de Fabricação do Sistema de Supervisão e Controle 4ª UF com paineis +#UC | M22: =O22/$O$11 | O22: 51581.22
A23: ='01_Preço'!$A$11 | B23: ='01_Preço'!$A$12 | C23: ='01_Preço'!$B$12 | D23: ='01_Preço'!$E$12 | E23: 59 | F23: =VLOOKUP(E23,'Tabela de mês'!$A$1:$B$70,2,TRUE) | G23: 234-SER -D | H23: INSIGHT | I23: INSIGHT | J23: 7.01 | L23: Aprovação completa dos Documentos do Projeto Executivo e de Fabricação do Sistema de Sincronismo 4ª UF | M23: =O23/$O$11 | O23: 144476.52
A24: ='01_Preço'!$A$11 | B24: ='01_Preço'!$A$12 | C24: ='01_Preço'!$B$12 | D24: ='01_Preço'!$E$12 | E24: 65 | F24: =VLOOKUP(E24,'Tabela de mês'!$A$1:$B$70,2,TRUE) | G24: 005-SER | H24: LCS LINK | I24: FAT. DIRETO | J24: 7.01 | L24: Aprovação da versão conforme construído do Projeto do Sistema de Supervisão e Controle | M24: =O24/$O$11 | O24: 42984.35
A25: ='01_Preço'!$A$11 | B25: ='01_Preço'!$A$12 | C25: ='01_Preço'!$B$12 | D25: ='01_Preço'!$E$12 | E25: 65 | F25: =VLOOKUP(E25,'Tabela de mês'!$A$1:$B$70,2,TRUE) | G25: 235-SER | H25: INSIGHT | I25: INSIGHT | J25: 7.01 | L25: Aprovação da versão conforme construído do Projeto do Sistema de Sincronismo | M25: =O25/$O$11 | O25: 42984.35
A26: ='01_Preço'!$A$11 | B26: ='01_Preço'!$A$14 | C26: ='01_Preço'!$B$14 | D26: Desmontagem eletromecânica completa | L26: ='01_Preço'!$E$14 | M26: =O26/$N$10 | O26: =SUM(O27:O30)
A27: ='01_Preço'!$A$11 | B27: ='01_Preço'!$A$14 | C27: ='01_Preço'!$B$14 | D27: Desmontagem eletromecânica completa | E27: 27 | F27: =VLOOKUP(E27,'Tabela de mês'!$A$1:$B$70,2,TRUE) | G27: 013-SER | H27: INSIGHT | I27: INSIGHT | J27: 7.02 | L27: Conclusão da Desmontagem de todos equipamentos e componentes do SDSC da 1ª UF, integrado aos demais equipamentos e sistemas | M27: =O27/$O$26 | O27: 300690.07 | P27: 25 | Q27: 168000
A28: ='01_Preço'!$A$11 | B28: ='01_Preço'!$A$14 | C28: ='01_Preço'!$B$14 | D28: Desmontagem eletromecânica completa | E28: 37 | F28: =VLOOKUP(E28,'Tabela de mês'!$A$1:$B$70,2,TRUE) | G28: 015-SER | H28: INSIGHT | I28: INSIGHT | J28: 7.02 | L28: Conclusão da Desmontagem de todos equipamentos e componentes do SDSC da 2ª UF, integrado aos demais equipamentos e sistemas | M28: =O28/$O$26 | O28: 300690.07 | P28: 35 | Q28: 168000
A29: ='01_Preço'!$A$11 | B29: ='01_Preço'!$A$14 | C29: ='01_Preço'!$B$14 | D29: Desmontagem eletromecânica completa | E29: 49 | F29: =VLOOKUP(E29,'Tabela de mês'!$A$1:$B$70,2,TRUE) | G29: 016-SER | H29: INSIGHT | I29: INSIGHT | J29: 7.02 | L29: Conclusão da Desmontagem de todos equipamentos e componentes do SDSC da 3ª UF, integrado aos demais equipamentos e sistemas | M29: =O29/$O$26 | O29: 300690.07 | P29: 46 | Q29: 168000
A30: ='01_Preço'!$A$11 | B30: ='01_Preço'!$A$14 | C30: ='01_Preço'!$B$14 | D30: Desmontagem eletromecânica completa | E30: 59 | F30: =VLOOKUP(E30,'Tabela de mês'!$A$1:$B$70,2,TRUE) | G30: 017-SER | H30: INSIGHT | I30: INSIGHT | J30: 7.02 | L30: Conclusão da Desmontagem de todos equipamentos e componentes do SDSC da 4ª UF, SE e Sala de Controle, integrado aos demais equipamentos e sistemas | M30: =O30/$O$26 | O30: 300690.07 | P30: 56 | Q30: 168000
A31: ='01_Preço'!$A$11 | B31: ='01_Preço'!$A$16 | C31: ='01_Preço'!$B$16 | D31: ='01_Preço'!$E$16 | L31: ='01_Preço'!$E$16 | M31: =O31/$N$10 | O31: =SUM(O32:O38)
A32: ='01_Preço'!$A$11 | B32: ='01_Preço'!$A$16 | C32: ='01_Preço'!$B$16 | D32: ='01_Preço'!$E$16 | E32: 31 | F32: =VLOOKUP(E32,'Tabela de mês'!$A$1:$B$70,2,TRUE) | G32: 238-SER | H32: INSIGHT | I32: INSIGHT | J32: 7.02 | L32: Conclusão da Adequações e Montagem de todos equipamentos e componentes do SDSC da 1ª UF, integrado aos demais equipamentos e sistemas | M32: =O32/$O$31 | O32: 300690.07
A33: ='01_Preço'!$A$11 | B33: ='01_Preço'!$A$16 | C33: ='01_Preço'!$B$16 | D33: ='01_Preço'!$E$16 | E33: 35 | F33: =VLOOKUP(E33,'Tabela de mês'!$A$1:$B$70,2,TRUE) | G33: 014-SER A | H33: INSIGHT | I33: INSIGHT | J33: 7.02 | L33: Conclusão das Adequações e Montagem de todos equipamentos e componentes do SDSC dos Tomada d'agua Santo antônio | M33: =O33/$O$31 | O33: 76820.04
A34: ='01_Preço'!$A$11 | B34: ='01_Preço'!$A$16 | C34: ='01_Preço'!$B$16 | D34: ='01_Preço'!$E$16 | E34: 40 | F34: =VLOOKUP(E34,'Tabela de mês'!$A$1:$B$70,2,TRUE) | G34: 014-SER B | H34: INSIGHT | I34: INSIGHT | J34: 7.02 | L34: Conclusão das Adequações e Montagem de todos equipamentos e componentes do SDSC dos Vertedouro Guanhães | M34: =O34/$O$31 | O34: 76820.03
A35: ='01_Preço'!$A$11 | B35: ='01_Preço'!$A$16 | C35: ='01_Preço'!$B$16 | D35: ='01_Preço'!$E$16 | E35: 40 | F35: =VLOOKUP(E35,'Tabela de mês'!$A$1:$B$70,2,TRUE) | G35: 014-SER C | H35: INSIGHT | I35: INSIGHT | J35: 7.02 | L35: Conclusão das Adequações e Montagem de todos equipamentos e componentes do SDSC do Vertedouro Santo Antônio | M35: =O35/$O$31 | O35: 76820.03
A36: ='01_Preço'!$A$11 | B36: ='01_Preço'!$A$16 | C36: ='01_Preço'!$B$16 | D36: ='01_Preço'!$E$16 | E36: 43 | F36: =VLOOKUP(E36,'Tabela de mês'!$A$1:$B$70,2,TRUE) | G36: 239-SER | H36: INSIGHT | I36: INSIGHT | J36: 7.02 | L36: Conclusão da Adequações e Montagem de todos equipamentos e componentes do SDSC da 2ª UF, integrado aos demais equipamentos e sistemas | M36: =O36/$O$31 | O36: 300690.07
A37: ='01_Preço'!$A$11 | B37: ='01_Preço'!$A$16 | C37: ='01_Preço'!$B$16 | D37: ='01_Preço'!$E$16 | E37: 55 | F37: =VLOOKUP(E37,'Tabela de mês'!$A$1:$B$70,2,TRUE) | G37: 240-SER | H37: INSIGHT | I37: INSIGHT | J37: 7.02 | L37: Conclusão da Adequações e Montagem de todos equipamentos e componentes do SDSC da 3ª UF, integrado aos demais equipamentos e sistemas | M37: =O37/$O$31 | O37: 300690.07
A38: ='01_Preço'!$A$11 | B38: ='01_Preço'!$A$16 | C38: ='01_Preço'!$B$16 | D38: ='01_Preço'!$E$16 | E38: 65 | F38: =VLOOKUP(E38,'Tabela de mês'!$A$1:$B$70,2,TRUE) | G38: 241-SER | H38: INSIGHT | I38: INSIGHT | J38: 7.02 | L38: Conclusão das adequações e Montagem de todos equipamentos e componentes do SDSC da 4ª UF, SE e Sala de Controle, integrado aos demais equipamentos e sistemas | M38: =O38/$O$31 | O38: 300690.07
A39: ='01_Preço'!$A$11 | B39: ='01_Preço'!$A$18 | C39: ='01_Preço'!$B$18 | D39: ='01_Preço'!$E$16 | L39: ='01_Preço'!$E$18 | M39: =O39/$N$10 | O39: =SUM(O40:O50)
A40: ='01_Preço'!$A$11 | B40: ='01_Preço'!$A$18 | C40: ='01_Preço'!$B$18 | D40: ='01_Preço'!$E$16 | E40: 33 | F40: =VLOOKUP(E40,'Tabela de mês'!$A$1:$B$70,2,TRUE) | G40: 018-SER | H40: LCS LINK | I40: FAT. DIRETO | J40: 7.02 | L40: Conclusão do Comissionamento estático do SDSC da 1ª UF, integrado aos demais equipamentos e sistemas | M40: =O40/$O$39 | O40: 175015.85
A41: ='01_Preço'!$A$11 | B41: ='01_Preço'!$A$18 | C41: ='01_Preço'!$B$18 | D41: ='01_Preço'!$E$16 | E41: 34 | F41: =VLOOKUP(E41,'Tabela de mês'!$A$1:$B$70,2,TRUE) | G41: 242-SER | H41: LCS LINK | I41: FAT. DIRETO | J41: 7.02 | L41: Conclusão do Comissionamento dinâmico do SDSC da 1ª UF, integrado aos demais equipamentos e sistemas | M41: =O41/$O$39 | O41: 408370.3
A42: ='01_Preço'!$A$11 | B42: ='01_Preço'!$A$18 | C42: ='01_Preço'!$B$18 | D42: ='01_Preço'!$E$16 | E42: 37 | F42: =VLOOKUP(E42,'Tabela de mês'!$A$1:$B$70,2,TRUE) | G42: 019-SER A | H42: LCS LINK | I42: FAT. DIRETO | J42: 7.02 | L42: Conclusão do Comissionamento do SDSC da Tomada d'Água Santo Antônio | M42: =O42/$O$39 | O42: 25928.27
A43: ='01_Preço'!$A$11 | B43: ='01_Preço'!$A$18 | C43: ='01_Preço'!$B$18 | D43: ='01_Preço'!$E$16 | E43: 42 | F43: =VLOOKUP(E43,'Tabela de mês'!$A$1:$B$70,2,TRUE) | G43: 019-SER B | H43: LCS LINK | I43: FAT. DIRETO | J43: 7.02 | L43: Conclusão do Comissionamento do SDSC do Vertedouro Guanhães | M43: =O43/$O$39 | O43: 25928.27
A44: ='01_Preço'!$A$11 | B44: ='01_Preço'!$A$18 | C44: ='01_Preço'!$B$18 | D44: ='01_Preço'!$E$16 | E44: 42 | F44: =VLOOKUP(E44,'Tabela de mês'!$A$1:$B$70,2,TRUE) | G44: 019-SER C | H44: LCS LINK | I44: FAT. DIRETO | J44: 7.02 | L44: Conclusão do Comissionamento do SDSC dos Vertedouro Santo Antônio | M44: =O44/$O$39 | O44: 25928.28
A45: ='01_Preço'!$A$11 | B45: ='01_Preço'!$A$18 | C45: ='01_Preço'!$B$18 | D45: ='01_Preço'!$E$16 | E45: 44 | F45: =VLOOKUP(E45,'Tabela de mês'!$A$1:$B$70,2,TRUE) | G45: 020-SER | H45: LCS LINK | I45: FAT. DIRETO | J45: 7.02 | L45: Conclusão do Comissionamento estático do SDSC da 2ª UF, integrado aos demais equipamentos e sistemas | M45: =O45/$O$39 | O45: 128344.95
A46: ='01_Preço'!$A$11 | B46: ='01_Preço'!$A$18 | C46: ='01_Preço'!$B$18 | D46: ='01_Preço'!$E$16 | E46: 45 | F46: =VLOOKUP(E46,'Tabela de mês'!$A$1:$B$70,2,TRUE) | G46: 243-SER | H46: LCS LINK | I46: FAT. DIRETO | J46: 7.02 | L46: Conclusão do Comissionamento dinâmico do SDSC da 2ª UF, integrado aos demais equipamentos e sistemas | M46: =O46/$O$39 | O46: 299471.56
A47: ='01_Preço'!$A$11 | B47: ='01_Preço'!$A$18 | C47: ='01_Preço'!$B$18 | D47: ='01_Preço'!$E$16 | E47: 56 | F47: =VLOOKUP(E47,'Tabela de mês'!$A$1:$B$70,2,TRUE) | G47: 021-SER | H47: LCS LINK | I47: FAT. DIRETO | J47: 7.02 | L47: Conclusão do Comissionamento estático do SDSC da 3ª UF, integrado aos demais equipamentos e sistemas | M47: =O47/$O$39 | O47: 128344.95
A48: ='01_Preço'!$A$11 | B48: ='01_Preço'!$A$18 | C48: ='01_Preço'!$B$18 | D48: ='01_Preço'!$E$16 | E48: 57 | F48: =VLOOKUP(E48,'Tabela de mês'!$A$1:$B$70,2,TRUE) | G48: 244-SER | H48: LCS LINK | I48: FAT. DIRETO | J48: 7.02 | L48: Conclusão do Comissionamento dinâmico do SDSC da 3ª UF, integrado aos demais equipamentos e sistemas | M48: =O48/$O$39 | O48: 299471.56
A49: ='01_Preço'!$A$11 | B49: ='01_Preço'!$A$18 | C49: ='01_Preço'!$B$18 | D49: ='01_Preço'!$E$16 | E49: 66 | F49: =VLOOKUP(E49,'Tabela de mês'!$A$1:$B$70,2,TRUE) | G49: 022-SER | H49: LCS LINK | I49: FAT. DIRETO | J49: 7.02 | L49: Conclusão do Comissionamento estático do SDSC da 4ª UF, SE e Sala de Controle, integrado aos demais equipamentos e sistemas | M49: =O49/$O$39 | O49: 128344.95
A50: ='01_Preço'!$A$11 | B50: ='01_Preço'!$A$18 | C50: ='01_Preço'!$B$18 | D50: ='01_Preço'!$E$16 | E50: 67 | F50: =VLOOKUP(E50,'Tabela de mês'!$A$1:$B$70,2,TRUE) | G50: 245-SER | H50: LCS LINK | I50: FAT. DIRETO | J50: 7.02 | L50: Conclusão do Comissionamento dinâmico do SDSC da 4ª UF, SE e Sala de Controle, integrado aos demais equipamentos e sistemas | M50: =O50/$O$39 | O50: 299471.56
A51: ='01_Preço'!$A$11 | B51: =CONCATENATE('01_Preço'!$A$20) | C51: ='01_Preço'!$B$20 | D51: Equipamentos e materiais | L51: =CONCATENATE('01_Preço'!$E$20) | M51: =O51/$N$10 | O51: =SUM(O52:O55)
A52: ='01_Preço'!$A$11 | B52: =CONCATENATE('01_Preço'!$A$20) | C52: ='01_Preço'!$B$20 | D52: Equipamentos e materiais | E52: 28 | F52: =VLOOKUP(E52,'Tabela de mês'!$A$1:$B$70,2,TRUE) | G52: 006-MAT | H52: INSIGHT | I52: INSIGHT | L52: Entrega completa na obra dos equipamentos e materiais na Usina do SDSC e sincronismo da 1ª UF ( #+UC) | M52: =O52/$O$51 | O52: 996595.77 | P52: 22 | Q52: 818454.51
A53: ='01_Preço'!$A$11 | B53: =CONCATENATE('01_Preço'!$A$20) | C53: ='01_Preço'!$B$20 | D53: Equipamentos e materiais | E53: 38 | F53: =VLOOKUP(E53,'Tabela de mês'!$A$1:$B$70,2,TRUE) | G53: 008-MAT | H53: INSIGHT | I53: INSIGHT | L53: Entrega completa na obra dos equipamentos e materiais na Usina do SDSC e sincronismo da 2ª UF ( #+UC) | M53: =O53/$O$51 | O53: 996595.78 | P53: 29 | Q53: 818454.51
A54: ='01_Preço'!$A$11 | B54: =CONCATENATE('01_Preço'!$A$20) | C54: ='01_Preço'!$B$20 | D54: Equipamentos e materiais | E54: 50 | F54: =VLOOKUP(E54,'Tabela de mês'!$A$1:$B$70,2,TRUE) | G54: 009-MAT | H54: INSIGHT | I54: INSIGHT | L54: Entrega completa na obra dos equipamentos e materiais na Usina do SDSC e sincronismo da 3ª UF ( #+UC) | M54: =O54/$O$51 | O54: 996595.78 | P54: 39 | Q54: 818454.51
A55: ='01_Preço'!$A$11 | B55: =CONCATENATE('01_Preço'!$A$20) | C55: ='01_Preço'!$B$20 | D55: Equipamentos e materiais | E55: 61 | F55: =VLOOKUP(E55,'Tabela de mês'!$A$1:$B$70,2,TRUE) | G55: 0010-MAT | H55: INSIGHT | I55: INSIGHT | L55: Entrega completa na obra dos equipamentos e materiais na Usina do SDSC e sincronismo da 4ª UF ( #+UC) | M55: =O55/$O$51 | O55: 996595.78 | P55: 60 | Q55: 818454.51
A56: ='01_Preço'!$A$11 | B56: ='01_Preço'!$A$22 | C56: ='01_Preço'!B$22 | D56: Equipamentos e materiais | E56: 28 | F56: =VLOOKUP(E56,'Tabela de mês'!$A$1:$B$54,2,TRUE) | G56: 007-MAT A | H56: INSIGHT | I56: INSIGHT | L56: Entrega em campo do painel completo (+AUC) para supervisão, comando e controle dos serviços auxiliares elétricos e mecânicos da casa de força e tomada d´água de Santo Antônio | M56: =O56/$N$10 | O56: 797753.84 | P56: 22 | Q56: =1136927.23*0.6
A57: ='01_Preço'!$A$11 | B57: ='01_Preço'!$A$24 | C57: ='01_Preço'!B$24 | D57: Equipamentos e materiais | E57: 31 | F57: =VLOOKUP(E57,'Tabela de mês'!$A$1:$B$54,2,TRUE) | G57: 011-MAT A | H57: INSIGHT | I57: INSIGHT | L57: Entrega em campo do painel completo (+VUC1) contendo a unidade de aquisição e controle (UAC) para supervisão do nível do reservatório de Santo Antônio | M57: =O57/$N$10 | O57: 328307.6 | P57: 22 | Q57: =462726.05*0.6
A58: ='01_Preço'!$A$11 | B58: ='01_Preço'!$A$26 | C58: ='01_Preço'!B$26 | D58: Equipamentos e materiais | E58: 36 | F58: =VLOOKUP(E58,'Tabela de mês'!$A$1:$B$54,2,TRUE) | G58: 011-MAT B | H58: INSIGHT | I58: INSIGHT | L58: Entrega em campo do painel completo (+VUC2) contendo a unidade de aquisição e controle (UAC) para supervisão do nível do reservatório de Guanhães | M58: =O58/$N$10 | O58: 328307.6 | P58: 22 | Q58: =462726.05*0.6
A59: ='01_Preço'!$A$11 | B59: ='01_Preço'!$A$28 | C59: ='01_Preço'!B$28 | D59: Equipamentos e materiais | E59: 36 | F59: =VLOOKUP(E59,'Tabela de mês'!$A$1:$B$54,2,TRUE) | G59: 011-MAT C | H59: INSIGHT | I59: INSIGHT | L59: Entrega em campo do painel completo (+VUC3) contendo a unidade de aquisição e controle (UAC) para supervisão, comando e controle das comportas de tomada d’água Santo Antônio e aquisição de nível dos reservatórios (Santo Antônio e Guanhães) | M59: =O59/$N$10 | O59: 328307.6 | P59: 22 | Q59: =462726.05*0.6
A60: ='01_Preço'!$A$11 | B60: ='01_Preço'!$A$30 | C60: ='01_Preço'!B$30 | D60: Equipamentos e materiais | E60: 28 | F60: =VLOOKUP(E60,'Tabela de mês'!$A$1:$B$54,2,TRUE) | G60: 007-MAT B | H60: INSIGHT | I60: INSIGHT | L60: Entrega em campo do painel completo (+SUC) contendo a unidade de aquisição e controle (UAC) para a supervisão, comando e controle da subestação Salto Grande | M60: =O60/$N$10 | O60: 785598.22 | P60: 22 | Q60: =903711*0.6
A61: ='01_Preço'!$A$11 | B61: ='01_Preço'!$A$32 | C61: ='01_Preço'!B$32 | D61: Equipamentos e materiais | E61: 28 | F61: =VLOOKUP(E61,'Tabela de mês'!$A$1:$B$54,2,TRUE) | G61: 007-MAT C | H61: INSIGHT | I61: INSIGHT | L61: Entrega em campo do painel completo contendo o módulo de comunicação (MCO) com o centro de operação, os equipamentos da rede de dados e os equipamentos do sistema de sincronismo de tempo - GPS | M61: =O61/$N$10 | O61: 485003.49 | P61: 22 | Q61: 350000
A62: ='01_Preço'!$A$11 | B62: ='01_Preço'!$A$34 | C62: ='01_Preço'!B$20 | D62: Equipamentos e materiais | E62: 54 | F62: =VLOOKUP(E62,'Tabela de mês'!$A$1:$B$54,2,TRUE) | G62: 012-MAT A | H62: INSIGHT | I62: INSIGHT | L62: Entrega em campo do mobiliário completo para o Sistema Digital de Supervisão e Controle | M62: =O62/$N$10 | O62: 41647.43 | P62: 40 | Q62: 20000
A63: ='01_Preço'!$A$11 | B63: ='01_Preço'!$A$36 | C63: ='01_Preço'!B$20 | D63: Equipamentos e materiais | E63: 32 | F63: =VLOOKUP(E63,'Tabela de mês'!$A$1:$B$54,2,TRUE) | G63: 012-MAT B | H63: INSIGHT | I63: INSIGHT | L63: Entrega em campo da estação de operação (EOP), Módulos de configuração e desenvolvimento (MCD) e impressora multifuncional | M63: =O63/$N$10 | O63: 113080.49 | P63: 43 | Q63: 20000
A64: ='01_Preço'!$A$11 | B64: ='01_Preço'!$A$38 | C64: ='01_Preço'!B$20 | D64: Equipamentos e materiais | E64: 32 | F64: =VLOOKUP(E64,'Tabela de mês'!$A$1:$B$54,2,TRUE) | G64: 237-MAT | H64: INSIGHT | I64: INSIGHT | L64: Fornecimento das cópias e licenças dos diversos softwares, para o funcionamento integral, operação, visualização, configuração e manutenção do Sistema Digital de Supervisão e Controle | M64: =O64/$N$10 | O64: 218550.51 | P64: 43 | Q64: 400000
A65: ='01_Preço'!$A$11 | B65: ='01_Preço'!$A$40 | C65: ='01_Preço'!B$20 | D65: Equipamentos e materiais | E65: 28 | F65: =VLOOKUP(E65,'Tabela de mês'!$A$1:$B$54,2,TRUE) | G65: 012-MAT C | H65: INSIGHT | I65: INSIGHT | L65: Entrega em campo do sistema de energia para alimentação ininterrupta em 220Vca | M65: =O65/$N$10 | O65: 39367.8 | P65: 40 | Q65: 30000
A66: 2.02 - Sistema de Proteção | N66: =SUM(O67,O76,O81,O86,O95,O100,O101,O106,O107,O108)
A67: ='01_Preço'!$A$42 | B67: ='01_Preço'!A43 | C67: ='01_Preço'!B$43 | D67: Equipamentos e materiais | L67: ='01_Preço'!E43 | M67: =O67/$N$66 | O67: =SUM(O68:O75)
A68: ='01_Preço'!$A$42 | B68: ='01_Preço'!A43 | C68: ='01_Preço'!B$43 | D68: ='01_Preço'!E43 | E68: 16 | F68: =VLOOKUP(E68,'Tabela de mês'!$A$1:$B$70,2,TRUE) | G68: 023-SER | H68: ERZEG | I68: INSIGHT | J68: 7.01 | L68: Aprovação do Plano de Emissão de Documentos do Sistema de Proteção | M68: =O68/$O$67 | O68: 16569.98 | S68: SIM
A69: ='01_Preço'!$A$42 | B69: ='01_Preço'!A43 | C69: ='01_Preço'!B$43 | D69: ='01_Preço'!E43 | E69: 22 | F69: =VLOOKUP(E69,'Tabela de mês'!$A$1:$B$70,2,TRUE) | G69: 024-SER | H69: ERZEG | I69: INSIGHT | J69: 7.01 | L69: Aprovação do Diagrama Unifilar de Proteção e Medição | M69: =O69/$O$67 | O69: 49709.94
A70: ='01_Preço'!$A$42 | B70: ='01_Preço'!A43 | C70: ='01_Preço'!B$43 | D70: ='01_Preço'!E43 | E70: 22 | F70: =VLOOKUP(E70,'Tabela de mês'!$A$1:$B$70,2,TRUE) | G70: 025-SER | H70: ERZEG | I70: INSIGHT | J70: 7.01 | L70: Aprovação da Memória de Cálculo e Dimensionamento do Sistema de Proteção | M70: =O70/$O$67 | O70: 149129.85 | P70: 22 | Q70: 31920
A71: ='01_Preço'!$A$42 | B71: ='01_Preço'!A43 | C71: ='01_Preço'!B$43 | D71: ='01_Preço'!E43 | E71: 24 | F71: =VLOOKUP(E71,'Tabela de mês'!$A$1:$B$70,2,TRUE) | G71: 026-SER A | H71: ERZEG | I71: INSIGHT | J71: 7.01 | L71: Aprovação completa dos Documentos do Projeto Executivo e de Fabricação do Sistema de Proteção 1ª UF e RDP | M71: =O71/$O$67 | O71: 161557.35 | P71: 22 | Q71: =233810/4
A72: ='01_Preço'!$A$42 | B72: ='01_Preço'!A43 | C72: ='01_Preço'!B$43 | D72: ='01_Preço'!E43 | E72: 35 | F72: =VLOOKUP(E72,'Tabela de mês'!$A$1:$B$70,2,TRUE) | G72: 026-SER B | H72: ERZEG | I72: INSIGHT | J72: 7.01 | L72: Aprovação completa dos Documentos do Projeto Executivo e de Fabricação do Sistema de Proteção 2ª UF | M72: =O72/$O$67 | O72: 161557.35 | P72: 31 | Q72: =233810/4
A73: ='01_Preço'!$A$42 | B73: ='01_Preço'!A43 | C73: ='01_Preço'!B$43 | D73: ='01_Preço'!E43 | E73: 48 | F73: =VLOOKUP(E73,'Tabela de mês'!$A$1:$B$70,2,TRUE) | G73: 026-SER C | H73: ERZEG | I73: INSIGHT | J73: 7.01 | L73: Aprovação completa dos Documentos do Projeto Executivo e de Fabricação do Sistema de Proteção 3ª UF | M73: =O73/$O$67 | O73: 161557.35 | P73: 43 | Q73: =233810/4
A74: ='01_Preço'!$A$42 | B74: ='01_Preço'!A43 | C74: ='01_Preço'!B$43 | D74: ='01_Preço'!E43 | E74: 59 | F74: =VLOOKUP(E74,'Tabela de mês'!$A$1:$B$70,2,TRUE) | G74: 026-SER D | H74: ERZEG | I74: INSIGHT | J74: 7.01 | L74: Aprovação completa dos Documentos do Projeto Executivo e de Fabricação do Sistema de Proteção 4ª UF | M74: =O74/$O$67 | O74: 161557.35 | P74: 53 | Q74: =233810/4
A75: 2.02 - Sistema de Proteção | B75: ='01_Preço'!A43 | C75: ='01_Preço'!B$43 | D75: ='01_Preço'!E43 | E75: 65 | F75: =VLOOKUP(E75,'Tabela de mês'!$A$1:$B$70,2,TRUE) | G75: 027-SER | H75: ERZEG | I75: INSIGHT | J75: 7.01 | L75: Aprovação da versão conforme construído do Projeto do Sistema de Proteção | M75: =O75/$O$67 | O75: 33139.97
A76: ='01_Preço'!$A$42 | B76: ='01_Preço'!$A$45 | C76: ='01_Preço'!B$45 | D76: Desmontagem e montagem eletromecânica completa | L76: ='01_Preço'!E45 | M76: =O76/$N$66 | O76: =SUM(O77:O80)
A77: ='01_Preço'!$A$42 | B77: ='01_Preço'!$A$45 | C77: ='01_Preço'!B$45 | D77: Desmontagem e montagem eletromecânica completa | E77: 27 | F77: =VLOOKUP(E77,'Tabela de mês'!$A$1:$B$70,2,TRUE) | G77: 034-SER A | H77: INSIGHT | I77: INSIGHT | J77: 7.02 | L77: Conclusão da desmontagem de todos equipamentos e componentes do Sistema de Proteção da 1ª UF, integrado aos demais equipamentos e sistemas | M77: =O77/$O$76 | O77: 316894.58
A78: ='01_Preço'!$A$42 | B78: ='01_Preço'!$A$45 | C78: ='01_Preço'!B$45 | D78: Desmontagem e montagem eletromecânica completa | E78: 39 | F78: =VLOOKUP(E78,'Tabela de mês'!$A$1:$B$70,2,TRUE) | G78: 035-SER A | H78: INSIGHT | I78: INSIGHT | J78: 7.02 | L78: Conclusão da desmontagem de todos equipamentos e componentes do Sistema de Proteção da 2ª UF, integrado aos demais equipamentos e sistemas | M78: =O78/$O$76 | O78: 316894.58
A79: ='01_Preço'!$A$42 | B79: ='01_Preço'!$A$45 | C79: ='01_Preço'!B$45 | D79: Desmontagem e montagem eletromecânica completa | E79: 51 | F79: =VLOOKUP(E79,'Tabela de mês'!$A$1:$B$70,2,TRUE) | G79: 036-SER A | H79: INSIGHT | I79: INSIGHT | J79: 7.02 | L79: Conclusão da desmontagem de todos equipamentos e componentes do Sistema de Proteção da 3ª UF, integrado aos demais equipamentos e sistemas | M79: =O79/$O$76 | O79: 316894.58
A80: ='01_Preço'!$A$42 | B80: ='01_Preço'!$A$45 | C80: ='01_Preço'!B$45 | D80: Desmontagem e montagem eletromecânica completa | E80: 61 | F80: =VLOOKUP(E80,'Tabela de mês'!$A$1:$B$70,2,TRUE) | G80: 037-SER A | H80: INSIGHT | I80: INSIGHT | J80: 7.02 | L80: Conclusão da desmontagem de todos equipamentos e componentes do Sistema de Proteção da 4ª UF, integrado aos demais equipamentos e sistemas | M80: =O80/$O$76 | O80: 316894.58
A81: ='01_Preço'!$A$42 | B81: ='01_Preço'!$A$47 | C81: ='01_Preço'!B$47 | D81: Equipamentos e materiais | L81: ='01_Preço'!E47 | M81: =O81/$N$66 | O81: =SUM(O82:O85)
A82: ='01_Preço'!$A$42 | B82: ='01_Preço'!$A$47 | C82: ='01_Preço'!$B$47 | D82: Desmontagem e montagem eletromecânica completa | E82: 31 | F82: =VLOOKUP(E82,'Tabela de mês'!$A$1:$B$70,2,TRUE) | G82: 034-SER B | H82: INSIGHT | I82: INSIGHT | J82: 7.02 | L82: Conclusão da Montagem de todos equipamentos e componentes do Sistema de Proteção da 1ª UF, integrado aos demais equipamentos e sistemas | M82: =O82/$O$81 | O82: 316894.57
A83: ='01_Preço'!$A$42 | B83: ='01_Preço'!$A$47 | C83: ='01_Preço'!$B$47 | D83: Desmontagem e montagem eletromecânica completa | E83: 43 | F83: =VLOOKUP(E83,'Tabela de mês'!$A$1:$B$70,2,TRUE) | G83: 035-SER B | H83: INSIGHT | I83: INSIGHT | J83: 7.02 | L83: Conclusão da Montagem de todos equipamentos e componentes do Sistema de Proteção da 2ª UF, integrado aos demais equipamentos e sistemas | M83: =O83/$O$81 | O83: 316894.57
A84: ='01_Preço'!$A$42 | B84: ='01_Preço'!$A$47 | C84: ='01_Preço'!$B$47 | D84: Desmontagem e montagem eletromecânica completa | E84: 55 | F84: =VLOOKUP(E84,'Tabela de mês'!$A$1:$B$70,2,TRUE) | G84: 036-SER B | H84: INSIGHT | I84: INSIGHT | J84: 7.02 | L84: Conclusão da Montagem de todos equipamentos e componentes do Sistema de Proteção da 3ª UF, integrado aos demais equipamentos e sistemas | M84: =O84/$O$81 | O84: 316894.58
A85: ='01_Preço'!$A$42 | B85: ='01_Preço'!$A$47 | C85: ='01_Preço'!$B$47 | D85: Desmontagem e montagem eletromecânica completa | E85: 66 | F85: =VLOOKUP(E85,'Tabela de mês'!$A$1:$B$70,2,TRUE) | G85: 037-SER B | H85: INSIGHT | I85: INSIGHT | J85: 7.02 | L85: Conclusão da Montagem de todos equipamentos e componentes do Sistema de Proteção da 4ª UF, integrado aos demais equipamentos e sistemas | M85: =O85/$O$81 | O85: 316894.58
A86: ='01_Preço'!$A$42 | B86: ='01_Preço'!$A$49 | C86: ='01_Preço'!B$49 | D86: Equipamentos e materiais | L86: ='01_Preço'!E49 | M86: =O86/$N$66 | O86: =SUM(O87:O94)
A87: ='01_Preço'!$A$42 | B87: ='01_Preço'!$A$49 | C87: ='01_Preço'!$B$49 | D87: Equipamentos e materiais | E87: 32 | F87: =VLOOKUP(E87,'Tabela de mês'!$A$1:$B$70,2,TRUE) | G87: 038-SER A | H87: INSIGHT | I87: INSIGHT | J87: 7.02 | L87: Conclusão do Comissionamento estático do Sistema de Proteção e RDP da 1ª UF | M87: =O87/$O$86 | O87: 26720.495
A88: ='01_Preço'!$A$42 | B88: ='01_Preço'!$A$49 | C88: ='01_Preço'!$B$49 | D88: Equipamentos e materiais | E88: 44 | F88: =VLOOKUP(E88,'Tabela de mês'!$A$1:$B$70,2,TRUE) | G88: 039-SER A | H88: INSIGHT | I88: INSIGHT | J88: 7.02 | L88: Conclusão do Comissionamento estático do Sistema de Proteção e RDP da 2ª UF | M88: =O88/$O$86 | O88: 26720.495
A89: ='01_Preço'!$A$42 | B89: ='01_Preço'!$A$49 | C89: ='01_Preço'!$B$49 | D89: Equipamentos e materiais | E89: 55 | F89: =VLOOKUP(E89,'Tabela de mês'!$A$1:$B$70,2,TRUE) | G89: 040-SER A | H89: INSIGHT | I89: INSIGHT | J89: 7.02 | L89: Conclusão do Comissionamento estático do Sistema de Proteção e RDP da 3ª UF | M89: =O89/$O$86 | O89: 26720.495
A90: ='01_Preço'!$A$42 | B90: ='01_Preço'!$A$49 | C90: ='01_Preço'!$B$49 | D90: Equipamentos e materiais | E90: 67 | F90: =VLOOKUP(E90,'Tabela de mês'!$A$1:$B$70,2,TRUE) | G90: 041-SER A | H90: INSIGHT | I90: INSIGHT | J90: 7.02 | L90: Conclusão do Comissionamento estático do Sistema de Proteção e RDP da 4ª UF | M90: =O90/$O$86 | O90: 26720.495
A91: ='01_Preço'!$A$42 | B91: ='01_Preço'!$A$49 | C91: ='01_Preço'!$B$49 | D91: Equipamentos e materiais | E91: 33 | F91: =VLOOKUP(E91,'Tabela de mês'!$A$1:$B$70,2,TRUE) | G91: 038-SER B | H91: INSIGHT | I91: INSIGHT | J91: 7.02 | L91: Conclusão do Comissionamento dinâmico do Sistema de Proteção e RDP da 1ª UF | M91: =O91/$O$86 | O91: 26720.495
A92: ='01_Preço'!$A$42 | B92: ='01_Preço'!$A$49 | C92: ='01_Preço'!$B$49 | D92: Equipamentos e materiais | E92: 45 | F92: =VLOOKUP(E92,'Tabela de mês'!$A$1:$B$70,2,TRUE) | G92: 039-SER B | H92: INSIGHT | I92: INSIGHT | J92: 7.02 | L92: Conclusão do Comissionamento dinâmico do Sistema de Proteção e RDP da 2ª UF | M92: =O92/$O$86 | O92: 26720.495
A93: ='01_Preço'!$A$42 | B93: ='01_Preço'!$A$49 | C93: ='01_Preço'!$B$49 | D93: Equipamentos e materiais | E93: 56 | F93: =VLOOKUP(E93,'Tabela de mês'!$A$1:$B$70,2,TRUE) | G93: 040-SER B | H93: INSIGHT | I93: INSIGHT | J93: 7.02 | L93: Conclusão do Comissionamento dinâmico do Sistema de Proteção e RDP da 3ª UF | M93: =O93/$O$86 | O93: 26720.495
A94: ='01_Preço'!$A$42 | B94: ='01_Preço'!$A$49 | C94: ='01_Preço'!$B$49 | D94: Equipamentos e materiais | E94: 68 | F94: =VLOOKUP(E94,'Tabela de mês'!$A$1:$B$70,2,TRUE) | G94: 041-SER B | H94: INSIGHT | I94: INSIGHT | J94: 7.02 | L94: Conclusão do Comissionamento dinâmico do Sistema de Proteção e RDP da 4ª UF | M94: =O94/$O$86 | O94: 26720.495
A95: ='01_Preço'!$A$42 | B95: =CONCATENATE('01_Preço'!$A$51," e ",'01_Preço'!$A$53) | C95: ='01_Preço'!B$51 | D95: Equipamentos e materiais | L95: =CONCATENATE('01_Preço'!$E$51," e ",'01_Preço'!$E$53) | M95: =O95/$N$66 | O95: =SUM(O96:O99)
A96: ='01_Preço'!$A$42 | B96: =CONCATENATE('01_Preço'!$A$51," e ",'01_Preço'!$A$53) | C96: ='01_Preço'!$B$51 | D96: Equipamentos e materiais | E96: 30 | F96: =VLOOKUP(E96,'Tabela de mês'!$A$1:$B$70,2,TRUE) | G96: 028-MAT A | H96: ERZEG | I96: INSIGHT | L96: Entrega completa na obra dos equipamentos e materiais do Sistemas de Proteção da 1ª UF | M96: =O96/$O$95 | O96: 1024536 | P96: 21 | Q96: 900000
A97: ='01_Preço'!$A$42 | B97: =CONCATENATE('01_Preço'!$A$51," e ",'01_Preço'!$A$53) | C97: ='01_Preço'!$B$51 | D97: Equipamentos e materiais | E97: 40 | F97: =VLOOKUP(E97,'Tabela de mês'!$A$1:$B$70,2,TRUE) | G97: 031-MAT A | H97: ERZEG | I97: INSIGHT | L97: Entrega completa na obra dos equipamentos e materiais do Sistemas de Proteção da 2ª UF | M97: =O97/$O$95 | O97: 1024536 | P97: 30 | Q97: 900000
A98: ='01_Preço'!$A$42 | B98: =CONCATENATE('01_Preço'!$A$51," e ",'01_Preço'!$A$53) | C98: ='01_Preço'!$B$51 | D98: Equipamentos e materiais | E98: 52 | F98: =VLOOKUP(E98,'Tabela de mês'!$A$1:$B$70,2,TRUE) | G98: 032-MAT A | H98: ERZEG | I98: INSIGHT | L98: Entrega completa na obra dos equipamentos e materiais do Sistemas de Proteção da 3ª UF | M98: =O98/$O$95 | O98: 1024536 | P98: 40 | Q98: 900000
A99: ='01_Preço'!$A$42 | B99: =CONCATENATE('01_Preço'!$A$51," e ",'01_Preço'!$A$53) | C99: ='01_Preço'!$B$51 | D99: Equipamentos e materiais | E99: 62 | F99: =VLOOKUP(E99,'Tabela de mês'!$A$1:$B$70,2,TRUE) | G99: 033-MAT A | H99: ERZEG | I99: INSIGHT | L99: Entrega completa na obra dos equipamentos e materiais do Sistemas de Proteção da 4ª UF | M99: =O99/$O$95 | O99: 1024536 | P99: 50 | Q99: 900000
A100: ='01_Preço'!$A$42 | B100: ='01_Preço'!$A$55 | C100: ='01_Preço'!B$55 | D100: Equipamentos e materiais | E100: 30 | F100: =VLOOKUP(E100,'Tabela de mês'!$A$1:$B$70,2,TRUE) | G100: 029-MAT | H100: ERZEG | I100: INSIGHT | L100: Entrega em campo de painel completo contendo o Registrador Digital de Perturbações (RDP) | M100: =O100/$N$66 | O100: 1185036.9 | P100: 21 | Q100: 800000
A101: ='01_Preço'!$A$42 | B101: ='01_Preço'!$A$57 | C101: ='01_Preço'!B57 | D101: Equipamentos e materiais | L101: ='01_Preço'!E57 | M101: =O101/$N$66 | O101: =SUM(O102:O105) | P101: 14
A102: ='01_Preço'!$A$42 | B102: ='01_Preço'!$A$57 | C102: ='01_Preço'!$B$57 | D102: Equipamentos e materiais | E102: 30 | F102: =VLOOKUP(E102,'Tabela de mês'!$A$1:$B$70,2,TRUE) | G102: 028-MAT B | H102: ERZEG | I102: INSIGHT | L102: Entrega completa na obra da rede de dados para aquisição de oscilografia e parametrização de relés para comunicação entre os relés de proteção e SDSC do Sistemas de Proteção da 1ª UF | M102: =O102/$O$101 | O102: 50848.09 | P102: 30 | Q102: 10000
...

Sheet 04_TOTALIZADORA (2)
A1: ='01_Preço'!A1
A2: TABELA TOTALIZADORA DOS PREÇOS DOS MATERIAIS E SERVIÇOS DA REFORMA E MODERNIZAÇÃO DA UHE SALTO GRANDE E MODERNIZAÇÃO E DIGITALIZAÇÃO DA SE UHE SALTO GRANDE – ATIVOS CEMIG D
A4: OBJETO: CONTRATAÇÃO DE SERVIÇOS PARA EXECUÇÃO DA MODERNIZAÇÃO DA UHE SALTO GRANDE | O4: =_xlfn.CONCAT('01_Preço'!M4," ",'01_Preço'!O4) | Q4: BASE ECONÔMICA TRIBUTÁRIA: | R4: ='01_Preço'!V4
A5: NOME EMPRESA PROPONENTE: | D5: ='01_Preço'!C5 | O5: Nº CNPJ: | P5: ='01_Preço'!L5 | Q5: Nº INSC ESTADUAL: | R5: ='01_Preço'!Q5
A6: NOME REPRESENTANTE LEGAL: | D6: ='01_Preço'!C6 | O6: Nº CPF: | P6: ='01_Preço'!L6 | Q6: Nº IDENTIDADE: | R6: ='01_Preço'!Q6
A7: ASSINATURA DO REPRESENTANTE LEGAL DA EMPRESA: | E7: ='01_Preço'!E7 | Q7: DATA DE EMISSÃO: | R7: ='01_Preço'!V5
A9: % DA ANTECIPAÇÃO SOLICITADA | D9: 0.05 | E9: VALOR ANTECIPAÇÃO SOLICITADA | M9: =D9*Q9 | O9: PREÇO GLOBAL | Q9: =O83
A12: MÊS | B12: ESCOPO CEMIG GT | D12: ESCOPO CEMIG D | F12: VALOR ACUMULADO (com todos os impostos) (R$) | G12: INSIGHT | H12: DESEMBOLSO ACUMULADO VALOR ACUMULADO | I12: FAT. DIRETO | J12: DESEMBOLSO TOTAL ACUMULADO VALOR ACUMULADO | K12: FATURAMENTO REALIZADO | L12: FATURAMENTO ACUMULADO | M12: PREÇO DA REFORMA E MODERNIZAÇÃO DA UHE SALTO GRANDE | Q12: =C84
B13: EVENTOS NO MÊS | C13: VALOR TOTAL MENSAL (com todos os impostos) (R$) | D13: EVENTOS NO MÊS | E13: VALOR TOTAL MENSAL (com todos os impostos) (R$) | G13: DESEMBOLSO MENSAL | I13: DESEMBOLSO MENSAL | M13: PREÇO DA MODERNIZAÇÃO E DIGITALIZAÇÃO DA SE UHE SALTO GRANDE - ATIVO CEMIG D | Q13: =E84
A14: 1 | B14: =SUM(COUNTIF('03_Eventos_pagamentos'!$E$11:$E$697,'04_TOTALIZADORA (2)'!A14)+COUNTIF('03_Eventos_pagamentos'!$E$766:$E$836,'04_TOTALIZADORA (2)'!A14)) | C14: =SUMIF('03_Eventos_pagamentos'!$E$11:$E$699,A14,'03_Eventos_pagamentos'!$O$11:$O$697)+SUMIF('03_Eventos_pagamentos'!$E$766:$E$836,A14,'03_Eventos_pagamentos'!$O$766:$O$836) | D14: =COUNTIF('03_Eventos_pagamentos'!$E$702:$E$763,'04_TOTALIZADORA (2)'!A14) | E14: =SUMIF('03_Eventos_pagamentos'!$E$702:$E$763,A14,'03_Eventos_pagamentos'!$O$702:$O$763) | F14: =C14+E14 | G14: =SUMIF('03_Eventos_pagamentos'!$P$11:$P$843,A15,'03_Eventos_pagamentos'!$Q$11:$Q$843) | I14: =SUMIFS( '03_Eventos_pagamentos'!$O$11:$O$843,'03_Eventos_pagamentos'!$E$11:$E$843,A14,'03_Eventos_pagamentos'!$I$11:$I$843,"FAT. DIRETO") | J14: =H14+I14 | K14: 0 | L14: =K14
A15: 2 à 15 | B15: =SUM(COUNTIF('03_Eventos_pagamentos'!$E$11:$E$697,'04_TOTALIZADORA (2)'!A15)+COUNTIF('03_Eventos_pagamentos'!$E$766:$E$836,'04_TOTALIZADORA (2)'!A15)) | C15: =SUMIF('03_Eventos_pagamentos'!$E$11:$E$699,A15,'03_Eventos_pagamentos'!$O$11:$O$697)+SUMIF('03_Eventos_pagamentos'!$E$766:$E$836,A15,'03_Eventos_pagamentos'!$O$766:$O$836) | D15: =COUNTIF('03_Eventos_pagamentos'!$E$702:$E$763,'04_TOTALIZADORA (2)'!A15) | E15: =SUMIF('03_Eventos_pagamentos'!$E$702:$E$763,A15,'03_Eventos_pagamentos'!$O$702:$O$763) | F15: =C15+E15+F14 | G15: =SUMIF('03_Eventos_pagamentos'!$P$11:$P$843,A16,'03_Eventos_pagamentos'!$Q$11:$Q$843) | H15: =G15+H14 | I15: =SUMIFS( '03_Eventos_pagamentos'!$O$11:$O$843,'03_Eventos_pagamentos'!$E$11:$E$843,A15,'03_Eventos_pagamentos'!$I$11:$I$843,"FAT. DIRETO") | J15: =G15+I15+J14 | K15: =R83 | L15: =K15+L14
A16: 3 | B16: =SUM(COUNTIF('03_Eventos_pagamentos'!$E$11:$E$697,'04_TOTALIZADORA (2)'!A16)+COUNTIF('03_Eventos_pagamentos'!$E$766:$E$836,'04_TOTALIZADORA (2)'!A16)) | C16: =SUMIF('03_Eventos_pagamentos'!$E$11:$E$699,A16,'03_Eventos_pagamentos'!$O$11:$O$697)+SUMIF('03_Eventos_pagamentos'!$E$766:$E$836,A16,'03_Eventos_pagamentos'!$O$766:$O$836) | D16: =COUNTIF('03_Eventos_pagamentos'!$E$702:$E$763,'04_TOTALIZADORA (2)'!A16) | E16: =SUMIF('03_Eventos_pagamentos'!$E$702:$E$763,A16,'03_Eventos_pagamentos'!$O$702:$O$763) | F16: =C16+E16+F15 | G16: =SUMIF('03_Eventos_pagamentos'!$P$11:$P$843,A17,'03_Eventos_pagamentos'!$Q$11:$Q$843) | H16: =G16+H15 | I16: =SUMIFS( '03_Eventos_pagamentos'!$O$11:$O$843,'03_Eventos_pagamentos'!$E$11:$E$843,A16,'03_Eventos_pagamentos'!$I$11:$I$843,"FAT. DIRETO") | J16: =G16+I16+J15 | L16: =K16+L15
A17: 4 | B17: =SUM(COUNTIF('03_Eventos_pagamentos'!$E$11:$E$697,'04_TOTALIZADORA (2)'!A17)+COUNTIF('03_Eventos_pagamentos'!$E$766:$E$836,'04_TOTALIZADORA (2)'!A17)) | C17: =SUMIF('03_Eventos_pagamentos'!$E$11:$E$699,A17,'03_Eventos_pagamentos'!$O$11:$O$697)+SUMIF('03_Eventos_pagamentos'!$E$766:$E$836,A17,'03_Eventos_pagamentos'!$O$766:$O$836) | D17: =COUNTIF('03_Eventos_pagamentos'!$E$702:$E$763,'04_TOTALIZADORA (2)'!A17) | E17: =SUMIF('03_Eventos_pagamentos'!$E$702:$E$763,A17,'03_Eventos_pagamentos'!$O$702:$O$763) | F17: =C17+E17+F16 | G17: =SUMIF('03_Eventos_pagamentos'!$P$11:$P$843,A18,'03_Eventos_pagamentos'!$Q$11:$Q$843) | H17: =G17+H16 | I17: =SUMIFS( '03_Eventos_pagamentos'!$O$11:$O$843,'03_Eventos_pagamentos'!$E$11:$E$843,A17,'03_Eventos_pagamentos'!$I$11:$I$843,"FAT. DIRETO") | J17: =G17+I17+J16 | L17: =K17+L16
A18: 5 | B18: =SUM(COUNTIF('03_Eventos_pagamentos'!$E$11:$E$697,'04_TOTALIZADORA (2)'!A18)+COUNTIF('03_Eventos_pagamentos'!$E$766:$E$836,'04_TOTALIZADORA (2)'!A18)) | C18: =SUMIF('03_Eventos_pagamentos'!$E$11:$E$699,A18,'03_Eventos_pagamentos'!$O$11:$O$697)+SUMIF('03_Eventos_pagamentos'!$E$766:$E$836,A18,'03_Eventos_pagamentos'!$O$766:$O$836) | D18: =COUNTIF('03_Eventos_pagamentos'!$E$702:$E$763,'04_TOTALIZADORA (2)'!A18) | E18: =SUMIF('03_Eventos_pagamentos'!$E$702:$E$763,A18,'03_Eventos_pagamentos'!$O$702:$O$763) | F18: =C18+E18+F17 | G18: =SUMIF('03_Eventos_pagamentos'!$P$11:$P$843,A19,'03_Eventos_pagamentos'!$Q$11:$Q$843) | H18: =G18+H17 | I18: =SUMIFS( '03_Eventos_pagamentos'!$O$11:$O$843,'03_Eventos_pagamentos'!$E$11:$E$843,A18,'03_Eventos_pagamentos'!$I$11:$I$843,"FAT. DIRETO") | J18: =G18+I18+J17 | L18: =K18+L17
A19: 6 | B19: =SUM(COUNTIF('03_Eventos_pagamentos'!$E$11:$E$697,'04_TOTALIZADORA (2)'!A19)+COUNTIF('03_Eventos_pagamentos'!$E$766:$E$836,'04_TOTALIZADORA (2)'!A19)) | C19: =SUMIF('03_Eventos_pagamentos'!$E$11:$E$699,A19,'03_Eventos_pagamentos'!$O$11:$O$697)+SUMIF('03_Eventos_pagamentos'!$E$766:$E$836,A19,'03_Eventos_pagamentos'!$O$766:$O$836) | D19: =COUNTIF('03_Eventos_pagamentos'!$E$702:$E$763,'04_TOTALIZADORA (2)'!A19) | E19: =SUMIF('03_Eventos_pagamentos'!$E$702:$E$763,A19,'03_Eventos_pagamentos'!$O$702:$O$763) | F19: =C19+E19+F18 | G19: =SUMIF('03_Eventos_pagamentos'!$P$11:$P$843,A20,'03_Eventos_pagamentos'!$Q$11:$Q$843) | H19: =G19+H18 | I19: =SUMIFS( '03_Eventos_pagamentos'!$O$11:$O$843,'03_Eventos_pagamentos'!$E$11:$E$843,A19,'03_Eventos_pagamentos'!$I$11:$I$843,"FAT. DIRETO") | J19: =G19+I19+J18 | L19: =K19+L18
A20: 7 | B20: =SUM(COUNTIF('03_Eventos_pagamentos'!$E$11:$E$697,'04_TOTALIZADORA (2)'!A20)+COUNTIF('03_Eventos_pagamentos'!$E$766:$E$836,'04_TOTALIZADORA (2)'!A20)) | C20: =SUMIF('03_Eventos_pagamentos'!$E$11:$E$699,A20,'03_Eventos_pagamentos'!$O$11:$O$697)+SUMIF('03_Eventos_pagamentos'!$E$766:$E$836,A20,'03_Eventos_pagamentos'!$O$766:$O$836) | D20: =COUNTIF('03_Eventos_pagamentos'!$E$702:$E$763,'04_TOTALIZADORA (2)'!A20) | E20: =SUMIF('03_Eventos_pagamentos'!$E$702:$E$763,A20,'03_Eventos_pagamentos'!$O$702:$O$763) | F20: =C20+E20+F19 | G20: =SUMIF('03_Eventos_pagamentos'!$P$11:$P$843,A21,'03_Eventos_pagamentos'!$Q$11:$Q$843) | H20: =G20+H19 | I20: =SUMIFS( '03_Eventos_pagamentos'!$O$11:$O$843,'03_Eventos_pagamentos'!$E$11:$E$843,A20,'03_Eventos_pagamentos'!$I$11:$I$843,"FAT. DIRETO") | J20: =G20+I20+J19 | L20: =K20+L19
A21: 8 | B21: =SUM(COUNTIF('03_Eventos_pagamentos'!$E$11:$E$697,'04_TOTALIZADORA (2)'!A21)+COUNTIF('03_Eventos_pagamentos'!$E$766:$E$836,'04_TOTALIZADORA (2)'!A21)) | C21: =SUMIF('03_Eventos_pagamentos'!$E$11:$E$699,A21,'03_Eventos_pagamentos'!$O$11:$O$697)+SUMIF('03_Eventos_pagamentos'!$E$766:$E$836,A21,'03_Eventos_pagamentos'!$O$766:$O$836) | D21: =COUNTIF('03_Eventos_pagamentos'!$E$702:$E$763,'04_TOTALIZADORA (2)'!A21) | E21: =SUMIF('03_Eventos_pagamentos'!$E$702:$E$763,A21,'03_Eventos_pagamentos'!$O$702:$O$763) | F21: =C21+E21+F20 | G21: =SUMIF('03_Eventos_pagamentos'!$P$11:$P$843,A22,'03_Eventos_pagamentos'!$Q$11:$Q$843) | H21: =G21+H20 | I21: =SUMIFS( '03_Eventos_pagamentos'!$O$11:$O$843,'03_Eventos_pagamentos'!$E$11:$E$843,A21,'03_Eventos_pagamentos'!$I$11:$I$843,"FAT. DIRETO") | J21: =G21+I21+J20 | L21: =K21+L20
A22: 9 | B22: =SUM(COUNTIF('03_Eventos_pagamentos'!$E$11:$E$697,'04_TOTALIZADORA (2)'!A22)+COUNTIF('03_Eventos_pagamentos'!$E$766:$E$836,'04_TOTALIZADORA (2)'!A22)) | C22: =SUMIF('03_Eventos_pagamentos'!$E$11:$E$699,A22,'03_Eventos_pagamentos'!$O$11:$O$697)+SUMIF('03_Eventos_pagamentos'!$E$766:$E$836,A22,'03_Eventos_pagamentos'!$O$766:$O$836) | D22: =COUNTIF('03_Eventos_pagamentos'!$E$702:$E$763,'04_TOTALIZADORA (2)'!A22) | E22: =SUMIF('03_Eventos_pagamentos'!$E$702:$E$763,A22,'03_Eventos_pagamentos'!$O$702:$O$763) | F22: =C22+E22+F21 | G22: =SUMIF('03_Eventos_pagamentos'!$P$11:$P$843,A23,'03_Eventos_pagamentos'!$Q$11:$Q$843) | H22: =G22+H21 | I22: =SUMIFS( '03_Eventos_pagamentos'!$O$11:$O$843,'03_Eventos_pagamentos'!$E$11:$E$843,A22,'03_Eventos_pagamentos'!$I$11:$I$843,"FAT. DIRETO") | J22: =G22+I22+J21 | L22: =K22+L21
A23: 10 | B23: =SUM(COUNTIF('03_Eventos_pagamentos'!$E$11:$E$697,'04_TOTALIZADORA (2)'!A23)+COUNTIF('03_Eventos_pagamentos'!$E$766:$E$836,'04_TOTALIZADORA (2)'!A23)) | C23: =SUMIF('03_Eventos_pagamentos'!$E$11:$E$699,A23,'03_Eventos_pagamentos'!$O$11:$O$697)+SUMIF('03_Eventos_pagamentos'!$E$766:$E$836,A23,'03_Eventos_pagamentos'!$O$766:$O$836) | D23: =COUNTIF('03_Eventos_pagamentos'!$E$702:$E$763,'04_TOTALIZADORA (2)'!A23) | E23: =SUMIF('03_Eventos_pagamentos'!$E$702:$E$763,A23,'03_Eventos_pagamentos'!$O$702:$O$763) | F23: =C23+E23+F22 | G23: =SUMIF('03_Eventos_pagamentos'!$P$11:$P$843,A24,'03_Eventos_pagamentos'!$Q$11:$Q$843) | H23: =G23+H22 | I23: =SUMIFS( '03_Eventos_pagamentos'!$O$11:$O$843,'03_Eventos_pagamentos'!$E$11:$E$843,A23,'03_Eventos_pagamentos'!$I$11:$I$843,"FAT. DIRETO") | J23: =G23+I23+J22 | L23: =K23+L22
A24: 11 | B24: =SUM(COUNTIF('03_Eventos_pagamentos'!$E$11:$E$697,'04_TOTALIZADORA (2)'!A24)+COUNTIF('03_Eventos_pagamentos'!$E$766:$E$836,'04_TOTALIZADORA (2)'!A24)) | C24: =SUMIF('03_Eventos_pagamentos'!$E$11:$E$699,A24,'03_Eventos_pagamentos'!$O$11:$O$697)+SUMIF('03_Eventos_pagamentos'!$E$766:$E$836,A24,'03_Eventos_pagamentos'!$O$766:$O$836) | D24: =COUNTIF('03_Eventos_pagamentos'!$E$702:$E$763,'04_TOTALIZADORA (2)'!A24) | E24: =SUMIF('03_Eventos_pagamentos'!$E$702:$E$763,A24,'03_Eventos_pagamentos'!$O$702:$O$763) | F24: =C24+E24+F23 | G24: =SUMIF('03_Eventos_pagamentos'!$P$11:$P$843,A25,'03_Eventos_pagamentos'!$Q$11:$Q$843) | H24: =G24+H23 | I24: =SUMIFS( '03_Eventos_pagamentos'!$O$11:$O$843,'03_Eventos_pagamentos'!$E$11:$E$843,A24,'03_Eventos_pagamentos'!$I$11:$I$843,"FAT. DIRETO") | J24: =G24+I24+J23 | L24: =K24+L23
A25: 12 | B25: =SUM(COUNTIF('03_Eventos_pagamentos'!$E$11:$E$697,'04_TOTALIZADORA (2)'!A25)+COUNTIF('03_Eventos_pagamentos'!$E$766:$E$836,'04_TOTALIZADORA (2)'!A25)) | C25: =SUMIF('03_Eventos_pagamentos'!$E$11:$E$699,A25,'03_Eventos_pagamentos'!$O$11:$O$697)+SUMIF('03_Eventos_pagamentos'!$E$766:$E$836,A25,'03_Eventos_pagamentos'!$O$766:$O$836) | D25: =COUNTIF('03_Eventos_pagamentos'!$E$702:$E$763,'04_TOTALIZADORA (2)'!A25) | E25: =SUMIF('03_Eventos_pagamentos'!$E$702:$E$763,A25,'03_Eventos_pagamentos'!$O$702:$O$763) | F25: =C25+E25+F24 | G25: =SUMIF('03_Eventos_pagamentos'!$P$11:$P$843,A26,'03_Eventos_pagamentos'!$Q$11:$Q$843) | H25: =G25+H24 | I25: =SUMIFS( '03_Eventos_pagamentos'!$O$11:$O$843,'03_Eventos_pagamentos'!$E$11:$E$843,A25,'03_Eventos_pagamentos'!$I$11:$I$843,"FAT. DIRETO") | J25: =G25+I25+J24 | L25: =K25+L24
A26: 13 | B26: =SUM(COUNTIF('03_Eventos_pagamentos'!$E$11:$E$697,'04_TOTALIZADORA (2)'!A26)+COUNTIF('03_Eventos_pagamentos'!$E$766:$E$836,'04_TOTALIZADORA (2)'!A26)) | C26: =SUMIF('03_Eventos_pagamentos'!$E$11:$E$699,A26,'03_Eventos_pagamentos'!$O$11:$O$697)+SUMIF('03_Eventos_pagamentos'!$E$766:$E$836,A26,'03_Eventos_pagamentos'!$O$766:$O$836) | D26: =COUNTIF('03_Eventos_pagamentos'!$E$702:$E$763,'04_TOTALIZADORA (2)'!A26) | E26: =SUMIF('03_Eventos_pagamentos'!$E$702:$E$763,A26,'03_Eventos_pagamentos'!$O$702:$O$763) | F26: =C26+E26+F25 | G26: =SUMIF('03_Eventos_pagamentos'!$P$11:$P$843,A27,'03_Eventos_pagamentos'!$Q$11:$Q$843) | H26: =G26+H25 | I26: =SUMIFS( '03_Eventos_pagamentos'!$O$11:$O$843,'03_Eventos_pagamentos'!$E$11:$E$843,A26,'03_Eventos_pagamentos'!$I$11:$I$843,"FAT. DIRETO") | J26: =G26+I26+J25 | L26: =K26+L25
A27: 14 | B27: =SUM(COUNTIF('03_Eventos_pagamentos'!$E$11:$E$697,'04_TOTALIZADORA (2)'!A27)+COUNTIF('03_Eventos_pagamentos'!$E$766:$E$836,'04_TOTALIZADORA (2)'!A27)) | C27: =SUMIF('03_Eventos_pagamentos'!$E$11:$E$699,A27,'03_Eventos_pagamentos'!$O$11:$O$697)+SUMIF('03_Eventos_pagamentos'!$E$766:$E$836,A27,'03_Eventos_pagamentos'!$O$766:$O$836) | D27: =COUNTIF('03_Eventos_pagamentos'!$E$702:$E$763,'04_TOTALIZADORA (2)'!A27) | E27: =SUMIF('03_Eventos_pagamentos'!$E$702:$E$763,A27,'03_Eventos_pagamentos'!$O$702:$O$763) | F27: =C27+E27+F26 | G27: =SUMIF('03_Eventos_pagamentos'!$P$11:$P$843,A28,'03_Eventos_pagamentos'!$Q$11:$Q$843) | H27: =G27+H26 | I27: =SUMIFS( '03_Eventos_pagamentos'!$O$11:$O$843,'03_Eventos_pagamentos'!$E$11:$E$843,A27,'03_Eventos_pagamentos'!$I$11:$I$843,"FAT. DIRETO") | J27: =G27+I27+J26 | L27: =K27+L26
A28: 15 | B28: =SUM(COUNTIF('03_Eventos_pagamentos'!$E$11:$E$697,'04_TOTALIZADORA (2)'!A28)+COUNTIF('03_Eventos_pagamentos'!$E$766:$E$836,'04_TOTALIZADORA (2)'!A28)) | C28: =SUMIF('03_Eventos_pagamentos'!$E$11:$E$699,A28,'03_Eventos_pagamentos'!$O$11:$O$697)+SUMIF('03_Eventos_pagamentos'!$E$766:$E$836,A28,'03_Eventos_pagamentos'!$O$766:$O$836) | D28: =COUNTIF('03_Eventos_pagamentos'!$E$702:$E$763,'04_TOTALIZADORA (2)'!A28) | E28: =SUMIF('03_Eventos_pagamentos'!$E$702:$E$763,A28,'03_Eventos_pagamentos'!$O$702:$O$763) | F28: =C28+E28+F27 | G28: =SUMIF('03_Eventos_pagamentos'!$P$11:$P$843,A29,'03_Eventos_pagamentos'!$Q$11:$Q$843) | H28: =G28+H27 | I28: =SUMIFS( '03_Eventos_pagamentos'!$O$11:$O$843,'03_Eventos_pagamentos'!$E$11:$E$843,A28,'03_Eventos_pagamentos'!$I$11:$I$843,"FAT. DIRETO") | J28: =G28+I28+J27 | K28: =0.85*412245.2 | L28: =K28+L27
A29: 16 | B29: =SUM(COUNTIF('03_Eventos_pagamentos'!$E$11:$E$697,'04_TOTALIZADORA (2)'!A29)+COUNTIF('03_Eventos_pagamentos'!$E$766:$E$836,'04_TOTALIZADORA (2)'!A29)) | C29: =SUMIF('03_Eventos_pagamentos'!$E$11:$E$699,A29,'03_Eventos_pagamentos'!$O$11:$O$697)+SUMIF('03_Eventos_pagamentos'!$E$766:$E$836,A29,'03_Eventos_pagamentos'!$O$766:$O$836) | D29: =COUNTIF('03_Eventos_pagamentos'!$E$702:$E$763,'04_TOTALIZADORA (2)'!A29) | E29: =SUMIF('03_Eventos_pagamentos'!$E$702:$E$763,A29,'03_Eventos_pagamentos'!$O$702:$O$763) | F29: =C29+E29+F28 | G29: =SUMIF('03_Eventos_pagamentos'!$P$11:$P$843,A30,'03_Eventos_pagamentos'!$Q$11:$Q$843) | H29: =G29+H28 | I29: =SUMIFS( '03_Eventos_pagamentos'!$O$11:$O$843,'03_Eventos_pagamentos'!$E$11:$E$843,A29,'03_Eventos_pagamentos'!$I$11:$I$843,"FAT. DIRETO") | J29: =G29+I29+J28 | L29: =K29+L28
A30: 17 | B30: =SUM(COUNTIF('03_Eventos_pagamentos'!$E$11:$E$697,'04_TOTALIZADORA (2)'!A30)+COUNTIF('03_Eventos_pagamentos'!$E$766:$E$836,'04_TOTALIZADORA (2)'!A30)) | C30: =SUMIF('03_Eventos_pagamentos'!$E$11:$E$699,A30,'03_Eventos_pagamentos'!$O$11:$O$697)+SUMIF('03_Eventos_pagamentos'!$E$766:$E$836,A30,'03_Eventos_pagamentos'!$O$766:$O$836) | D30: =COUNTIF('03_Eventos_pagamentos'!$E$702:$E$763,'04_TOTALIZADORA (2)'!A30) | E30: =SUMIF('03_Eventos_pagamentos'!$E$702:$E$763,A30,'03_Eventos_pagamentos'!$O$702:$O$763) | F30: =C30+E30+F29 | G30: =SUMIF('03_Eventos_pagamentos'!$P$11:$P$843,A31,'03_Eventos_pagamentos'!$Q$11:$Q$843) | H30: =G30+H29 | I30: =SUMIFS( '03_Eventos_pagamentos'!$O$11:$O$843,'03_Eventos_pagamentos'!$E$11:$E$843,A30,'03_Eventos_pagamentos'!$I$11:$I$843,"FAT. DIRETO") | J30: =G30+I30+J29 | K30: =0.85*800224.32 | L30: =K30+L29
A31: 18 | B31: =SUM(COUNTIF('03_Eventos_pagamentos'!$E$11:$E$697,'04_TOTALIZADORA (2)'!A31)+COUNTIF('03_Eventos_pagamentos'!$E$766:$E$836,'04_TOTALIZADORA (2)'!A31)) | C31: =SUMIF('03_Eventos_pagamentos'!$E$11:$E$699,A31,'03_Eventos_pagamentos'!$O$11:$O$697)+SUMIF('03_Eventos_pagamentos'!$E$766:$E$836,A31,'03_Eventos_pagamentos'!$O$766:$O$836) | D31: =COUNTIF('03_Eventos_pagamentos'!$E$702:$E$763,'04_TOTALIZADORA (2)'!A31) | E31: =SUMIF('03_Eventos_pagamentos'!$E$702:$E$763,A31,'03_Eventos_pagamentos'!$O$702:$O$763) | F31: =C31+E31+F30 | G31: =SUMIF('03_Eventos_pagamentos'!$P$11:$P$843,A32,'03_Eventos_pagamentos'!$Q$11:$Q$843) | H31: =G31+H30 | I31: =SUMIFS( '03_Eventos_pagamentos'!$O$11:$O$843,'03_Eventos_pagamentos'!$E$11:$E$843,A31,'03_Eventos_pagamentos'!$I$11:$I$843,"FAT. DIRETO") | J31: =G31+I31+J30 | L31: =K31+L30
A32: 19 | B32: =SUM(COUNTIF('03_Eventos_pagamentos'!$E$11:$E$697,'04_TOTALIZADORA (2)'!A32)+COUNTIF('03_Eventos_pagamentos'!$E$766:$E$836,'04_TOTALIZADORA (2)'!A32)) | C32: =SUMIF('03_Eventos_pagamentos'!$E$11:$E$699,A32,'03_Eventos_pagamentos'!$O$11:$O$697)+SUMIF('03_Eventos_pagamentos'!$E$766:$E$836,A32,'03_Eventos_pagamentos'!$O$766:$O$836) | D32: =COUNTIF('03_Eventos_pagamentos'!$E$702:$E$763,'04_TOTALIZADORA (2)'!A32) | E32: =SUMIF('03_Eventos_pagamentos'!$E$702:$E$763,A32,'03_Eventos_pagamentos'!$O$702:$O$763) | F32: =C32+E32+F31 | G32: =SUMIF('03_Eventos_pagamentos'!$P$11:$P$843,A33,'03_Eventos_pagamentos'!$Q$11:$Q$843) | H32: =G32+H31 | I32: =SUMIFS( '03_Eventos_pagamentos'!$O$11:$O$843,'03_Eventos_pagamentos'!$E$11:$E$843,A32,'03_Eventos_pagamentos'!$I$11:$I$843,"FAT. DIRETO") | J32: =G32+I32+J31 | L32: =K32+L31
A33: 20 | B33: =SUM(COUNTIF('03_Eventos_pagamentos'!$E$11:$E$697,'04_TOTALIZADORA (2)'!A33)+COUNTIF('03_Eventos_pagamentos'!$E$766:$E$836,'04_TOTALIZADORA (2)'!A33)) | C33: =SUMIF('03_Eventos_pagamentos'!$E$11:$E$699,A33,'03_Eventos_pagamentos'!$O$11:$O$697)+SUMIF('03_Eventos_pagamentos'!$E$766:$E$836,A33,'03_Eventos_pagamentos'!$O$766:$O$836) | D33: =COUNTIF('03_Eventos_pagamentos'!$E$702:$E$763,'04_TOTALIZADORA (2)'!A33) | E33: =SUMIF('03_Eventos_pagamentos'!$E$702:$E$763,A33,'03_Eventos_pagamentos'!$O$702:$O$763) | F33: =C33+E33+F32 | G33: =SUMIF('03_Eventos_pagamentos'!$P$11:$P$843,A34,'03_Eventos_pagamentos'!$Q$11:$Q$843) | H33: =G33+H32 | I33: =SUMIFS( '03_Eventos_pagamentos'!$O$11:$O$843,'03_Eventos_pagamentos'!$E$11:$E$843,A33,'03_Eventos_pagamentos'!$I$11:$I$843,"FAT. DIRETO") | J33: =G33+I33+J32 | L33: =K33+L32
A34: 21 | B34: =SUM(COUNTIF('03_Eventos_pagamentos'!$E$11:$E$697,'04_TOTALIZADORA (2)'!A34)+COUNTIF('03_Eventos_pagamentos'!$E$766:$E$836,'04_TOTALIZADORA (2)'!A34)) | C34: =SUMIF('03_Eventos_pagamentos'!$E$11:$E$699,A34,'03_Eventos_pagamentos'!$O$11:$O$697)+SUMIF('03_Eventos_pagamentos'!$E$766:$E$836,A34,'03_Eventos_pagamentos'!$O$766:$O$836) | D34: =COUNTIF('03_Eventos_pagamentos'!$E$702:$E$763,'04_TOTALIZADORA (2)'!A34) | E34: =SUMIF('03_Eventos_pagamentos'!$E$702:$E$763,A34,'03_Eventos_pagamentos'!$O$702:$O$763) | F34: =C34+E34+F33 | G34: =SUMIF('03_Eventos_pagamentos'!$P$11:$P$843,A35,'03_Eventos_pagamentos'!$Q$11:$Q$843) | H34: =G34+H33 | I34: =SUMIFS( '03_Eventos_pagamentos'!$O$11:$O$843,'03_Eventos_pagamentos'!$E$11:$E$843,A34,'03_Eventos_pagamentos'!$I$11:$I$843,"FAT. DIRETO") | J34: =G34+I34+J33 | L34: =K34+L33
A35: 22 | B35: =SUM(COUNTIF('03_Eventos_pagamentos'!$E$11:$E$697,'04_TOTALIZADORA (2)'!A35)+COUNTIF('03_Eventos_pagamentos'!$E$766:$E$836,'04_TOTALIZADORA (2)'!A35)) | C35: =SUMIF('03_Eventos_pagamentos'!$E$11:$E$699,A35,'03_Eventos_pagamentos'!$O$11:$O$697)+SUMIF('03_Eventos_pagamentos'!$E$766:$E$836,A35,'03_Eventos_pagamentos'!$O$766:$O$836) | D35: =COUNTIF('03_Eventos_pagamentos'!$E$702:$E$763,'04_TOTALIZADORA (2)'!A35) | E35: =SUMIF('03_Eventos_pagamentos'!$E$702:$E$763,A35,'03_Eventos_pagamentos'!$O$702:$O$763) | F35: =C35+E35+F34 | G35: =SUMIF('03_Eventos_pagamentos'!$P$11:$P$843,A36,'03_Eventos_pagamentos'!$Q$11:$Q$843) | H35: =G35+H34 | I35: =SUMIFS( '03_Eventos_pagamentos'!$O$11:$O$843,'03_Eventos_pagamentos'!$E$11:$E$843,A35,'03_Eventos_pagamentos'!$I$11:$I$843,"FAT. DIRETO") | J35: =G35+I35+J34 | L35: =K35+L34
A36: 23 | B36: =SUM(COUNTIF('03_Eventos_pagamentos'!$E$11:$E$697,'04_TOTALIZADORA (2)'!A36)+COUNTIF('03_Eventos_pagamentos'!$E$766:$E$836,'04_TOTALIZADORA (2)'!A36)) | C36: =SUMIF('03_Eventos_pagamentos'!$E$11:$E$699,A36,'03_Eventos_pagamentos'!$O$11:$O$697)+SUMIF('03_Eventos_pagamentos'!$E$766:$E$836,A36,'03_Eventos_pagamentos'!$O$766:$O$836) | D36: =COUNTIF('03_Eventos_pagamentos'!$E$702:$E$763,'04_TOTALIZADORA (2)'!A36) | E36: =SUMIF('03_Eventos_pagamentos'!$E$702:$E$763,A36,'03_Eventos_pagamentos'!$O$702:$O$763) | F36: =C36+E36+F35 | G36: =SUMIF('03_Eventos_pagamentos'!$P$11:$P$843,A37,'03_Eventos_pagamentos'!$Q$11:$Q$843) | H36: =G36+H35 | I36: =SUMIFS( '03_Eventos_pagamentos'!$O$11:$O$843,'03_Eventos_pagamentos'!$E$11:$E$843,A36,'03_Eventos_pagamentos'!$I$11:$I$843,"FAT. DIRETO") | J36: =G36+I36+J35 | L36: =K36+L35
A37: 24 | B37: =SUM(COUNTIF('03_Eventos_pagamentos'!$E$11:$E$697,'04_TOTALIZADORA (2)'!A37)+COUNTIF('03_Eventos_pagamentos'!$E$766:$E$836,'04_TOTALIZADORA (2)'!A37)) | C37: =SUMIF('03_Eventos_pagamentos'!$E$11:$E$699,A37,'03_Eventos_pagamentos'!$O$11:$O$697)+SUMIF('03_Eventos_pagamentos'!$E$766:$E$836,A37,'03_Eventos_pagamentos'!$O$766:$O$836) | D37: =COUNTIF('03_Eventos_pagamentos'!$E$702:$E$763,'04_TOTALIZADORA (2)'!A37) | E37: =SUMIF('03_Eventos_pagamentos'!$E$702:$E$763,A37,'03_Eventos_pagamentos'!$O$702:$O$763) | F37: =C37+E37+F36 | G37: =SUMIF('03_Eventos_pagamentos'!$P$11:$P$843,A38,'03_Eventos_pagamentos'!$Q$11:$Q$843) | H37: =G37+H36 | I37: =SUMIFS( '03_Eventos_pagamentos'!$O$11:$O$843,'03_Eventos_pagamentos'!$E$11:$E$843,A37,'03_Eventos_pagamentos'!$I$11:$I$843,"FAT. DIRETO") | J37: =G37+I37+J36 | L37: =K37+L36
A38: 25 | B38: =SUM(COUNTIF('03_Eventos_pagamentos'!$E$11:$E$697,'04_TOTALIZADORA (2)'!A38)+COUNTIF('03_Eventos_pagamentos'!$E$766:$E$836,'04_TOTALIZADORA (2)'!A38)) | C38: =SUMIF('03_Eventos_pagamentos'!$E$11:$E$699,A38,'03_Eventos_pagamentos'!$O$11:$O$697)+SUMIF('03_Eventos_pagamentos'!$E$766:$E$836,A38,'03_Eventos_pagamentos'!$O$766:$O$836) | D38: =COUNTIF('03_Eventos_pagamentos'!$E$702:$E$763,'04_TOTALIZADORA (2)'!A38) | E38: =SUMIF('03_Eventos_pagamentos'!$E$702:$E$763,A38,'03_Eventos_pagamentos'!$O$702:$O$763) | F38: =C38+E38+F37 | G38: =SUMIF('03_Eventos_pagamentos'!$P$11:$P$843,A39,'03_Eventos_pagamentos'!$Q$11:$Q$843) | H38: =G38+H37 | I38: =SUMIFS( '03_Eventos_pagamentos'!$O$11:$O$843,'03_Eventos_pagamentos'!$E$11:$E$843,A38,'03_Eventos_pagamentos'!$I$11:$I$843,"FAT. DIRETO") | J38: =G38+I38+J37 | L38: =K38+L37
A39: 26 | B39: =SUM(COUNTIF('03_Eventos_pagamentos'!$E$11:$E$697,'04_TOTALIZADORA (2)'!A39)+COUNTIF('03_Eventos_pagamentos'!$E$766:$E$836,'04_TOTALIZADORA (2)'!A39)) | C39: =SUMIF('03_Eventos_pagamentos'!$E$11:$E$699,A39,'03_Eventos_pagamentos'!$O$11:$O$697)+SUMIF('03_Eventos_pagamentos'!$E$766:$E$836,A39,'03_Eventos_pagamentos'!$O$766:$O$836) | D39: =COUNTIF('03_Eventos_pagamentos'!$E$702:$E$763,'04_TOTALIZADORA (2)'!A39) | E39: =SUMIF('03_Eventos_pagamentos'!$E$702:$E$763,A39,'03_Eventos_pagamentos'!$O$702:$O$763) | F39: =C39+E39+F38 | G39: =SUMIF('03_Eventos_pagamentos'!$P$11:$P$843,A40,'03_Eventos_pagamentos'!$Q$11:$Q$843) | H39: =G39+H38 | I39: =SUMIFS( '03_Eventos_pagamentos'!$O$11:$O$843,'03_Eventos_pagamentos'!$E$11:$E$843,A39,'03_Eventos_pagamentos'!$I$11:$I$843,"FAT. DIRETO") | J39: =G39+I39+J38 | L39: =K39+L38
A40: 27 | B40: =SUM(COUNTIF('03_Eventos_pagamentos'!$E$11:$E$697,'04_TOTALIZADORA (2)'!A40)+COUNTIF('03_Eventos_pagamentos'!$E$766:$E$836,'04_TOTALIZADORA (2)'!A40)) | C40: =SUMIF('03_Eventos_pagamentos'!$E$11:$E$699,A40,'03_Eventos_pagamentos'!$O$11:$O$697)+SUMIF('03_Eventos_pagamentos'!$E$766:$E$836,A40,'03_Eventos_pagamentos'!$O$766:$O$836) | D40: =COUNTIF('03_Eventos_pagamentos'!$E$702:$E$763,'04_TOTALIZADORA (2)'!A40) | E40: =SUMIF('03_Eventos_pagamentos'!$E$702:$E$763,A40,'03_Eventos_pagamentos'!$O$702:$O$763) | F40: =C40+E40+F39 | G40: =SUMIF('03_Eventos_pagamentos'!$P$11:$P$843,A41,'03_Eventos_pagamentos'!$Q$11:$Q$843) | H40: =G40+H39 | I40: =SUMIFS( '03_Eventos_pagamentos'!$O$11:$O$843,'03_Eventos_pagamentos'!$E$11:$E$843,A40,'03_Eventos_pagamentos'!$I$11:$I$843,"FAT. DIRETO") | J40: =G40+I40+J39 | L40: =K40+L39
A41: 28 | B41: =SUM(COUNTIF('03_Eventos_pagamentos'!$E$11:$E$697,'04_TOTALIZADORA (2)'!A41)+COUNTIF('03_Eventos_pagamentos'!$E$766:$E$836,'04_TOTALIZADORA (2)'!A41)) | C41: =SUMIF('03_Eventos_pagamentos'!$E$11:$E$699,A41,'03_Eventos_pagamentos'!$O$11:$O$697)+SUMIF('03_Eventos_pagamentos'!$E$766:$E$836,A41,'03_Eventos_pagamentos'!$O$766:$O$836) | D41: =COUNTIF('03_Eventos_pagamentos'!$E$702:$E$763,'04_TOTALIZADORA (2)'!A41) | E41: =SUMIF('03_Eventos_pagamentos'!$E$702:$E$763,A41,'03_Eventos_pagamentos'!$O$702:$O$763) | F41: =C41+E41+F40 | G41: =SUMIF('03_Eventos_pagamentos'!$P$11:$P$843,A42,'03_Eventos_pagamentos'!$Q$11:$Q$843) | H41: =G41+H40 | I41: =SUMIFS( '03_Eventos_pagamentos'!$O$11:$O$843,'03_Eventos_pagamentos'!$E$11:$E$843,A41,'03_Eventos_pagamentos'!$I$11:$I$843,"FAT. DIRETO") | J41: =G41+I41+J40 | L41: =K41+L40
A42: 29 | B42: =SUM(COUNTIF('03_Eventos_pagamentos'!$E$11:$E$697,'04_TOTALIZADORA (2)'!A42)+COUNTIF('03_Eventos_pagamentos'!$E$766:$E$836,'04_TOTALIZADORA (2)'!A42)) | C42: =SUMIF('03_Eventos_pagamentos'!$E$11:$E$699,A42,'03_Eventos_pagamentos'!$O$11:$O$697)+SUMIF('03_Eventos_pagamentos'!$E$766:$E$836,A42,'03_Eventos_pagamentos'!$O$766:$O$836) | D42: =COUNTIF('03_Eventos_pagamentos'!$E$702:$E$763,'04_TOTALIZADORA (2)'!A42) | E42: =SUMIF('03_Eventos_pagamentos'!$E$702:$E$763,A42,'03_Eventos_pagamentos'!$O$702:$O$763) | F42: =C42+E42+F41 | G42: =SUMIF('03_Eventos_pagamentos'!$P$11:$P$843,A43,'03_Eventos_pagamentos'!$Q$11:$Q$843) | H42: =G42+H41 | I42: =SUMIFS( '03_Eventos_pagamentos'!$O$11:$O$843,'03_Eventos_pagamentos'!$E$11:$E$843,A42,'03_Eventos_pagamentos'!$I$11:$I$843,"FAT. DIRETO") | J42: =G42+I42+J41 | L42: =K42+L41
... A78: 65 | B78: =SUM(COUNTIF('03_Eventos_pagamentos'!$E$11:$E$697,'04_TOTALIZADORA (2)'!A78)+COUNTIF('03_Eventos_pagamentos'!$E$766:$E$836,'04_TOTALIZADORA (2)'!A78)) | C78: =SUMIF('03_Eventos_pagamentos'!$E$11:$E$699,A78,'03_Eventos_pagamentos'!$O$11:$O$697)+SUMIF('03_Eventos_pagamentos'!$E$766:$E$836,A78,'03_Eventos_pagamentos'!$O$766:$O$836) | D78: =COUNTIF('03_Eventos_pagamentos'!$E$702:$E$763,'04_TOTALIZADORA (2)'!A78) | E78: =SUMIF('03_Eventos_pagamentos'!$E$702:$E$763,A78,'03_Eventos_pagamentos'!$O$702:$O$763) | F78: =C78+E78+F77 | G78: =SUMIF('03_Eventos_pagamentos'!$P$11:$P$843,A79,'03_Eventos_pagamentos'!$Q$11:$Q$843) | H78: =G78+H77 | I78: =SUMIFS( '03_Eventos_pagamentos'!$O$11:$O$843,'03_Eventos_pagamentos'!$E$11:$E$843,A78,'03_Eventos_pagamentos'!$I$11:$I$843,"FAT. DIRETO") | J78: =G78+I78+J77 | L78: =K78+L77
A79: 66 | B79: =SUM(COUNTIF('03_Eventos_pagamentos'!$E$11:$E$697,'04_TOTALIZADORA (2)'!A79)+COUNTIF('03_Eventos_pagamentos'!$E$766:$E$836,'04_TOTALIZADORA (2)'!A79)) | C79: =SUMIF('03_Eventos_pagamentos'!$E$11:$E$699,A79,'03_Eventos_pagamentos'!$O$11:$O$697)+SUMIF('03_Eventos_pagamentos'!$E$766:$E$836,A79,'03_Eventos_pagamentos'!$O$766:$O$836) | D79: =COUNTIF('03_Eventos_pagamentos'!$E$702:$E$763,'04_TOTALIZADORA (2)'!A79) | E79: =SUMIF('03_Eventos_pagamentos'!$E$702:$E$763,A79,'03_Eventos_pagamentos'!$O$702:$O$763) | F79: =C79+E79+F78 | G79: =SUMIF('03_Eventos_pagamentos'!$P$11:$P$843,A80,'03_Eventos_pagamentos'!$Q$11:$Q$843) | H79: =G79+H78 | I79: =SUMIFS( '03_Eventos_pagamentos'!$O$11:$O$843,'03_Eventos_pagamentos'!$E$11:$E$843,A79,'03_Eventos_pagamentos'!$I$11:$I$843,"FAT. DIRETO") | J79: =G79+I79+J78 | L79: =K79+L78 | Q79: VALOR AMORTIZADO | R79: =(SUM(K28,K30)/0.85)*0.15
A80: 67 | B80: =SUM(COUNTIF('03_Eventos_pagamentos'!$E$11:$E$697,'04_TOTALIZADORA (2)'!A80)+COUNTIF('03_Eventos_pagamentos'!$E$766:$E$836,'04_TOTALIZADORA (2)'!A80)) | C80: =SUMIF('03_Eventos_pagamentos'!$E$11:$E$699,A80,'03_Eventos_pagamentos'!$O$11:$O$697)+SUMIF('03_Eventos_pagamentos'!$E$766:$E$836,A80,'03_Eventos_pagamentos'!$O$766:$O$836) | D80: =COUNTIF('03_Eventos_pagamentos'!$E$702:$E$763,'04_TOTALIZADORA (2)'!A80) | E80: =SUMIF('03_Eventos_pagamentos'!$E$702:$E$763,A80,'03_Eventos_pagamentos'!$O$702:$O$763) | F80: =C80+E80+F79 | G80: =SUMIF('03_Eventos_pagamentos'!$P$11:$P$843,A81,'03_Eventos_pagamentos'!$Q$11:$Q$843) | H80: =G80+H79 | I80: =SUMIFS( '03_Eventos_pagamentos'!$O$11:$O$843,'03_Eventos_pagamentos'!$E$11:$E$843,A80,'03_Eventos_pagamentos'!$I$11:$I$843,"FAT. DIRETO") | J80: =G80+I80+J79 | L80: =K80+L79
A81: 68 | B81: =SUM(COUNTIF('03_Eventos_pagamentos'!$E$11:$E$697,'04_TOTALIZADORA (2)'!A81)+COUNTIF('03_Eventos_pagamentos'!$E$766:$E$836,'04_TOTALIZADORA (2)'!A81)) | C81: =SUMIF('03_Eventos_pagamentos'!$E$11:$E$699,A81,'03_Eventos_pagamentos'!$O$11:$O$697)+SUMIF('03_Eventos_pagamentos'!$E$766:$E$836,A81,'03_Eventos_pagamentos'!$O$766:$O$836) | D81: =COUNTIF('03_Eventos_pagamentos'!$E$702:$E$763,'04_TOTALIZADORA (2)'!A81) | E81: =SUMIF('03_Eventos_pagamentos'!$E$702:$E$763,A81,'03_Eventos_pagamentos'!$O$702:$O$763) | F81: =C81+E81+F80 | G81: =SUMIF('03_Eventos_pagamentos'!$P$11:$P$843,A82,'03_Eventos_pagamentos'!$Q$11:$Q$843) | H81: =G81+H80 | I81: =SUMIFS( '03_Eventos_pagamentos'!$O$11:$O$843,'03_Eventos_pagamentos'!$E$11:$E$843,A81,'03_Eventos_pagamentos'!$I$11:$I$843,"FAT. DIRETO") | J81: =G81+I81+J80 | L81: =K81+L80
A82: 69 | B82: =SUM(COUNTIF('03_Eventos_pagamentos'!$E$11:$E$697,'04_TOTALIZADORA (2)'!A82)+COUNTIF('03_Eventos_pagamentos'!$E$766:$E$836,'04_TOTALIZADORA (2)'!A82)) | C82: =SUMIF('03_Eventos_pagamentos'!$E$11:$E$699,A82,'03_Eventos_pagamentos'!$O$11:$O$697)+SUMIF('03_Eventos_pagamentos'!$E$766:$E$836,A82,'03_Eventos_pagamentos'!$O$766:$O$836) | D82: =COUNTIF('03_Eventos_pagamentos'!$E$702:$E$763,'04_TOTALIZADORA (2)'!A82) | E82: =SUMIF('03_Eventos_pagamentos'!$E$702:$E$763,A82,'03_Eventos_pagamentos'!$O$702:$O$763) | F82: =C82+E82+F81 | G82: =SUMIF('03_Eventos_pagamentos'!$P$11:$P$843,A83,'03_Eventos_pagamentos'!$Q$11:$Q$843) | H82: =G82+H81 | I82: =SUMIFS( '03_Eventos_pagamentos'!$O$11:$O$843,'03_Eventos_pagamentos'!$E$11:$E$843,A82,'03_Eventos_pagamentos'!$I$11:$I$843,"FAT. DIRETO") | J82: =G82+I82+J81 | L82: =K82+L81
A83: Meses | B83: EVENTOS | C83: =B12 | D83: EVENTOS | E83: =D12 | F83: VALOR TOTAL | H83: VALOR TOTAL | J83: VALOR TOTAL | K83: VALOR TOTAL | L83: VALOR TOTAL | M83: TOTAL EVENTOS | N83: PREÇO GLOBAL | O83: =SUM(C14:C82,E14:E82) | Q83: VALOR ANTECIPAÇÃO SOLICITADA | R83: =M9
A84: 70 | B84: =SUM(B14:B82) | C84: =SUM(C14:C82) | D84: =SUM(D14:D82) | E84: =SUM(E14:E82) | F84: =SUM(C84,E84) | H84: =H82 | J84: =J82 | K84: =SUM(K14:K82) | L84: =L82 | M84: =SUM(B84,D84)
A86: Nota: Preencher somente a célula em destaque amarelo, campo de ANTECIPAÇÃO SOLICITADA, com o valor percentual referênte a solicitação de antecipação, de acordo com as regras do edital e limitado a 5% do VALOR GLOBAL da proposta, demais campos são de preenchimento automático, meramente ilustrativos, pois seguirão as disposições descritas na Minuta de Contrato.

Sheet 04_TOTALIZADORA
A1: ='01_Preço'!A1
A2: TABELA TOTALIZADORA DOS PREÇOS DOS MATERIAIS E SERVIÇOS DA REFORMA E MODERNIZAÇÃO DA UHE SALTO GRANDE E MODERNIZAÇÃO E DIGITALIZAÇÃO DA SE UHE SALTO GRANDE – ATIVOS CEMIG D
A4: OBJETO: CONTRATAÇÃO DE SERVIÇOS PARA EXECUÇÃO DA MODERNIZAÇÃO DA UHE SALTO GRANDE | U4: =_xlfn.CONCAT('01_Preço'!M4," ",'01_Preço'!O4) | W4: BASE ECONÔMICA TRIBUTÁRIA: | X4: ='01_Preço'!V4
A5: NOME EMPRESA PROPONENTE: | D5: ='01_Preço'!C5 | U5: Nº CNPJ: | V5: ='01_Preço'!L5 | W5: Nº INSC ESTADUAL: | X5: ='01_Preço'!Q5
A6: NOME REPRESENTANTE LEGAL: | D6: ='01_Preço'!C6 | U6: Nº CPF: | V6: ='01_Preço'!L6 | W6: Nº IDENTIDADE: | X6: ='01_Preço'!Q6
A7: ASSINATURA DO REPRESENTANTE LEGAL DA EMPRESA: | E7: ='01_Preço'!E7 | W7: DATA DE EMISSÃO: | X7: ='01_Preço'!V5
A9: % DA ANTECIPAÇÃO SOLICITADA | D9: 0.05 | E9: VALOR ANTECIPAÇÃO SOLICITADA | G9: Amortização | H9: =SUM(H14:H82) | S9: =D9*W9 | U9: PREÇO GLOBAL | W9: =U83
G10: Entrada | H10: =O15
A12: MÊS | B12: ESCOPO CEMIG GT | D12: ESCOPO CEMIG D | F12: VALOR ACUMULADO (com todos os impostos) (R$) | K12: INSIGHT | L12: DESEMBOLSO ACUMULADO VALOR ACUMULADO | M12: FAT. DIRETO | N12: DESEMBOLSO TOTAL ACUMULADO VALOR ACUMULADO | O12: FATURAMENTO REALIZADO | P12: FATURAMENTO ACUMULADO | Q12: PROGRAMAÇÃO DE PEDIDOS REALIZADOS | R12: PROGRAMAÇÃO ACUMULADA DE PEDIDOS REALIZADOS | S12: PREÇO DA REFORMA E MODERNIZAÇÃO DA UHE SALTO GRANDE | W12: =C84
B13: EVENTOS NO MÊS | C13: VALOR TOTAL MENSAL (com todos os impostos) (R$) | D13: EVENTOS NO MÊS | E13: VALOR TOTAL MENSAL (com todos os impostos) (R$) | G13: VALOR DA MEDIÇÃO PELA INSIGHT | H13: VALOR A AMORTIZAR | I13: VALOR PARA ENTRAR EM CAIXA DA INSIGHT | J13: VALOR A RECEBER (INSIGHT + DIRETO) | K13: DESEMBOLSO MENSAL | M13: DESEMBOLSO MENSAL | S13: PREÇO DA MODERNIZAÇÃO E DIGITALIZAÇÃO DA SE UHE SALTO GRANDE - ATIVO CEMIG D | W13: =E84
A14: 1 | B14: =SUM(COUNTIF('03_Eventos_pagamentos'!$E$11:$E$697,'04_TOTALIZADORA'!A14)+COUNTIF('03_Eventos_pagamentos'!$E$766:$E$836,'04_TOTALIZADORA'!A14)) | C14: =SUMIF('03_Eventos_pagamentos'!$E$11:$E$699,A14,'03_Eventos_pagamentos'!$O$11:$O$697)+SUMIF('03_Eventos_pagamentos'!$E$766:$E$836,A14,'03_Eventos_pagamentos'!$O$766:$O$836) | D14: =COUNTIF('03_Eventos_pagamentos'!$E$702:$E$763,'04_TOTALIZADORA'!A14) | E14: =SUMIF('03_Eventos_pagamentos'!$E$702:$E$763,A14,'03_Eventos_pagamentos'!$O$702:$O$763) | F14: =C14+E14 | G14: =SUMIF('03_Eventos_pagamentos'!$E$11:$E$699,F14,'03_Eventos_pagamentos'!$O$11:$O$697)+SUMIF('03_Eventos_pagamentos'!$E$766:$E$836,F14,'03_Eventos_pagamentos'!$O$766:$O$836) | H14: =SUMIF('03_Eventos_pagamentos'!$E$702:$E$763,F14,'03_Eventos_pagamentos'!$O$702:$O$763) | I14: =H10 | J14: =I14+M14 | K14: =SUMIF('03_Eventos_pagamentos'!$P$11:$P$843,A15,'03_Eventos_pagamentos'!$Q$11:$Q$843) | M14: =SUMIFS( '03_Eventos_pagamentos'!$O$11:$O$843,'03_Eventos_pagamentos'!$E$11:$E$843,A14,'03_Eventos_pagamentos'!$I$11:$I$843,"FAT. DIRETO") | N14: =L14+M14 | O14: 0 | P14: =O14 | Q14: 9546933.1 | R14: =Q14
A15: 2 | B15: =SUM(COUNTIF('03_Eventos_pagamentos'!$E$11:$E$697,'04_TOTALIZADORA'!A15)+COUNTIF('03_Eventos_pagamentos'!$E$766:$E$836,'04_TOTALIZADORA'!A15)) | C15: =SUMIF('03_Eventos_pagamentos'!$E$11:$E$699,A15,'03_Eventos_pagamentos'!$O$11:$O$697)+SUMIF('03_Eventos_pagamentos'!$E$766:$E$836,A15,'03_Eventos_pagamentos'!$O$766:$O$836) | D15: =COUNTIF('03_Eventos_pagamentos'!$E$702:$E$763,'04_TOTALIZADORA'!A15) | E15: =SUMIF('03_Eventos_pagamentos'!$E$702:$E$763,A15,'03_Eventos_pagamentos'!$O$702:$O$763) | F15: =C15+E15+F14 | H15: =SUMIF('03_Eventos_pagamentos'!$E$702:$E$763,F15,'03_Eventos_pagamentos'!$O$702:$O$763) | I15: =G15-H15 | J15: =I15+M15 | K15: =SUMIF('03_Eventos_pagamentos'!$P$11:$P$843,A16,'03_Eventos_pagamentos'!$Q$11:$Q$843) | L15: =K15+L14 | M15: =SUMIFS( '03_Eventos_pagamentos'!$O$11:$O$843,'03_Eventos_pagamentos'!$E$11:$E$843,A15,'03_Eventos_pagamentos'!$I$11:$I$843,"FAT. DIRETO") | N15: =K15+M15+N14 | O15: =X83 | P15: =O15+P14
A16: 3 | B16: =SUM(COUNTIF('03_Eventos_pagamentos'!$E$11:$E$697,'04_TOTALIZADORA'!A16)+COUNTIF('03_Eventos_pagamentos'!$E$766:$E$836,'04_TOTALIZADORA'!A16)) | C16: =SUMIF('03_Eventos_pagamentos'!$E$11:$E$699,A16,'03_Eventos_pagamentos'!$O$11:$O$697)+SUMIF('03_Eventos_pagamentos'!$E$766:$E$836,A16,'03_Eventos_pagamentos'!$O$766:$O$836) | D16: =COUNTIF('03_Eventos_pagamentos'!$E$702:$E$763,'04_TOTALIZADORA'!A16) | E16: =SUMIF('03_Eventos_pagamentos'!$E$702:$E$763,A16,'03_Eventos_pagamentos'!$O$702:$O$763) | F16: =C16+E16+F15 | G16: =C16+E16-M16 | H16: =SUMIF('03_Eventos_pagamentos'!$E$702:$E$763,F16,'03_Eventos_pagamentos'!$O$702:$O$763) | I16: =G16-H16 | J16: =I16+M16 | K16: =SUMIF('03_Eventos_pagamentos'!$P$11:$P$843,A17,'03_Eventos_pagamentos'!$Q$11:$Q$843) | L16: =K16+L15 | M16: =SUMIFS( '03_Eventos_pagamentos'!$O$11:$O$843,'03_Eventos_pagamentos'!$E$11:$E$843,A16,'03_Eventos_pagamentos'!$I$11:$I$843,"FAT. DIRETO") | N16: =K16+M16+N15 | P16: =O16+P15
A17: 4 | B17: =SUM(COUNTIF('03_Eventos_pagamentos'!$E$11:$E$697,'04_TOTALIZADORA'!A17)+COUNTIF('03_Eventos_pagamentos'!$E$766:$E$836,'04_TOTALIZADORA'!A17)) | C17: =SUMIF('03_Eventos_pagamentos'!$E$11:$E$699,A17,'03_Eventos_pagamentos'!$O$11:$O$697)+SUMIF('03_Eventos_pagamentos'!$E$766:$E$836,A17,'03_Eventos_pagamentos'!$O$766:$O$836) | D17: =COUNTIF('03_Eventos_pagamentos'!$E$702:$E$763,'04_TOTALIZADORA'!A17) | E17: =SUMIF('03_Eventos_pagamentos'!$E$702:$E$763,A17,'03_Eventos_pagamentos'!$O$702:$O$763) | F17: =C17+E17+F16 | G17: =C17+E17-M17 | H17: =SUMIF('03_Eventos_pagamentos'!$E$702:$E$763,F17,'03_Eventos_pagamentos'!$O$702:$O$763) | I17: =G17-H17 | J17: =I17+M17 | K17: =SUMIF('03_Eventos_pagamentos'!$P$11:$P$843,A18,'03_Eventos_pagamentos'!$Q$11:$Q$843) | L17: =K17+L16 | M17: =SUMIFS( '03_Eventos_pagamentos'!$O$11:$O$843,'03_Eventos_pagamentos'!$E$11:$E$843,A17,'03_Eventos_pagamentos'!$I$11:$I$843,"FAT. DIRETO") | N17: =K17+M17+N16 | P17: =O17+P16
A18: 5 | B18: =SUM(COUNTIF('03_Eventos_pagamentos'!$E$11:$E$697,'04_TOTALIZADORA'!A18)+COUNTIF('03_Eventos_pagamentos'!$E$766:$E$836,'04_TOTALIZADORA'!A18)) | C18: =SUMIF('03_Eventos_pagamentos'!$E$11:$E$699,A18,'03_Eventos_pagamentos'!$O$11:$O$697)+SUMIF('03_Eventos_pagamentos'!$E$766:$E$836,A18,'03_Eventos_pagamentos'!$O$766:$O$836) | D18: =COUNTIF('03_Eventos_pagamentos'!$E$702:$E$763,'04_TOTALIZADORA'!A18) | E18: =SUMIF('03_Eventos_pagamentos'!$E$702:$E$763,A18,'03_Eventos_pagamentos'!$O$702:$O$763) | F18: =C18+E18+F17 | G18: =C18+E18-M18 | H18: =SUMIF('03_Eventos_pagamentos'!$E$702:$E$763,F18,'03_Eventos_pagamentos'!$O$702:$O$763) | I18: =G18-H18 | J18: =I18+M18 | K18: =SUMIF('03_Eventos_pagamentos'!$P$11:$P$843,A19,'03_Eventos_pagamentos'!$Q$11:$Q$843) | L18: =K18+L17 | M18: =SUMIFS( '03_Eventos_pagamentos'!$O$11:$O$843,'03_Eventos_pagamentos'!$E$11:$E$843,A18,'03_Eventos_pagamentos'!$I$11:$I$843,"FAT. DIRETO") | N18: =K18+M18+N17 | P18: =O18+P17
A19: 6 | B19: =SUM(COUNTIF('03_Eventos_pagamentos'!$E$11:$E$697,'04_TOTALIZADORA'!A19)+COUNTIF('03_Eventos_pagamentos'!$E$766:$E$836,'04_TOTALIZADORA'!A19)) | C19: =SUMIF('03_Eventos_pagamentos'!$E$11:$E$699,A19,'03_Eventos_pagamentos'!$O$11:$O$697)+SUMIF('03_Eventos_pagamentos'!$E$766:$E$836,A19,'03_Eventos_pagamentos'!$O$766:$O$836) | D19: =COUNTIF('03_Eventos_pagamentos'!$E$702:$E$763,'04_TOTALIZADORA'!A19) | E19: =SUMIF('03_Eventos_pagamentos'!$E$702:$E$763,A19,'03_Eventos_pagamentos'!$O$702:$O$763) | F19: =C19+E19+F18 | G19: =C19+E19-M19 | H19: =SUMIF('03_Eventos_pagamentos'!$E$702:$E$763,F19,'03_Eventos_pagamentos'!$O$702:$O$763) | I19: =G19-H19 | J19: =I19+M19 | K19: =SUMIF('03_Eventos_pagamentos'!$P$11:$P$843,A20,'03_Eventos_pagamentos'!$Q$11:$Q$843) | L19: =K19+L18 | M19: =SUMIFS( '03_Eventos_pagamentos'!$O$11:$O$843,'03_Eventos_pagamentos'!$E$11:$E$843,A19,'03_Eventos_pagamentos'!$I$11:$I$843,"FAT. DIRETO") | N19: =K19+M19+N18 | P19: =O19+P18
A20: 7 | B20: =SUM(COUNTIF('03_Eventos_pagamentos'!$E$11:$E$697,'04_TOTALIZADORA'!A20)+COUNTIF('03_Eventos_pagamentos'!$E$766:$E$836,'04_TOTALIZADORA'!A20)) | C20: =SUMIF('03_Eventos_pagamentos'!$E$11:$E$699,A20,'03_Eventos_pagamentos'!$O$11:$O$697)+SUMIF('03_Eventos_pagamentos'!$E$766:$E$836,A20,'03_Eventos_pagamentos'!$O$766:$O$836) | D20: =COUNTIF('03_Eventos_pagamentos'!$E$702:$E$763,'04_TOTALIZADORA'!A20) | E20: =SUMIF('03_Eventos_pagamentos'!$E$702:$E$763,A20,'03_Eventos_pagamentos'!$O$702:$O$763) | F20: =C20+E20+F19 | G20: =C20+E20-M20 | H20: =SUMIF('03_Eventos_pagamentos'!$E$702:$E$763,F20,'03_Eventos_pagamentos'!$O$702:$O$763) | I20: =G20-H20 | J20: =I20+M20 | K20: =SUMIF('03_Eventos_pagamentos'!$P$11:$P$843,A21,'03_Eventos_pagamentos'!$Q$11:$Q$843) | L20: =K20+L19 | M20: =SUMIFS( '03_Eventos_pagamentos'!$O$11:$O$843,'03_Eventos_pagamentos'!$E$11:$E$843,A20,'03_Eventos_pagamentos'!$I$11:$I$843,"FAT. DIRETO") | N20: =K20+M20+N19 | P20: =O20+P19
A21: 8 | B21: =SUM(COUNTIF('03_Eventos_pagamentos'!$E$11:$E$697,'04_TOTALIZADORA'!A21)+COUNTIF('03_Eventos_pagamentos'!$E$766:$E$836,'04_TOTALIZADORA'!A21)) | C21: =SUMIF('03_Eventos_pagamentos'!$E$11:$E$699,A21,'03_Eventos_pagamentos'!$O$11:$O$697)+SUMIF('03_Eventos_pagamentos'!$E$766:$E$836,A21,'03_Eventos_pagamentos'!$O$766:$O$836) | D21: =COUNTIF('03_Eventos_pagamentos'!$E$702:$E$763,'04_TOTALIZADORA'!A21) | E21: =SUMIF('03_Eventos_pagamentos'!$E$702:$E$763,A21,'03_Eventos_pagamentos'!$O$702:$O$763) | F21: =C21+E21+F20 | G21: =C21+E21-M21 | H21: =SUMIF('03_Eventos_pagamentos'!$E$702:$E$763,F21,'03_Eventos_pagamentos'!$O$702:$O$763) | I21: =G21-H21 | J21: =I21+M21 | K21: =SUMIF('03_Eventos_pagamentos'!$P$11:$P$843,A22,'03_Eventos_pagamentos'!$Q$11:$Q$843) | L21: =K21+L20 | M21: =SUMIFS( '03_Eventos_pagamentos'!$O$11:$O$843,'03_Eventos_pagamentos'!$E$11:$E$843,A21,'03_Eventos_pagamentos'!$I$11:$I$843,"FAT. DIRETO") | N21: =K21+M21+N20 | P21: =O21+P20
A22: 9 | B22: =SUM(COUNTIF('03_Eventos_pagamentos'!$E$11:$E$697,'04_TOTALIZADORA'!A22)+COUNTIF('03_Eventos_pagamentos'!$E$766:$E$836,'04_TOTALIZADORA'!A22)) | C22: =SUMIF('03_Eventos_pagamentos'!$E$11:$E$699,A22,'03_Eventos_pagamentos'!$O$11:$O$697)+SUMIF('03_Eventos_pagamentos'!$E$766:$E$836,A22,'03_Eventos_pagamentos'!$O$766:$O$836) | D22: =COUNTIF('03_Eventos_pagamentos'!$E$702:$E$763,'04_TOTALIZADORA'!A22) | E22: =SUMIF('03_Eventos_pagamentos'!$E$702:$E$763,A22,'03_Eventos_pagamentos'!$O$702:$O$763) | F22: =C22+E22+F21 | G22: =C22+E22-M22 | H22: =SUMIF('03_Eventos_pagamentos'!$E$702:$E$763,F22,'03_Eventos_pagamentos'!$O$702:$O$763) | I22: =G22-H22 | J22: =I22+M22 | K22: =SUMIF('03_Eventos_pagamentos'!$P$11:$P$843,A23,'03_Eventos_pagamentos'!$Q$11:$Q$843) | L22: =K22+L21 | M22: =SUMIFS( '03_Eventos_pagamentos'!$O$11:$O$843,'03_Eventos_pagamentos'!$E$11:$E$843,A22,'03_Eventos_pagamentos'!$I$11:$I$843,"FAT. DIRETO") | N22: =K22+M22+N21 | P22: =O22+P21
A23: 10 | B23: =SUM(COUNTIF('03_Eventos_pagamentos'!$E$11:$E$697,'04_TOTALIZADORA'!A23)+COUNTIF('03_Eventos_pagamentos'!$E$766:$E$836,'04_TOTALIZADORA'!A23)) | C23: =SUMIF('03_Eventos_pagamentos'!$E$11:$E$699,A23,'03_Eventos_pagamentos'!$O$11:$O$697)+SUMIF('03_Eventos_pagamentos'!$E$766:$E$836,A23,'03_Eventos_pagamentos'!$O$766:$O$836) | D23: =COUNTIF('03_Eventos_pagamentos'!$E$702:$E$763,'04_TOTALIZADORA'!A23) | E23: =SUMIF('03_Eventos_pagamentos'!$E$702:$E$763,A23,'03_Eventos_pagamentos'!$O$702:$O$763) | F23: =C23+E23+F22 | G23: =C23+E23-M23 | H23: =SUMIF('03_Eventos_pagamentos'!$E$702:$E$763,F23,'03_Eventos_pagamentos'!$O$702:$O$763) | I23: =G23-H23 | J23: =I23+M23 | K23: =SUMIF('03_Eventos_pagamentos'!$P$11:$P$843,A24,'03_Eventos_pagamentos'!$Q$11:$Q$843) | L23: =K23+L22 | M23: =SUMIFS( '03_Eventos_pagamentos'!$O$11:$O$843,'03_Eventos_pagamentos'!$E$11:$E$843,A23,'03_Eventos_pagamentos'!$I$11:$I$843,"FAT. DIRETO") | N23: =K23+M23+N22 | P23: =O23+P22
A24: 11 | B24: =SUM(COUNTIF('03_Eventos_pagamentos'!$E$11:$E$697,'04_TOTALIZADORA'!A24)+COUNTIF('03_Eventos_pagamentos'!$E$766:$E$836,'04_TOTALIZADORA'!A24)) | C24: =SUMIF('03_Eventos_pagamentos'!$E$11:$E$699,A24,'03_Eventos_pagamentos'!$O$11:$O$697)+SUMIF('03_Eventos_pagamentos'!$E$766:$E$836,A24,'03_Eventos_pagamentos'!$O$766:$O$836) | D24: =COUNTIF('03_Eventos_pagamentos'!$E$702:$E$763,'04_TOTALIZADORA'!A24) | E24: =SUMIF('03_Eventos_pagamentos'!$E$702:$E$763,A24,'03_Eventos_pagamentos'!$O$702:$O$763) | F24: =C24+E24+F23 | G24: =C24+E24-M24 | H24: =SUMIF('03_Eventos_pagamentos'!$E$702:$E$763,F24,'03_Eventos_pagamentos'!$O$702:$O$763) | I24: =G24-H24 | J24: =I24+M24 | K24: =SUMIF('03_Eventos_pagamentos'!$P$11:$P$843,A25,'03_Eventos_pagamentos'!$Q$11:$Q$843) | L24: =K24+L23 | M24: =SUMIFS( '03_Eventos_pagamentos'!$O$11:$O$843,'03_Eventos_pagamentos'!$E$11:$E$843,A24,'03_Eventos_pagamentos'!$I$11:$I$843,"FAT. DIRETO") | N24: =K24+M24+N23 | P24: =O24+P23
A25: 12 | B25: =SUM(COUNTIF('03_Eventos_pagamentos'!$E$11:$E$697,'04_TOTALIZADORA'!A25)+COUNTIF('03_Eventos_pagamentos'!$E$766:$E$836,'04_TOTALIZADORA'!A25)) | C25: =SUMIF('03_Eventos_pagamentos'!$E$11:$E$699,A25,'03_Eventos_pagamentos'!$O$11:$O$697)+SUMIF('03_Eventos_pagamentos'!$E$766:$E$836,A25,'03_Eventos_pagamentos'!$O$766:$O$836) | D25: =COUNTIF('03_Eventos_pagamentos'!$E$702:$E$763,'04_TOTALIZADORA'!A25) | E25: =SUMIF('03_Eventos_pagamentos'!$E$702:$E$763,A25,'03_Eventos_pagamentos'!$O$702:$O$763) | F25: =C25+E25+F24 | G25: =C25+E25-M25 | H25: =SUMIF('03_Eventos_pagamentos'!$E$702:$E$763,F25,'03_Eventos_pagamentos'!$O$702:$O$763) | I25: =G25-H25 | J25: =I25+M25 | K25: =SUMIF('03_Eventos_pagamentos'!$P$11:$P$843,A26,'03_Eventos_pagamentos'!$Q$11:$Q$843) | L25: =K25+L24 | M25: =SUMIFS( '03_Eventos_pagamentos'!$O$11:$O$843,'03_Eventos_pagamentos'!$E$11:$E$843,A25,'03_Eventos_pagamentos'!$I$11:$I$843,"FAT. DIRETO") | N25: =K25+M25+N24 | P25: =O25+P24
A26: 13 | B26: =SUM(COUNTIF('03_Eventos_pagamentos'!$E$11:$E$697,'04_TOTALIZADORA'!A26)+COUNTIF('03_Eventos_pagamentos'!$E$766:$E$836,'04_TOTALIZADORA'!A26)) | C26: =SUMIF('03_Eventos_pagamentos'!$E$11:$E$699,A26,'03_Eventos_pagamentos'!$O$11:$O$697)+SUMIF('03_Eventos_pagamentos'!$E$766:$E$836,A26,'03_Eventos_pagamentos'!$O$766:$O$836) | D26: =COUNTIF('03_Eventos_pagamentos'!$E$702:$E$763,'04_TOTALIZADORA'!A26) | E26: =SUMIF('03_Eventos_pagamentos'!$E$702:$E$763,A26,'03_Eventos_pagamentos'!$O$702:$O$763) | F26: =C26+E26+F25 | G26: =C26+E26-M26 | H26: =SUMIF('03_Eventos_pagamentos'!$E$702:$E$763,F26,'03_Eventos_pagamentos'!$O$702:$O$763) | I26: =G26-H26 | J26: =I26+M26 | K26: =SUMIF('03_Eventos_pagamentos'!$P$11:$P$843,A27,'03_Eventos_pagamentos'!$Q$11:$Q$843) | L26: =K26+L25 | M26: =SUMIFS( '03_Eventos_pagamentos'!$O$11:$O$843,'03_Eventos_pagamentos'!$E$11:$E$843,A26,'03_Eventos_pagamentos'!$I$11:$I$843,"FAT. DIRETO") | N26: =K26+M26+N25 | P26: =O26+P25
A27: 14 | B27: =SUM(COUNTIF('03_Eventos_pagamentos'!$E$11:$E$697,'04_TOTALIZADORA'!A27)+COUNTIF('03_Eventos_pagamentos'!$E$766:$E$836,'04_TOTALIZADORA'!A27)) | C27: =SUMIF('03_Eventos_pagamentos'!$E$11:$E$699,A27,'03_Eventos_pagamentos'!$O$11:$O$697)+SUMIF('03_Eventos_pagamentos'!$E$766:$E$836,A27,'03_Eventos_pagamentos'!$O$766:$O$836) | D27: =COUNTIF('03_Eventos_pagamentos'!$E$702:$E$763,'04_TOTALIZADORA'!A27) | E27: =SUMIF('03_Eventos_pagamentos'!$E$702:$E$763,A27,'03_Eventos_pagamentos'!$O$702:$O$763) | F27: =C27+E27+F26 | G27: =C27+E27-M27 | H27: =SUMIF('03_Eventos_pagamentos'!$E$702:$E$763,F27,'03_Eventos_pagamentos'!$O$702:$O$763) | I27: =G27-H27 | J27: =I27+M27 | K27: =SUMIF('03_Eventos_pagamentos'!$P$11:$P$843,A28,'03_Eventos_pagamentos'!$Q$11:$Q$843) | L27: =K27+L26 | M27: =SUMIFS( '03_Eventos_pagamentos'!$O$11:$O$843,'03_Eventos_pagamentos'!$E$11:$E$843,A27,'03_Eventos_pagamentos'!$I$11:$I$843,"FAT. DIRETO") | N27: =K27+M27+N26 | P27: =O27+P26
A28: 15 | B28: =SUM(COUNTIF('03_Eventos_pagamentos'!$E$11:$E$697,'04_TOTALIZADORA'!A28)+COUNTIF('03_Eventos_pagamentos'!$E$766:$E$836,'04_TOTALIZADORA'!A28)) | C28: =SUMIF('03_Eventos_pagamentos'!$E$11:$E$699,A28,'03_Eventos_pagamentos'!$O$11:$O$697)+SUMIF('03_Eventos_pagamentos'!$E$766:$E$836,A28,'03_Eventos_pagamentos'!$O$766:$O$836) | D28: =COUNTIF('03_Eventos_pagamentos'!$E$702:$E$763,'04_TOTALIZADORA'!A28) | E28: =SUMIF('03_Eventos_pagamentos'!$E$702:$E$763,A28,'03_Eventos_pagamentos'!$O$702:$O$763) | F28: =C28+E28+F27 | G28: =C28+E28-M28 | H28: =SUMIF('03_Eventos_pagamentos'!$E$702:$E$763,F28,'03_Eventos_pagamentos'!$O$702:$O$763) | I28: =G28-H28 | J28: =I28+M28 | K28: =SUMIF('03_Eventos_pagamentos'!$P$11:$P$843,A29,'03_Eventos_pagamentos'!$Q$11:$Q$843) | L28: =K28+L27 | M28: =SUMIFS( '03_Eventos_pagamentos'!$O$11:$O$843,'03_Eventos_pagamentos'!$E$11:$E$843,A28,'03_Eventos_pagamentos'!$I$11:$I$843,"FAT. DIRETO") | N28: =K28+M28+N27 | O28: =0.85*412245.2 | P28: =O28+P27
A29: 16 | B29: =SUM(COUNTIF('03_Eventos_pagamentos'!$E$11:$E$697,'04_TOTALIZADORA'!A29)+COUNTIF('03_Eventos_pagamentos'!$E$766:$E$836,'04_TOTALIZADORA'!A29)) | C29: =SUMIF('03_Eventos_pagamentos'!$E$11:$E$699,A29,'03_Eventos_pagamentos'!$O$11:$O$697)+SUMIF('03_Eventos_pagamentos'!$E$766:$E$836,A29,'03_Eventos_pagamentos'!$O$766:$O$836) | D29: =COUNTIF('03_Eventos_pagamentos'!$E$702:$E$763,'04_TOTALIZADORA'!A29) | E29: =SUMIF('03_Eventos_pagamentos'!$E$702:$E$763,A29,'03_Eventos_pagamentos'!$O$702:$O$763) | F29: =C29+E29+F28 | G29: =C29+E29-M29 | H29: =G29*0.15 | I29: =G29-H29 | J29: =I29+M29 | K29: =SUMIF('03_Eventos_pagamentos'!$P$11:$P$843,A30,'03_Eventos_pagamentos'!$Q$11:$Q$843) | L29: =K29+L28 | M29: =SUMIFS( '03_Eventos_pagamentos'!$O$11:$O$843,'03_Eventos_pagamentos'!$E$11:$E$843,A29,'03_Eventos_pagamentos'!$I$11:$I$843,"FAT. DIRETO") | N29: =K29+M29+N28 | P29: =O29+P28
A30: 17 | B30: =SUM(COUNTIF('03_Eventos_pagamentos'!$E$11:$E$697,'04_TOTALIZADORA'!A30)+COUNTIF('03_Eventos_pagamentos'!$E$766:$E$836,'04_TOTALIZADORA'!A30)) | C30: =SUMIF('03_Eventos_pagamentos'!$E$11:$E$699,A30,'03_Eventos_pagamentos'!$O$11:$O$697)+SUMIF('03_Eventos_pagamentos'!$E$766:$E$836,A30,'03_Eventos_pagamentos'!$O$766:$O$836) | D30: =COUNTIF('03_Eventos_pagamentos'!$E$702:$E$763,'04_TOTALIZADORA'!A30) | E30: =SUMIF('03_Eventos_pagamentos'!$E$702:$E$763,A30,'03_Eventos_pagamentos'!$O$702:$O$763) | F30: =C30+E30+F29 | G30: =C30+E30-M30 | H30: =G30*0.15 | I30: =G30-H30 | J30: =I30+M30 | K30: =SUMIF('03_Eventos_pagamentos'!$P$11:$P$843,A31,'03_Eventos_pagamentos'!$Q$11:$Q$843) | L30: =K30+L29 | M30: =SUMIFS( '03_Eventos_pagamentos'!$O$11:$O$843,'03_Eventos_pagamentos'!$E$11:$E$843,A30,'03_Eventos_pagamentos'!$I$11:$I$843,"FAT. DIRETO") | N30: =K30+M30+N29 | O30: =0.85*800224.32 | P30: =O30+P29 | Q30: 1724103.7 | R30: =R14+Q30
A31: 18 | B31: =SUM(COUNTIF('03_Eventos_pagamentos'!$E$11:$E$697,'04_TOTALIZADORA'!A31)+COUNTIF('03_Eventos_pagamentos'!$E$766:$E$836,'04_TOTALIZADORA'!A31)) | C31: =SUMIF('03_Eventos_pagamentos'!$E$11:$E$699,A31,'03_Eventos_pagamentos'!$O$11:$O$697)+SUMIF('03_Eventos_pagamentos'!$E$766:$E$836,A31,'03_Eventos_pagamentos'!$O$766:$O$836) | D31: =COUNTIF('03_Eventos_pagamentos'!$E$702:$E$763,'04_TOTALIZADORA'!A31) | E31: =SUMIF('03_Eventos_pagamentos'!$E$702:$E$763,A31,'03_Eventos_pagamentos'!$O$702:$O$763) | F31: =C31+E31+F30 | G31: =C31+E31-M31 | H31: =G31*0.15 | I31: =G31-H31 | J31: =I31+M31 | K31: =SUMIF('03_Eventos_pagamentos'!$P$11:$P$843,A32,'03_Eventos_pagamentos'!$Q$11:$Q$843) | L31: =K31+L30 | M31: =SUMIFS( '03_Eventos_pagamentos'!$O$11:$O$843,'03_Eventos_pagamentos'!$E$11:$E$843,A31,'03_Eventos_pagamentos'!$I$11:$I$843,"FAT. DIRETO") | N31: =K31+M31+N30 | P31: =O31+P30 | Q31: 996943.88 | R31: =R30+Q31
A32: 19 | B32: =SUM(COUNTIF('03_Eventos_pagamentos'!$E$11:$E$697,'04_TOTALIZADORA'!A32)+COUNTIF('03_Eventos_pagamentos'!$E$766:$E$836,'04_TOTALIZADORA'!A32)) | C32: =SUMIF('03_Eventos_pagamentos'!$E$11:$E$699,A32,'03_Eventos_pagamentos'!$O$11:$O$697)+SUMIF('03_Eventos_pagamentos'!$E$766:$E$836,A32,'03_Eventos_pagamentos'!$O$766:$O$836) | D32: =COUNTIF('03_Eventos_pagamentos'!$E$702:$E$763,'04_TOTALIZADORA'!A32) | E32: =SUMIF('03_Eventos_pagamentos'!$E$702:$E$763,A32,'03_Eventos_pagamentos'!$O$702:$O$763) | F32: =C32+E32+F31 | G32: =C32+E32-M32 | H32: =G32*0.15 | I32: =G32-H32 | J32: =I32+M32 | K32: =SUMIF('03_Eventos_pagamentos'!$P$11:$P$843,A33,'03_Eventos_pagamentos'!$Q$11:$Q$843) | L32: =K32+L31 | M32: =SUMIFS( '03_Eventos_pagamentos'!$O$11:$O$843,'03_Eventos_pagamentos'!$E$11:$E$843,A32,'03_Eventos_pagamentos'!$I$11:$I$843,"FAT. DIRETO") | N32: =K32+M32+N31 | O32: =0.85*213547.66 | P32: =O32+P31 | Q32: 900062.68 | R32: =R31+Q32
A33: 20 | B33: =SUM(COUNTIF('03_Eventos_pagamentos'!$E$11:$E$697,'04_TOTALIZADORA'!A33)+COUNTIF('03_Eventos_pagamentos'!$E$766:$E$836,'04_TOTALIZADORA'!A33)) | C33: =SUMIF('03_Eventos_pagamentos'!$E$11:$E$699,A33,'03_Eventos_pagamentos'!$O$11:$O$697)+SUMIF('03_Eventos_pagamentos'!$E$766:$E$836,A33,'03_Eventos_pagamentos'!$O$766:$O$836) | D33: =COUNTIF('03_Eventos_pagamentos'!$E$702:$E$763,'04_TOTALIZADORA'!A33) | E33: =SUMIF('03_Eventos_pagamentos'!$E$702:$E$763,A33,'03_Eventos_pagamentos'!$O$702:$O$763) | F33: =C33+E33+F32 | G33: =C33+E33-M33 | H33: =G33*0.15 | I33: =G33-H33 | J33: =I33+M33 | K33: =SUMIF('03_Eventos_pagamentos'!$P$11:$P$843,A34,'03_Eventos_pagamentos'!$Q$11:$Q$843) | L33: =K33+L32 | M33: =SUMIFS( '03_Eventos_pagamentos'!$O$11:$O$843,'03_Eventos_pagamentos'!$E$11:$E$843,A33,'03_Eventos_pagamentos'!$I$11:$I$843,"FAT. DIRETO") | N33: =K33+M33+N32 | P33: =O33+P32 | Q33: 623444.52 | R33: =R32+Q33
A34: 21 | B34: =SUM(COUNTIF('03_Eventos_pagamentos'!$E$11:$E$697,'04_TOTALIZADORA'!A34)+COUNTIF('03_Eventos_pagamentos'!$E$766:$E$836,'04_TOTALIZADORA'!A34)) | C34: =SUMIF('03_Eventos_pagamentos'!$E$11:$E$699,A34,'03_Eventos_pagamentos'!$O$11:$O$697)+SUMIF('03_Eventos_pagamentos'!$E$766:$E$836,A34,'03_Eventos_pagamentos'!$O$766:$O$836) | D34: =COUNTIF('03_Eventos_pagamentos'!$E$702:$E$763,'04_TOTALIZADORA'!A34) | E34: =SUMIF('03_Eventos_pagamentos'!$E$702:$E$763,A34,'03_Eventos_pagamentos'!$O$702:$O$763) | F34: =C34+E34+F33 | G34: =C34+E34-M34 | H34: =G34*0.15 | I34: =G34-H34 | J34: =I34+M34 | K34: =SUMIF('03_Eventos_pagamentos'!$P$11:$P$843,A35,'03_Eventos_pagamentos'!$Q$11:$Q$843) | L34: =K34+L33 | M34: =SUMIFS( '03_Eventos_pagamentos'!$O$11:$O$843,'03_Eventos_pagamentos'!$E$11:$E$843,A34,'03_Eventos_pagamentos'!$I$11:$I$843,"FAT. DIRETO") | N34: =K34+M34+N33 | P34: =O34+P33 | Q34: 628101.5 | R34: =R33+Q34
A35: 22 | B35: =SUM(COUNTIF('03_Eventos_pagamentos'!$E$11:$E$697,'04_TOTALIZADORA'!A35)+COUNTIF('03_Eventos_pagamentos'!$E$766:$E$836,'04_TOTALIZADORA'!A35)) | C35: =SUMIF('03_Eventos_pagamentos'!$E$11:$E$699,A35,'03_Eventos_pagamentos'!$O$11:$O$697)+SUMIF('03_Eventos_pagamentos'!$E$766:$E$836,A35,'03_Eventos_pagamentos'!$O$766:$O$836) | D35: =COUNTIF('03_Eventos_pagamentos'!$E$702:$E$763,'04_TOTALIZADORA'!A35) | E35: =SUMIF('03_Eventos_pagamentos'!$E$702:$E$763,A35,'03_Eventos_pagamentos'!$O$702:$O$763) | F35: =C35+E35+F34 | G35: =C35+E35-M35 | H35: =G35*0.15 | I35: =G35-H35 | J35: =I35+M35 | K35: =SUMIF('03_Eventos_pagamentos'!$P$11:$P$843,A36,'03_Eventos_pagamentos'!$Q$11:$Q$843) | L35: =K35+L34 | M35: =SUMIFS( '03_Eventos_pagamentos'!$O$11:$O$843,'03_Eventos_pagamentos'!$E$11:$E$843,A35,'03_Eventos_pagamentos'!$I$11:$I$843,"FAT. DIRETO") | N35: =K35+M35+N34 | P35: =O35+P34 | Q35: 899398.5 | R35: =R34+Q35
A36: 23 | B36: =SUM(COUNTIF('03_Eventos_pagamentos'!$E$11:$E$697,'04_TOTALIZADORA'!A36)+COUNTIF('03_Eventos_pagamentos'!$E$766:$E$836,'04_TOTALIZADORA'!A36)) | C36: =SUMIF('03_Eventos_pagamentos'!$E$11:$E$699,A36,'03_Eventos_pagamentos'!$O$11:$O$697)+SUMIF('03_Eventos_pagamentos'!$E$766:$E$836,A36,'03_Eventos_pagamentos'!$O$766:$O$836) | D36: =COUNTIF('03_Eventos_pagamentos'!$E$702:$E$763,'04_TOTALIZADORA'!A36) | E36: =SUMIF('03_Eventos_pagamentos'!$E$702:$E$763,A36,'03_Eventos_pagamentos'!$O$702:$O$763) | F36: =C36+E36+F35 | G36: =C36+E36-M36 | H36: =G36*0.15 | I36: =G36-H36 | J36: =I36+M36 | K36: =SUMIF('03_Eventos_pagamentos'!$P$11:$P$843,A37,'03_Eventos_pagamentos'!$Q$11:$Q$843) | L36: =K36+L35 | M36: =SUMIFS( '03_Eventos_pagamentos'!$O$11:$O$843,'03_Eventos_pagamentos'!$E$11:$E$843,A36,'03_Eventos_pagamentos'!$I$11:$I$843,"FAT. DIRETO") | N36: =K36+M36+N35 | P36: =O36+P35 | Q36: 849378.18 | R36: =R35+Q36
A37: 24 | B37: =SUM(COUNTIF('03_Eventos_pagamentos'!$E$11:$E$697,'04_TOTALIZADORA'!A37)+COUNTIF('03_Eventos_pagamentos'!$E$766:$E$836,'04_TOTALIZADORA'!A37)) | C37: =SUMIF('03_Eventos_pagamentos'!$E$11:$E$699,A37,'03_Eventos_pagamentos'!$O$11:$O$697)+SUMIF('03_Eventos_pagamentos'!$E$766:$E$836,A37,'03_Eventos_pagamentos'!$O$766:$O$836) | D37: =COUNTIF('03_Eventos_pagamentos'!$E$702:$E$763,'04_TOTALIZADORA'!A37) | E37: =SUMIF('03_Eventos_pagamentos'!$E$702:$E$763,A37,'03_Eventos_pagamentos'!$O$702:$O$763) | F37: =C37+E37+F36 | G37: =C37+E37-M37 | H37: =G37*0.15 | I37: =G37-H37 | J37: =I37+M37 | K37: =SUMIF('03_Eventos_pagamentos'!$P$11:$P$843,A38,'03_Eventos_pagamentos'!$Q$11:$Q$843) | L37: =K37+L36 | M37: =SUMIFS( '03_Eventos_pagamentos'!$O$11:$O$843,'03_Eventos_pagamentos'!$E$11:$E$843,A37,'03_Eventos_pagamentos'!$I$11:$I$843,"FAT. DIRETO") | N37: =K37+M37+N36 | P37: =O37+P36 | Q37: 186000 | R37: =R36+Q37
A38: 25 | B38: =SUM(COUNTIF('03_Eventos_pagamentos'!$E$11:$E$697,'04_TOTALIZADORA'!A38)+COUNTIF('03_Eventos_pagamentos'!$E$766:$E$836,'04_TOTALIZADORA'!A38)) | C38: =SUMIF('03_Eventos_pagamentos'!$E$11:$E$699,A38,'03_Eventos_pagamentos'!$O$11:$O$697)+SUMIF('03_Eventos_pagamentos'!$E$766:$E$836,A38,'03_Eventos_pagamentos'!$O$766:$O$836) | D38: =COUNTIF('03_Eventos_pagamentos'!$E$702:$E$763,'04_TOTALIZADORA'!A38) | E38: =SUMIF('03_Eventos_pagamentos'!$E$702:$E$763,A38,'03_Eventos_pagamentos'!$O$702:$O$763) | F38: =C38+E38+F37 | G38: =C38+E38-M38 | H38: =G38*0.15 | I38: =G38-H38 | J38: =I38+M38 | K38: =SUMIF('03_Eventos_pagamentos'!$P$11:$P$843,A39,'03_Eventos_pagamentos'!$Q$11:$Q$843) | L38: =K38+L37 | M38: =SUMIFS( '03_Eventos_pagamentos'!$O$11:$O$843,'03_Eventos_pagamentos'!$E$11:$E$843,A38,'03_Eventos_pagamentos'!$I$11:$I$843,"FAT. DIRETO") | N38: =K38+M38+N37 | P38: =O38+P37 | Q38: 569901.22 | R38: =R37+Q38
A39: 26 | B39: =SUM(COUNTIF('03_Eventos_pagamentos'!$E$11:$E$697,'04_TOTALIZADORA'!A39)+COUNTIF('03_Eventos_pagamentos'!$E$766:$E$836,'04_TOTALIZADORA'!A39)) | C39: =SUMIF('03_Eventos_pagamentos'!$E$11:$E$699,A39,'03_Eventos_pagamentos'!$O$11:$O$697)+SUMIF('03_Eventos_pagamentos'!$E$766:$E$836,A39,'03_Eventos_pagamentos'!$O$766:$O$836) | D39: =COUNTIF('03_Eventos_pagamentos'!$E$702:$E$763,'04_TOTALIZADORA'!A39) | E39: =SUMIF('03_Eventos_pagamentos'!$E$702:$E$763,A39,'03_Eventos_pagamentos'!$O$702:$O$763) | F39: =C39+E39+F38 | G39: =C39+E39-M39 | H39: =G39*0.15 | I39: =G39-H39 | J39: =I39+M39 | K39: =SUMIF('03_Eventos_pagamentos'!$P$11:$P$843,A40,'03_Eventos_pagamentos'!$Q$11:$Q$843) | L39: =K39+L38 | M39: =SUMIFS( '03_Eventos_pagamentos'!$O$11:$O$843,'03_Eventos_pagamentos'!$E$11:$E$843,A39,'03_Eventos_pagamentos'!$I$11:$I$843,"FAT. DIRETO") | N39: =K39+M39+N38 | P39: =O39+P38 | R39: =R38+Q39
A40: 27 | B40: =SUM(COUNTIF('03_Eventos_pagamentos'!$E$11:$E$697,'04_TOTALIZADORA'!A40)+COUNTIF('03_Eventos_pagamentos'!$E$766:$E$836,'04_TOTALIZADORA'!A40)) | C40: =SUMIF('03_Eventos_pagamentos'!$E$11:$E$699,A40,'03_Eventos_pagamentos'!$O$11:$O$697)+SUMIF('03_Eventos_pagamentos'!$E$766:$E$836,A40,'03_Eventos_pagamentos'!$O$766:$O$836) | D40: =COUNTIF('03_Eventos_pagamentos'!$E$702:$E$763,'04_TOTALIZADORA'!A40) | E40: =SUMIF('03_Eventos_pagamentos'!$E$702:$E$763,A40,'03_Eventos_pagamentos'!$O$702:$O$763) | F40: =C40+E40+F39 | G40: =C40+E40-M40 | H40: =G40*0.15 | I40: =G40-H40 | J40: =I40+M40 | K40: =SUMIF('03_Eventos_pagamentos'!$P$11:$P$843,A41,'03_Eventos_pagamentos'!$Q$11:$Q$843) | L40: =K40+L39 | M40: =SUMIFS( '03_Eventos_pagamentos'!$O$11:$O$843,'03_Eventos_pagamentos'!$E$11:$E$843,A40,'03_Eventos_pagamentos'!$I$11:$I$843,"FAT. DIRETO") | N40: =K40+M40+N39 | P40: =O40+P39 | R40: =R39+Q40
A41: 28 | B41: =SUM(COUNTIF('03_Eventos_pagamentos'!$E$11:$E$697,'04_TOTALIZADORA'!A41)+COUNTIF('03_Eventos_pagamentos'!$E$766:$E$836,'04_TOTALIZADORA'!A41)) | C41: =SUMIF('03_Eventos_pagamentos'!$E$11:$E$699,A41,'03_Eventos_pagamentos'!$O$11:$O$697)+SUMIF('03_Eventos_pagamentos'!$E$766:$E$836,A41,'03_Eventos_pagamentos'!$O$766:$O$836) | D41: =COUNTIF('03_Eventos_pagamentos'!$E$702:$E$763,'04_TOTALIZADORA'!A41) | E41: =SUMIF('03_Eventos_pagamentos'!$E$702:$E$763,A41,'03_Eventos_pagamentos'!$O$702:$O$763) | F41: =C41+E41+F40 | G41: =C41+E41-M41 | H41: =G41*0.15 | I41: =G41-H41 | J41: =I41+M41 | K41: =SUMIF('03_Eventos_pagamentos'!$P$11:$P$843,A42,'03_Eventos_pagamentos'!$Q$11:$Q$843) | L41: =K41+L40 | M41: =SUMIFS( '03_Eventos_pagamentos'!$O$11:$O$843,'03_Eventos_pagamentos'!$E$11:$E$843,A41,'03_Eventos_pagamentos'!$I$11:$I$843,"FAT. DIRETO") | N41: =K41+M41+N40 | P41: =O41+P40 | R41: =R40+Q41
A42: 29 | B42: =SUM(COUNTIF('03_Eventos_pagamentos'!$E$11:$E$697,'04_TOTALIZADORA'!A42)+COUNTIF('03_Eventos_pagamentos'!$E$766:$E$836,'04_TOTALIZADORA'!A42)) | C42: =SUMIF('03_Eventos_pagamentos'!$E$11:$E$699,A42,'03_Eventos_pagamentos'!$O$11:$O$697)+SUMIF('03_Eventos_pagamentos'!$E$766:$E$836,A42,'03_Eventos_pagamentos'!$O$766:$O$836) | D42: =COUNTIF('03_Eventos_pagamentos'!$E$702:$E$763,'04_TOTALIZADORA'!A42) | E42: =SUMIF('03_Eventos_pagamentos'!$E$702:$E$763,A42,'03_Eventos_pagamentos'!$O$702:$O$763) | F42: =C42+E42+F41 | G42: =C42+E42-M42 | H42: =G42*0.15 | I42: =G42-H42 | J42: =I42+M42 | K42: =SUMIF('03_Eventos_pagamentos'!$P$11:$P$843,A43,'03_Eventos_pagamentos'!$Q$11:$Q$843) | L42: =K42+L41 | M42: =SUMIFS( '03_Eventos_pagamentos'!$O$11:$O$843,'03_Eventos_pagamentos'!$E$11:$E$843,A42,'03_Eventos_pagamentos'!$I$11:$I$843,"FAT. DIRETO") | N42: =K42+M42+N41 | P42: =O42+P41 | R42: =R41+Q42
A43: 30 | B43: =SUM(COUNTIF('03_Eventos_pagamentos'!$E$11:$E$697,'04_TOTALIZADORA'!A43)+COUNTIF('03_Eventos_pagamentos'!$E$766:$E$836,'04_TOTALIZADORA'!A43)) | C43: =SUMIF('03_Eventos_pagamentos'!$E$11:$E$699,A43,'03_Eventos_pagamentos'!$O$11:$O$697)+SUMIF('03_Eventos_pagamentos'!$E$766:$E$836,A43,'03_Eventos_pagamentos'!$O$766:$O$836) | D43: =COUNTIF('03_Eventos_pagamentos'!$E$702:$E$763,'04_TOTALIZADORA'!A43) | E43: =SUMIF('03_Eventos_pagamentos'!$E$702:$E$763,A43,'03_Eventos_pagamentos'!$O$702:$O$763) | F43: =C43+E43+F42 | G43: =C43+E43-M43 | H43: =G43*0.15 | I43: =G43-H43 | J43: =I43+M43 | K43: =SUMIF('03_Eventos_pagamentos'!$P$11:$P$843,A44,'03_Eventos_pagamentos'!$Q$11:$Q$843) | L43: =K43+L42 | M43: =SUMIFS( '03_Eventos_pagamentos'!$O$11:$O$843,'03_Eventos_pagamentos'!$E$11:$E$843,A43,'03_Eventos_pagamentos'!$I$11:$I$843,"FAT. DIRETO") | N43: =K43+M43+N42 | P43: =O43+P42 | R43: =R42+Q43
A44: 31 | B44: =SUM(COUNTIF('03_Eventos_pagamentos'!$E$11:$E$697,'04_TOTALIZADORA'!A44)+COUNTIF('03_Eventos_pagamentos'!$E$766:$E$836,'04_TOTALIZADORA'!A44)) | C44: =SUMIF('03_Eventos_pagamentos'!$E$11:$E$699,A44,'03_Eventos_pagamentos'!$O$11:$O$697)+SUMIF('03_Eventos_pagamentos'!$E$766:$E$836,A44,'03_Eventos_pagamentos'!$O$766:$O$836) | D44: =COUNTIF('03_Eventos_pagamentos'!$E$702:$E$763,'04_TOTALIZADORA'!A44) | E44: =SUMIF('03_Eventos_pagamentos'!$E$702:$E$763,A44,'03_Eventos_pagamentos'!$O$702:$O$763) | F44: =C44+E44+F43 | G44: =C44+E44-M44 | H44: =G44*0.15 | I44: =G44-H44 | J44: =I44+M44 | K44: =SUMIF('03_Eventos_pagamentos'!$P$11:$P$843,A45,'03_Eventos_pagamentos'!$Q$11:$Q$843) | L44: =K44+L43 | M44: =SUMIFS( '03_Eventos_pagamentos'!$O$11:$O$843,'03_Eventos_pagamentos'!$E$11:$E$843,A44,'03_Eventos_pagamentos'!$I$11:$I$843,"FAT. DIRETO") | N44: =K44+M44+N43 | P44: =O44+P43 | R44: =R43+Q44
A45: 32 | B45: =SUM(COUNTIF('03_Eventos_pagamentos'!$E$11:$E$697,'04_TOTALIZADORA'!A45)+COUNTIF('03_Eventos_pagamentos'!$E$766:$E$836,'04_TOTALIZADORA'!A45)) | C45: =SUMIF('03_Eventos_pagamentos'!$E$11:$E$699,A45,'03_Eventos_pagamentos'!$O$11:$O$697)+SUMIF('03_Eventos_pagamentos'!$E$766:$E$836,A45,'03_Eventos_pagamentos'!$O$766:$O$836) | D45: =COUNTIF('03_Eventos_pagamentos'!$E$702:$E$763,'04_TOTALIZADORA'!A45) | E45: =SUMIF('03_Eventos_pagamentos'!$E$702:$E$763,A45,'03_Eventos_pagamentos'!$O$702:$O$763) | F45: =C45+E45+F44 | G45: =C45+E45-M45 | H45: =G45*0.15 | I45: =G45-H45 | J45: =I45+M45 | K45: =SUMIF('03_Eventos_pagamentos'!$P$11:$P$843,A46,'03_Eventos_pagamentos'!$Q$11:$Q$843) | L45: =K45+L44 | M45: =SUMIFS( '03_Eventos_pagamentos'!$O$11:$O$843,'03_Eventos_pagamentos'!$E$11:$E$843,A45,'03_Eventos_pagamentos'!$I$11:$I$843,"FAT. DIRETO") | N45: =K45+M45+N44 | P45: =O45+P44 | Q45: 113319.2 | R45: =R44+Q45
A46: 33 | B46: =SUM(COUNTIF('03_Eventos_pagamentos'!$E$11:$E$697,'04_TOTALIZADORA'!A46)+COUNTIF('03_Eventos_pagamentos'!$E$766:$E$836,'04_TOTALIZADORA'!A46)) | C46: =SUMIF('03_Eventos_pagamentos'!$E$11:$E$699,A46,'03_Eventos_pagamentos'!$O$11:$O$697)+SUMIF('03_Eventos_pagamentos'!$E$766:$E$836,A46,'03_Eventos_pagamentos'!$O$766:$O$836) | D46: =COUNTIF('03_Eventos_pagamentos'!$E$702:$E$763,'04_TOTALIZADORA'!A46) | E46: =SUMIF('03_Eventos_pagamentos'!$E$702:$E$763,A46,'03_Eventos_pagamentos'!$O$702:$O$763) | F46: =C46+E46+F45 | G46: =C46+E46-M46 | H46: =G46*0.15 | I46: =G46-H46 | J46: =I46+M46 | K46: =SUMIF('03_Eventos_pagamentos'!$P$11:$P$843,A47,'03_Eventos_pagamentos'!$Q$11:$Q$843) | L46: =K46+L45 | M46: =SUMIFS( '03_Eventos_pagamentos'!$O$11:$O$843,'03_Eventos_pagamentos'!$E$11:$E$843,A46,'03_Eventos_pagamentos'!$I$11:$I$843,"FAT. DIRETO") | N46: =K46+M46+N45 | P46: =O46+P45 | R46: =R45+Q46
A47: 34 | B47: =SUM(COUNTIF('03_Eventos_pagamentos'!$E$11:$E$697,'04_TOTALIZADORA'!A47)+COUNTIF('03_Eventos_pagamentos'!$E$766:$E$836,'04_TOTALIZADORA'!A47)) | C47: =SUMIF('03_Eventos_pagamentos'!$E$11:$E$699,A47,'03_Eventos_pagamentos'!$O$11:$O$697)+SUMIF('03_Eventos_pagamentos'!$E$766:$E$836,A47,'03_Eventos_pagamentos'!$O$766:$O$836) | D47: =COUNTIF('03_Eventos_pagamentos'!$E$702:$E$763,'04_TOTALIZADORA'!A47) | E47: =SUMIF('03_Eventos_pagamentos'!$E$702:$E$763,A47,'03_Eventos_pagamentos'!$O$702:$O$763) | F47: =C47+E47+F46 | G47: =C47+E47-M47 | H47: =G47*0.15 | I47: =G47-H47 | J47: =I47+M47 | K47: =SUMIF('03_Eventos_pagamentos'!$P$11:$P$843,A48,'03_Eventos_pagamentos'!$Q$11:$Q$843) | L47: =K47+L46 | M47: =SUMIFS( '03_Eventos_pagamentos'!$O$11:$O$843,'03_Eventos_pagamentos'!$E$11:$E$843,A47,'03_Eventos_pagamentos'!$I$11:$I$843,"FAT. DIRETO") | N47: =K47+M47+N46 | P47: =O47+P46 | R47: =R46+Q47
A48: 35 | B48: =SUM(COUNTIF('03_Eventos_pagamentos'!$E$11:$E$697,'04_TOTALIZADORA'!A48)+COUNTIF('03_Eventos_pagamentos'!$E$766:$E$836,'04_TOTALIZADORA'!A48)) | C48: =SUMIF('03_Eventos_pagamentos'!$E$11:$E$699,A48,'03_Eventos_pagamentos'!$O$11:$O$697)+SUMIF('03_Eventos_pagamentos'!$E$766:$E$836,A48,'03_Eventos_pagamentos'!$O$766:$O$836) | D48: =COUNTIF('03_Eventos_pagamentos'!$E$702:$E$763,'04_TOTALIZADORA'!A48) | E48: =SUMIF('03_Eventos_pagamentos'!$E$702:$E$763,A48,'03_Eventos_pagamentos'!$O$702:$O$763) | F48: =C48+E48+F47 | G48: =C48+E48-M48 | H48: =I14-SUM(H29:H47) | I48: =G48-H48 | J48: =I48+M48 | K48: =SUMIF('03_Eventos_pagamentos'!$P$11:$P$843,A49,'03_Eventos_pagamentos'!$Q$11:$Q$843) | L48: =K48+L47 | M48: =SUMIFS( '03_Eventos_pagamentos'!$O$11:$O$843,'03_Eventos_pagamentos'!$E$11:$E$843,A48,'03_Eventos_pagamentos'!$I$11:$I$843,"FAT. DIRETO") | N48: =K48+M48+N47 | P48: =O48+P47 | R48: =R47+Q48
A49: 36 | B49: =SUM(COUNTIF('03_Eventos_pagamentos'!$E$11:$E$697,'04_TOTALIZADORA'!A49)+COUNTIF('03_Eventos_pagamentos'!$E$766:$E$836,'04_TOTALIZADORA'!A49)) | C49: =SUMIF('03_Eventos_pagamentos'!$E$11:$E$699,A49,'03_Eventos_pagamentos'!$O$11:$O$697)+SUMIF('03_Eventos_pagamentos'!$E$766:$E$836,A49,'03_Eventos_pagamentos'!$O$766:$O$836) | D49: =COUNTIF('03_Eventos_pagamentos'!$E$702:$E$763,'04_TOTALIZADORA'!A49) | E49: =SUMIF('03_Eventos_pagamentos'!$E$702:$E$763,A49,'03_Eventos_pagamentos'!$O$702:$O$763) | F49: =C49+E49+F48 | G49: =C49+E49-M49 | H49: =SUMIF('03_Eventos_pagamentos'!$E$702:$E$763,F49,'03_Eventos_pagamentos'!$O$702:$O$763) | I49: =G49-H49 | J49: =I49+M49 | K49: =SUMIF('03_Eventos_pagamentos'!$P$11:$P$843,A50,'03_Eventos_pagamentos'!$Q$11:$Q$843) | L49: =K49+L48 | M49: =SUMIFS( '03_Eventos_pagamentos'!$O$11:$O$843,'03_Eventos_pagamentos'!$E$11:$E$843,A49,'03_Eventos_pagamentos'!$I$11:$I$843,"FAT. DIRETO") | N49: =K49+M49+N48 | P49: =O49+P48 | R49: =R48+Q49
A50: 37 | B50: =SUM(COUNTIF('03_Eventos_pagamentos'!$E$11:$E$697,'04_TOTALIZADORA'!A50)+COUNTIF('03_Eventos_pagamentos'!$E$766:$E$836,'04_TOTALIZADORA'!A50)) | C50: =SUMIF('03_Eventos_pagamentos'!$E$11:$E$699,A50,'03_Eventos_pagamentos'!$O$11:$O$697)+SUMIF('03_Eventos_pagamentos'!$E$766:$E$836,A50,'03_Eventos_pagamentos'!$O$766:$O$836) | D50: =COUNTIF('03_Eventos_pagamentos'!$E$702:$E$763,'04_TOTALIZADORA'!A50) | E50: =SUMIF('03_Eventos_pagamentos'!$E$702:$E$763,A50,'03_Eventos_pagamentos'!$O$702:$O$763) | F50: =C50+E50+F49 | G50: =C50+E50-M50 | H50: =SUMIF('03_Eventos_pagamentos'!$E$702:$E$763,F50,'03_Eventos_pagamentos'!$O$702:$O$763) | I50: =G50-H50 | J50: =I50+M50 | K50: =SUMIF('03_Eventos_pagamentos'!$P$11:$P$843,A51,'03_Eventos_pagamentos'!$Q$11:$Q$843) | L50: =K50+L49 | M50: =SUMIFS( '03_Eventos_pagamentos'!$O$11:$O$843,'03_Eventos_pagamentos'!$E$11:$E$843,A50,'03_Eventos_pagamentos'!$I$11:$I$843,"FAT. DIRETO") | N50: =K50+M50+N49 | P50: =O50+P49 | R50: =R49+Q50
A51: 38 | B51: =SUM(COUNTIF('03_Eventos_pagamentos'!$E$11:$E$697,'04_TOTALIZADORA'!A51)+COUNTIF('03_Eventos_pagamentos'!$E$766:$E$836,'04_TOTALIZADORA'!A51)) | C51: =SUMIF('03_Eventos_pagamentos'!$E$11:$E$699,A51,'03_Eventos_pagamentos'!$O$11:$O$697)+SUMIF('03_Eventos_pagamentos'!$E$766:$E$836,A51,'03_Eventos_pagamentos'!$O$766:$O$836) | D51: =COUNTIF('03_Eventos_pagamentos'!$E$702:$E$763,'04_TOTALIZADORA'!A51) | E51: =SUMIF('03_Eventos_pagamentos'!$E$702:$E$763,A51,'03_Eventos_pagamentos'!$O$702:$O$763) | F51: =C51+E51+F50 | G51: =C51+E51-M51 | H51: =SUMIF('03_Eventos_pagamentos'!$E$702:$E$763,F51,'03_Eventos_pagamentos'!$O$702:$O$763) | I51: =G51-H51 | J51: =I51+M51 | K51: =SUMIF('03_Eventos_pagamentos'!$P$11:$P$843,A52,'03_Eventos_pagamentos'!$Q$11:$Q$843) | L51: =K51+L50 | M51: =SUMIFS( '03_Eventos_pagamentos'!$O$11:$O$843,'03_Eventos_pagamentos'!$E$11:$E$843,A51,'03_Eventos_pagamentos'!$I$11:$I$843,"FAT. DIRETO") | N51: =K51+M51+N50 | P51: =O51+P50 | R51: =R50+Q51
A52: 39 | B52: =SUM(COUNTIF('03_Eventos_pagamentos'!$E$11:$E$697,'04_TOTALIZADORA'!A52)+COUNTIF('03_Eventos_pagamentos'!$E$766:$E$836,'04_TOTALIZADORA'!A52)) | C52: =SUMIF('03_Eventos_pagamentos'!$E$11:$E$699,A52,'03_Eventos_pagamentos'!$O$11:$O$697)+SUMIF('03_Eventos_pagamentos'!$E$766:$E$836,A52,'03_Eventos_pagamentos'!$O$766:$O$836) | D52: =COUNTIF('03_Eventos_pagamentos'!$E$702:$E$763,'04_TOTALIZADORA'!A52) | E52: =SUMIF('03_Eventos_pagamentos'!$E$702:$E$763,A52,'03_Eventos_pagamentos'!$O$702:$O$763) | F52: =C52+E52+F51 | G52: =C52+E52-M52 | H52: =SUMIF('03_Eventos_pagamentos'!$E$702:$E$763,F52,'03_Eventos_pagamentos'!$O$702:$O$763) | I52: =G52-H52 | J52: =I52+M52 | K52: =SUMIF('03_Eventos_pagamentos'!$P$11:$P$843,A53,'03_Eventos_pagamentos'!$Q$11:$Q$843) | L52: =K52+L51 | M52: =SUMIFS( '03_Eventos_pagamentos'!$O$11:$O$843,'03_Eventos_pagamentos'!$E$11:$E$843,A52,'03_Eventos_pagamentos'!$I$11:$I$843,"FAT. DIRETO") | N52: =K52+M52+N51 | P52: =O52+P51 | R52: =R51+Q52
A53: 40 | B53: =SUM(COUNTIF('03_Eventos_pagamentos'!$E$11:$E$697,'04_TOTALIZADORA'!A53)+COUNTIF('03_Eventos_pagamentos'!$E$766:$E$836,'04_TOTALIZADORA'!A53)) | C53: =SUMIF('03_Eventos_pagamentos'!$E$11:$E$699,A53,'03_Eventos_pagamentos'!$O$11:$O$697)+SUMIF('03_Eventos_pagamentos'!$E$766:$E$836,A53,'03_Eventos_pagamentos'!$O$766:$O$836) | D53: =COUNTIF('03_Eventos_pagamentos'!$E$702:$E$763,'04_TOTALIZADORA'!A53) | E53: =SUMIF('03_Eventos_pagamentos'!$E$702:$E$763,A53,'03_Eventos_pagamentos'!$O$702:$O$763) | F53: =C53+E53+F52 | G53: =C53+E53-M53 | H53: =SUMIF('03_Eventos_pagamentos'!$E$702:$E$763,F53,'03_Eventos_pagamentos'!$O$702:$O$763) | I53: =G53-H53 | J53: =I53+M53 | K53: =SUMIF('03_Eventos_pagamentos'!$P$11:$P$843,A54,'03_Eventos_pagamentos'!$Q$11:$Q$843) | L53: =K53+L52 | M53: =SUMIFS( '03_Eventos_pagamentos'!$O$11:$O$843,'03_Eventos_pagamentos'!$E$11:$E$843,A53,'03_Eventos_pagamentos'!$I$11:$I$843,"FAT. DIRETO") | N53: =K53+M53+N52 | P53: =O53+P52 | R53: =R52+Q53
A54: 41 | B54: =SUM(COUNTIF('03_Eventos_pagamentos'!$E$11:$E$697,'04_TOTALIZADORA'!A54)+COUNTIF('03_Eventos_pagamentos'!$E$766:$E$836,'04_TOTALIZADORA'!A54)) | C54: =SUMIF('03_Eventos_pagamentos'!$E$11:$E$699,A54,'03_Eventos_pagamentos'!$O$11:$O$697)+SUMIF('03_Eventos_pagamentos'!$E$766:$E$836,A54,'03_Eventos_pagamentos'!$O$766:$O$836) | D54: =COUNTIF('03_Eventos_pagamentos'!$E$702:$E$763,'04_TOTALIZADORA'!A54) | E54: =SUMIF('03_Eventos_pagamentos'!$E$702:$E$763,A54,'03_Eventos_pagamentos'!$O$702:$O$763) | F54: =C54+E54+F53 | G54: =C54+E54-M54 | H54: =SUMIF('03_Eventos_pagamentos'!$E$702:$E$763,F54,'03_Eventos_pagamentos'!$O$702:$O$763) | I54: =G54-H54 | J54: =I54+M54 | K54: =SUMIF('03_Eventos_pagamentos'!$P$11:$P$843,A55,'03_Eventos_pagamentos'!$Q$11:$Q$843) | L54: =K54+L53 | M54: =SUMIFS( '03_Eventos_pagamentos'!$O$11:$O$843,'03_Eventos_pagamentos'!$E$11:$E$843,A54,'03_Eventos_pagamentos'!$I$11:$I$843,"FAT. DIRETO") | N54: =K54+M54+N53 | P54: =O54+P53 | R54: =R53+Q54
A55: 42 | B55: =SUM(COUNTIF('03_Eventos_pagamentos'!$E$11:$E$697,'04_TOTALIZADORA'!A55)+COUNTIF('03_Eventos_pagamentos'!$E$766:$E$836,'04_TOTALIZADORA'!A55)) | C55: =SUMIF('03_Eventos_pagamentos'!$E$11:$E$699,A55,'03_Eventos_pagamentos'!$O$11:$O$697)+SUMIF('03_Eventos_pagamentos'!$E$766:$E$836,A55,'03_Eventos_pagamentos'!$O$766:$O$836) | D55: =COUNTIF('03_Eventos_pagamentos'!$E$702:$E$763,'04_TOTALIZADORA'!A55) | E55: =SUMIF('03_Eventos_pagamentos'!$E$702:$E$763,A55,'03_Eventos_pagamentos'!$O$702:$O$763) | F55: =C55+E55+F54 | G55: =C55+E55-M55 | H55: =SUMIF('03_Eventos_pagamentos'!$E$702:$E$763,F55,'03_Eventos_pagamentos'!$O$702:$O$763) | I55: =G55-H55 | J55: =I55+M55 | K55: =SUMIF('03_Eventos_pagamentos'!$P$11:$P$843,A56,'03_Eventos_pagamentos'!$Q$11:$Q$843) | L55: =K55+L54 | M55: =SUMIFS( '03_Eventos_pagamentos'!$O$11:$O$843,'03_Eventos_pagamentos'!$E$11:$E$843,A55,'03_Eventos_pagamentos'!$I$11:$I$843,"FAT. DIRETO") | N55: =K55+M55+N54 | P55: =O55+P54 | Q55: 113319.22 | R55: =R54+Q55
A56: 43 | B56: =SUM(COUNTIF('03_Eventos_pagamentos'!$E$11:$E$697,'04_TOTALIZADORA'!A56)+COUNTIF('03_Eventos_pagamentos'!$E$766:$E$836,'04_TOTALIZADORA'!A56)) | C56: =SUMIF('03_Eventos_pagamentos'!$E$11:$E$699,A56,'03_Eventos_pagamentos'!$O$11:$O$697)+SUMIF('03_Eventos_pagamentos'!$E$766:$E$836,A56,'03_Eventos_pagamentos'!$O$766:$O$836) | D56: =COUNTIF('03_Eventos_pagamentos'!$E$702:$E$763,'04_TOTALIZADORA'!A56) | E56: =SUMIF('03_Eventos_pagamentos'!$E$702:$E$763,A56,'03_Eventos_pagamentos'!$O$702:$O$763) | F56: =C56+E56+F55 | G56: =C56+E56-M56 | H56: =SUMIF('03_Eventos_pagamentos'!$E$702:$E$763,F56,'03_Eventos_pagamentos'!$O$702:$O$763) | I56: =G56-H56 | J56: =I56+M56 | K56: =SUMIF('03_Eventos_pagamentos'!$P$11:$P$843,A57,'03_Eventos_pagamentos'!$Q$11:$Q$843) | L56: =K56+L55 | M56: =SUMIFS( '03_Eventos_pagamentos'!$O$11:$O$843,'03_Eventos_pagamentos'!$E$11:$E$843,A56,'03_Eventos_pagamentos'!$I$11:$I$843,"FAT. DIRETO") | N56: =K56+M56+N55 | P56: =O56+P55 | R56: =R55+Q56
A57: 44 | B57: =SUM(COUNTIF('03_Eventos_pagamentos'!$E$11:$E$697,'04_TOTALIZADORA'!A57)+COUNTIF('03_Eventos_pagamentos'!$E$766:$E$836,'04_TOTALIZADORA'!A57)) | C57: =SUMIF('03_Eventos_pagamentos'!$E$11:$E$699,A57,'03_Eventos_pagamentos'!$O$11:$O$697)+SUMIF('03_Eventos_pagamentos'!$E$766:$E$836,A57,'03_Eventos_pagamentos'!$O$766:$O$836) | D57: =COUNTIF('03_Eventos_pagamentos'!$E$702:$E$763,'04_TOTALIZADORA'!A57) | E57: =SUMIF('03_Eventos_pagamentos'!$E$702:$E$763,A57,'03_Eventos_pagamentos'!$O$702:$O$763) | F57: =C57+E57+F56 | G57: =C57+E57-M57 | H57: =SUMIF('03_Eventos_pagamentos'!$E$702:$E$763,F57,'03_Eventos_pagamentos'!$O$702:$O$763) | I57: =G57-H57 | J57: =I57+M57 | K57: =SUMIF('03_Eventos_pagamentos'!$P$11:$P$843,A58,'03_Eventos_pagamentos'!$Q$11:$Q$843) | L57: =K57+L56 | M57: =SUMIFS( '03_Eventos_pagamentos'!$O$11:$O$843,'03_Eventos_pagamentos'!$E$11:$E$843,A57,'03_Eventos_pagamentos'!$I$11:$I$843,"FAT. DIRETO") | N57: =K57+M57+N56 | P57: =O57+P56 | R57: =R56+Q57
A58: 45 | B58: =SUM(COUNTIF('03_Eventos_pagamentos'!$E$11:$E$697,'04_TOTALIZADORA'!A58)+COUNTIF('03_Eventos_pagamentos'!$E$766:$E$836,'04_TOTALIZADORA'!A58)) | C58: =SUMIF('03_Eventos_pagamentos'!$E$11:$E$699,A58,'03_Eventos_pagamentos'!$O$11:$O$697)+SUMIF('03_Eventos_pagamentos'!$E$766:$E$836,A58,'03_Eventos_pagamentos'!$O$766:$O$836) | D58: =COUNTIF('03_Eventos_pagamentos'!$E$702:$E$763,'04_TOTALIZADORA'!A58) | E58: =SUMIF('03_Eventos_pagamentos'!$E$702:$E$763,A58,'03_Eventos_pagamentos'!$O$702:$O$763) | F58: =C58+E58+F57 | G58: =C58+E58-M58 | H58: =SUMIF('03_Eventos_pagamentos'!$E$702:$E$763,F58,'03_Eventos_pagamentos'!$O$702:$O$763) | I58: =G58-H58 | J58: =I58+M58 | K58: =SUMIF('03_Eventos_pagamentos'!$P$11:$P$843,A59,'03_Eventos_pagamentos'!$Q$11:$Q$843) | L58: =K58+L57 | M58: =SUMIFS( '03_Eventos_pagamentos'!$O$11:$O$843,'03_Eventos_pagamentos'!$E$11:$E$843,A58,'03_Eventos_pagamentos'!$I$11:$I$843,"FAT. DIRETO") | N58: =K58+M58+N57 | P58: =O58+P57 | R58: =R57+Q58
A59: 46 | B59: =SUM(COUNTIF('03_Eventos_pagamentos'!$E$11:$E$697,'04_TOTALIZADORA'!A59)+COUNTIF('03_Eventos_pagamentos'!$E$766:$E$836,'04_TOTALIZADORA'!A59)) | C59: =SUMIF('03_Eventos_pagamentos'!$E$11:$E$699,A59,'03_Eventos_pagamentos'!$O$11:$O$697)+SUMIF('03_Eventos_pagamentos'!$E$766:$E$836,A59,'03_Eventos_pagamentos'!$O$766:$O$836) | D59: =COUNTIF('03_Eventos_pagamentos'!$E$702:$E$763,'04_TOTALIZADORA'!A59) | E59: =SUMIF('03_Eventos_pagamentos'!$E$702:$E$763,A59,'03_Eventos_pagamentos'!$O$702:$O$763) | F59: =C59+E59+F58 | G59: =C59+E59-M59 | H59: =SUMIF('03_Eventos_pagamentos'!$E$702:$E$763,F59,'03_Eventos_pagamentos'!$O$702:$O$763) | I59: =G59-H59 | J59: =I59+M59 | K59: =SUMIF('03_Eventos_pagamentos'!$P$11:$P$843,A60,'03_Eventos_pagamentos'!$Q$11:$Q$843) | L59: =K59+L58 | M59: =SUMIFS( '03_Eventos_pagamentos'!$O$11:$O$843,'03_Eventos_pagamentos'!$E$11:$E$843,A59,'03_Eventos_pagamentos'!$I$11:$I$843,"FAT. DIRETO") | N59: =K59+M59+N58 | P59: =O59+P58 | R59: =R58+Q59
A60: 47 | B60: =SUM(COUNTIF('03_Eventos_pagamentos'!$E$11:$E$697,'04_TOTALIZADORA'!A60)+COUNTIF('03_Eventos_pagamentos'!$E$766:$E$836,'04_TOTALIZADORA'!A60)) | C60: =SUMIF('03_Eventos_pagamentos'!$E$11:$E$699,A60,'03_Eventos_pagamentos'!$O$11:$O$697)+SUMIF('03_Eventos_pagamentos'!$E$766:$E$836,A60,'03_Eventos_pagamentos'!$O$766:$O$836) | D60: =COUNTIF('03_Eventos_pagamentos'!$E$702:$E$763,'04_TOTALIZADORA'!A60) | E60: =SUMIF('03_Eventos_pagamentos'!$E$702:$E$763,A60,'03_Eventos_pagamentos'!$O$702:$O$763) | F60: =C60+E60+F59 | G60: =C60+E60-M60 | H60: =SUMIF('03_Eventos_pagamentos'!$E$702:$E$763,F60,'03_Eventos_pagamentos'!$O$702:$O$763) | I60: =G60-H60 | J60: =I60+M60 | K60: =SUMIF('03_Eventos_pagamentos'!$P$11:$P$843,A61,'03_Eventos_pagamentos'!$Q$11:$Q$843) | L60: =K60+L59 | M60: =SUMIFS( '03_Eventos_pagamentos'!$O$11:$O$843,'03_Eventos_pagamentos'!$E$11:$E$843,A60,'03_Eventos_pagamentos'!$I$11:$I$843,"FAT. DIRETO") | N60: =K60+M60+N59 | P60: =O60+P59 | R60: =R59+Q60
A61: 48 | B61: =SUM(COUNTIF('03_Eventos_pagamentos'!$E$11:$E$697,'04_TOTALIZADORA'!A61)+COUNTIF('03_Eventos_pagamentos'!$E$766:$E$836,'04_TOTALIZADORA'!A61)) | C61: =SUMIF('03_Eventos_pagamentos'!$E$11:$E$699,A61,'03_Eventos_pagamentos'!$O$11:$O$697)+SUMIF('03_Eventos_pagamentos'!$E$766:$E$836,A61,'03_Eventos_pagamentos'!$O$766:$O$836) | D61: =COUNTIF('03_Eventos_pagamentos'!$E$702:$E$763,'04_TOTALIZADORA'!A61) | E61: =SUMIF('03_Eventos_pagamentos'!$E$702:$E$763,A61,'03_Eventos_pagamentos'!$O$702:$O$763) | F61: =C61+E61+F60 | G61: =C61+E61-M61 | H61: =SUMIF('03_Eventos_pagamentos'!$E$702:$E$763,F61,'03_Eventos_pagamentos'!$O$702:$O$763) | I61: =G61-H61 | J61: =I61+M61 | K61: =SUMIF('03_Eventos_pagamentos'!$P$11:$P$843,A62,'03_Eventos_pagamentos'!$Q$11:$Q$843) | L61: =K61+L60 | M61: =SUMIFS( '03_Eventos_pagamentos'!$O$11:$O$843,'03_Eventos_pagamentos'!$E$11:$E$843,A61,'03_Eventos_pagamentos'!$I$11:$I$843,"FAT. DIRETO") | N61: =K61+M61+N60 | P61: =O61+P60 | R61: =R60+Q61
A62: 49 | B62: =SUM(COUNTIF('03_Eventos_pagamentos'!$E$11:$E$697,'04_TOTALIZADORA'!A62)+COUNTIF('03_Eventos_pagamentos'!$E$766:$E$836,'04_TOTALIZADORA'!A62)) | C62: =SUMIF('03_Eventos_pagamentos'!$E$11:$E$699,A62,'03_Eventos_pagamentos'!$O$11:$O$697)+SUMIF('03_Eventos_pagamentos'!$E$766:$E$836,A62,'03_Eventos_pagamentos'!$O$766:$O$836) | D62: =COUNTIF('03_Eventos_pagamentos'!$E$702:$E$763,'04_TOTALIZADORA'!A62) | E62: =SUMIF('03_Eventos_pagamentos'!$E$702:$E$763,A62,'03_Eventos_pagamentos'!$O$702:$O$763) | F62: =C62+E62+F61 | G62: =C62+E62-M62 | H62: =SUMIF('03_Eventos_pagamentos'!$E$702:$E$763,F62,'03_Eventos_pagamentos'!$O$702:$O$763) | I62: =G62-H62 | J62: =I62+M62 | K62: =SUMIF('03_Eventos_pagamentos'!$P$11:$P$843,A63,'03_Eventos_pagamentos'!$Q$11:$Q$843) | L62: =K62+L61 | M62: =SUMIFS( '03_Eventos_pagamentos'!$O$11:$O$843,'03_Eventos_pagamentos'!$E$11:$E$843,A62,'03_Eventos_pagamentos'!$I$11:$I$843,"FAT. DIRETO") | N62: =K62+M62+N61 | P62: =O62+P61 | R62: =R61+Q62
A63: 50 | B63: =SUM(COUNTIF('03_Eventos_pagamentos'!$E$11:$E$697,'04_TOTALIZADORA'!A63)+COUNTIF('03_Eventos_pagamentos'!$E$766:$E$836,'04_TOTALIZADORA'!A63)) | C63: =SUMIF('03_Eventos_pagamentos'!$E$11:$E$699,A63,'03_Eventos_pagamentos'!$O$11:$O$697)+SUMIF('03_Eventos_pagamentos'!$E$766:$E$836,A63,'03_Eventos_pagamentos'!$O$766:$O$836) | D63: =COUNTIF('03_Eventos_pagamentos'!$E$702:$E$763,'04_TOTALIZADORA'!A63) | E63: =SUMIF('03_Eventos_pagamentos'!$E$702:$E$763,A63,'03_Eventos_pagamentos'!$O$702:$O$763) | F63: =C63+E63+F62 | G63: =C63+E63-M63 | H63: =SUMIF('03_Eventos_pagamentos'!$E$702:$E$763,F63,'03_Eventos_pagamentos'!$O$702:$O$763) | I63: =G63-H63 | J63: =I63+M63 | K63: =SUMIF('03_Eventos_pagamentos'!$P$11:$P$843,A64,'03_Eventos_pagamentos'!$Q$11:$Q$843) | L63: =K63+L62 | M63: =SUMIFS( '03_Eventos_pagamentos'!$O$11:$O$843,'03_Eventos_pagamentos'!$E$11:$E$843,A63,'03_Eventos_pagamentos'!$I$11:$I$843,"FAT. DIRETO") | N63: =K63+M63+N62 | P63: =O63+P62 | R63: =R62+Q63
A64: 51 | B64: =SUM(COUNTIF('03_Eventos_pagamentos'!$E$11:$E$697,'04_TOTALIZADORA'!A64)+COUNTIF('03_Eventos_pagamentos'!$E$766:$E$836,'04_TOTALIZADORA'!A64)) | C64: =SUMIF('03_Eventos_pagamentos'!$E$11:$E$699,A64,'03_Eventos_pagamentos'!$O$11:$O$697)+SUMIF('03_Eventos_pagamentos'!$E$766:$E$836,A64,'03_Eventos_pagamentos'!$O$766:$O$836) | D64: =COUNTIF('03_Eventos_pagamentos'!$E$702:$E$763,'04_TOTALIZADORA'!A64) | E64: =SUMIF('03_Eventos_pagamentos'!$E$702:$E$763,A64,'03_Eventos_pagamentos'!$O$702:$O$763) | F64: =C64+E64+F63 | G64: =C64+E64-M64 | H64: =SUMIF('03_Eventos_pagamentos'!$E$702:$E$763,F64,'03_Eventos_pagamentos'!$O$702:$O$763) | I64: =G64-H64 | J64: =I64+M64 | K64: =SUMIF('03_Eventos_pagamentos'!$P$11:$P$843,A65,'03_Eventos_pagamentos'!$Q$11:$Q$843) | L64: =K64+L63 | M64: =SUMIFS( '03_Eventos_pagamentos'!$O$11:$O$843,'03_Eventos_pagamentos'!$E$11:$E$843,A64,'03_Eventos_pagamentos'!$I$11:$I$843,"FAT. DIRETO") | N64: =K64+M64+N63 | P64: =O64+P63 | R64: =R63+Q64
A65: 52 | B65: =SUM(COUNTIF('03_Eventos_pagamentos'!$E$11:$E$697,'04_TOTALIZADORA'!A65)+COUNTIF('03_Eventos_pagamentos'!$E$766:$E$836,'04_TOTALIZADORA'!A65)) | C65: =SUMIF('03_Eventos_pagamentos'!$E$11:$E$699,A65,'03_Eventos_pagamentos'!$O$11:$O$697)+SUMIF('03_Eventos_pagamentos'!$E$766:$E$836,A65,'03_Eventos_pagamentos'!$O$766:$O$836) | D65: =COUNTIF('03_Eventos_pagamentos'!$E$702:$E$763,'04_TOTALIZADORA'!A65) | E65: =SUMIF('03_Eventos_pagamentos'!$E$702:$E$763,A65,'03_Eventos_pagamentos'!$O$702:$O$763) | F65: =C65+E65+F64 | G65: =C65+E65-M65 | H65: =SUMIF('03_Eventos_pagamentos'!$E$702:$E$763,F65,'03_Eventos_pagamentos'!$O$702:$O$763) | I65: =G65-H65 | J65: =I65+M65 | K65: =SUMIF('03_Eventos_pagamentos'!$P$11:$P$843,A66,'03_Eventos_pagamentos'!$Q$11:$Q$843) | L65: =K65+L64 | M65: =SUMIFS( '03_Eventos_pagamentos'!$O$11:$O$843,'03_Eventos_pagamentos'!$E$11:$E$843,A65,'03_Eventos_pagamentos'!$I$11:$I$843,"FAT. DIRETO") | N65: =K65+M65+N64 | P65: =O65+P64 | R65: =R64+Q65
A66: 53 | B66: =SUM(COUNTIF('03_Eventos_pagamentos'!$E$11:$E$697,'04_TOTALIZADORA'!A66)+COUNTIF('03_Eventos_pagamentos'!$E$766:$E$836,'04_TOTALIZADORA'!A66)) | C66: =SUMIF('03_Eventos_pagamentos'!$E$11:$E$699,A66,'03_Eventos_pagamentos'!$O$11:$O$697)+SUMIF('03_Eventos_pagamentos'!$E$766:$E$836,A66,'03_Eventos_pagamentos'!$O$766:$O$836) | D66: =COUNTIF('03_Eventos_pagamentos'!$E$702:$E$763,'04_TOTALIZADORA'!A66) | E66: =SUMIF('03_Eventos_pagamentos'!$E$702:$E$763,A66,'03_Eventos_pagamentos'!$O$702:$O$763) | F66: =C66+E66+F65 | G66: =C66+E66-M66 | H66: =SUMIF('03_Eventos_pagamentos'!$E$702:$E$763,F66,'03_Eventos_pagamentos'!$O$702:$O$763) | I66: =G66-H66 | J66: =I66+M66 | K66: =SUMIF('03_Eventos_pagamentos'!$P$11:$P$843,A67,'03_Eventos_pagamentos'!$Q$11:$Q$843) | L66: =K66+L65 | M66: =SUMIFS( '03_Eventos_pagamentos'!$O$11:$O$843,'03_Eventos_pagamentos'!$E$11:$E$843,A66,'03_Eventos_pagamentos'!$I$11:$I$843,"FAT. DIRETO") | N66: =K66+M66+N65 | P66: =O66+P65 | Q66: 124651.83 | R66: =R65+Q66
A67: 54 | B67: =SUM(COUNTIF('03_Eventos_pagamentos'!$E$11:$E$697,'04_TOTALIZADORA'!A67)+COUNTIF('03_Eventos_pagamentos'!$E$766:$E$836,'04_TOTALIZADORA'!A67)) | C67: =SUMIF('03_Eventos_pagamentos'!$E$11:$E$699,A67,'03_Eventos_pagamentos'!$O$11:$O$697)+SUMIF('03_Eventos_pagamentos'!$E$766:$E$836,A67,'03_Eventos_pagamentos'!$O$766:$O$836) | D67: =COUNTIF('03_Eventos_pagamentos'!$E$702:$E$763,'04_TOTALIZADORA'!A67) | E67: =SUMIF('03_Eventos_pagamentos'!$E$702:$E$763,A67,'03_Eventos_pagamentos'!$O$702:$O$763) | F67: =C67+E67+F66 | G67: =C67+E67-M67 | H67: =SUMIF('03_Eventos_pagamentos'!$E$702:$E$763,F67,'03_Eventos_pagamentos'!$O$702:$O$763) | I67: =G67-H67 | J67: =I67+M67 | K67: =SUMIF('03_Eventos_pagamentos'!$P$11:$P$843,A68,'03_Eventos_pagamentos'!$Q$11:$Q$843) | L67: =K67+L66 | M67: =SUMIFS( '03_Eventos_pagamentos'!$O$11:$O$843,'03_Eventos_pagamentos'!$E$11:$E$843,A67,'03_Eventos_pagamentos'!$I$11:$I$843,"FAT. DIRETO") | N67: =K67+M67+N66 | P67: =O67+P66 | R67: =R66+Q67
A68: 55 | B68: =SUM(COUNTIF('03_Eventos_pagamentos'!$E$11:$E$697,'04_TOTALIZADORA'!A68)+COUNTIF('03_Eventos_pagamentos'!$E$766:$E$836,'04_TOTALIZADORA'!A68)) | C68: =SUMIF('03_Eventos_pagamentos'!$E$11:$E$699,A68,'03_Eventos_pagamentos'!$O$11:$O$697)+SUMIF('03_Eventos_pagamentos'!$E$766:$E$836,A68,'03_Eventos_pagamentos'!$O$766:$O$836) | D68: =COUNTIF('03_Eventos_pagamentos'!$E$702:$E$763,'04_TOTALIZADORA'!A68) | E68: =SUMIF('03_Eventos_pagamentos'!$E$702:$E$763,A68,'03_Eventos_pagamentos'!$O$702:$O$763) | F68: =C68+E68+F67 | G68: =C68+E68-M68 | H68: =SUMIF('03_Eventos_pagamentos'!$E$702:$E$763,F68,'03_Eventos_pagamentos'!$O$702:$O$763) | I68: =G68-H68 | J68: =I68+M68 | K68: =SUMIF('03_Eventos_pagamentos'!$P$11:$P$843,A69,'03_Eventos_pagamentos'!$Q$11:$Q$843) | L68: =K68+L67 | M68: =SUMIFS( '03_Eventos_pagamentos'!$O$11:$O$843,'03_Eventos_pagamentos'!$E$11:$E$843,A68,'03_Eventos_pagamentos'!$I$11:$I$843,"FAT. DIRETO") | N68: =K68+M68+N67 | P68: =O68+P67 | R68: =R67+Q68
A69: 56 | B69: =SUM(COUNTIF('03_Eventos_pagamentos'!$E$11:$E$697,'04_TOTALIZADORA'!A69)+COUNTIF('03_Eventos_pagamentos'!$E$766:$E$836,'04_TOTALIZADORA'!A69)) | C69: =SUMIF('03_Eventos_pagamentos'!$E$11:$E$699,A69,'03_Eventos_pagamentos'!$O$11:$O$697)+SUMIF('03_Eventos_pagamentos'!$E$766:$E$836,A69,'03_Eventos_pagamentos'!$O$766:$O$836) | D69: =COUNTIF('03_Eventos_pagamentos'!$E$702:$E$763,'04_TOTALIZADORA'!A69) | E69: =SUMIF('03_Eventos_pagamentos'!$E$702:$E$763,A69,'03_Eventos_pagamentos'!$O$702:$O$763) | F69: =C69+E69+F68 | G69: =C69+E69-M69 | H69: =SUMIF('03_Eventos_pagamentos'!$E$702:$E$763,F69,'03_Eventos_pagamentos'!$O$702:$O$763) | I69: =G69-H69 | J69: =I69+M69 | K69: =SUMIF('03_Eventos_pagamentos'!$P$11:$P$843,A70,'03_Eventos_pagamentos'!$Q$11:$Q$843) | L69: =K69+L68 | M69: =SUMIFS( '03_Eventos_pagamentos'!$O$11:$O$843,'03_Eventos_pagamentos'!$E$11:$E$843,A69,'03_Eventos_pagamentos'!$I$11:$I$843,"FAT. DIRETO") | N69: =K69+M69+N68 | P69: =O69+P68 | R69: =R68+Q69
A70: 57 | B70: =SUM(COUNTIF('03_Eventos_pagamentos'!$E$11:$E$697,'04_TOTALIZADORA'!A70)+COUNTIF('03_Eventos_pagamentos'!$E$766:$E$836,'04_TOTALIZADORA'!A70)) | C70: =SUMIF('03_Eventos_pagamentos'!$E$11:$E$699,A70,'03_Eventos_pagamentos'!$O$11:$O$697)+SUMIF('03_Eventos_pagamentos'!$E$766:$E$836,A70,'03_Eventos_pagamentos'!$O$766:$O$836) | D70: =COUNTIF('03_Eventos_pagamentos'!$E$702:$E$763,'04_TOTALIZADORA'!A70) | E70: =SUMIF('03_Eventos_pagamentos'!$E$702:$E$763,A70,'03_Eventos_pagamentos'!$O$702:$O$763) | F70: =C70+E70+F69 | G70: =C70+E70-M70 | H70: =SUMIF('03_Eventos_pagamentos'!$E$702:$E$763,F70,'03_Eventos_pagamentos'!$O$702:$O$763) | I70: =G70-H70 | J70: =I70+M70 | K70: =SUMIF('03_Eventos_pagamentos'!$P$11:$P$843,A71,'03_Eventos_pagamentos'!$Q$11:$Q$843) | L70: =K70+L69 | M70: =SUMIFS( '03_Eventos_pagamentos'!$O$11:$O$843,'03_Eventos_pagamentos'!$E$11:$E$843,A70,'03_Eventos_pagamentos'!$I$11:$I$843,"FAT. DIRETO") | N70: =K70+M70+N69 | P70: =O70+P69 | R70: =R69+Q70
A71: 58 | B71: =SUM(COUNTIF('03_Eventos_pagamentos'!$E$11:$E$697,'04_TOTALIZADORA'!A71)+COUNTIF('03_Eventos_pagamentos'!$E$766:$E$836,'04_TOTALIZADORA'!A71)) | C71: =SUMIF('03_Eventos_pagamentos'!$E$11:$E$699,A71,'03_Eventos_pagamentos'!$O$11:$O$697)+SUMIF('03_Eventos_pagamentos'!$E$766:$E$836,A71,'03_Eventos_pagamentos'!$O$766:$O$836) | D71: =COUNTIF('03_Eventos_pagamentos'!$E$702:$E$763,'04_TOTALIZADORA'!A71) | E71: =SUMIF('03_Eventos_pagamentos'!$E$702:$E$763,A71,'03_Eventos_pagamentos'!$O$702:$O$763) | F71: =C71+E71+F70 | G71: =C71+E71-M71 | H71: =SUMIF('03_Eventos_pagamentos'!$E$702:$E$763,F71,'03_Eventos_pagamentos'!$O$702:$O$763) | I71: =G71-H71 | J71: =I71+M71 | K71: =SUMIF('03_Eventos_pagamentos'!$P$11:$P$843,A72,'03_Eventos_pagamentos'!$Q$11:$Q$843) | L71: =K71+L70 | M71: =SUMIFS( '03_Eventos_pagamentos'!$O$11:$O$843,'03_Eventos_pagamentos'!$E$11:$E$843,A71,'03_Eventos_pagamentos'!$I$11:$I$843,"FAT. DIRETO") | N71: =K71+M71+N70 | P71: =O71+P70 | R71: =R70+Q71
A72: 59 | B72: =SUM(COUNTIF('03_Eventos_pagamentos'!$E$11:$E$697,'04_TOTALIZADORA'!A72)+COUNTIF('03_Eventos_pagamentos'!$E$766:$E$836,'04_TOTALIZADORA'!A72)) | C72: =SUMIF('03_Eventos_pagamentos'!$E$11:$E$699,A72,'03_Eventos_pagamentos'!$O$11:$O$697)+SUMIF('03_Eventos_pagamentos'!$E$766:$E$836,A72,'03_Eventos_pagamentos'!$O$766:$O$836) | D72: =COUNTIF('03_Eventos_pagamentos'!$E$702:$E$763,'04_TOTALIZADORA'!A72) | E72: =SUMIF('03_Eventos_pagamentos'!$E$702:$E$763,A72,'03_Eventos_pagamentos'!$O$702:$O$763) | F72: =C72+E72+F71 | G72: =C72+E72-M72 | H72: =SUMIF('03_Eventos_pagamentos'!$E$702:$E$763,F72,'03_Eventos_pagamentos'!$O$702:$O$763) | I72: =G72-H72 | J72: =I72+M72 | K72: =SUMIF('03_Eventos_pagamentos'!$P$11:$P$843,A73,'03_Eventos_pagamentos'!$Q$11:$Q$843) | L72: =K72+L71 | M72: =SUMIFS( '03_Eventos_pagamentos'!$O$11:$O$843,'03_Eventos_pagamentos'!$E$11:$E$843,A72,'03_Eventos_pagamentos'!$I$11:$I$843,"FAT. DIRETO") | N72: =K72+M72+N71 | P72: =O72+P71 | R72: =R71+Q72
A73: 60 | B73: =SUM(COUNTIF('03_Eventos_pagamentos'!$E$11:$E$697,'04_TOTALIZADORA'!A73)+COUNTIF('03_Eventos_pagamentos'!$E$766:$E$836,'04_TOTALIZADORA'!A73)) | C73: =SUMIF('03_Eventos_pagamentos'!$E$11:$E$699,A73,'03_Eventos_pagamentos'!$O$11:$O$697)+SUMIF('03_Eventos_pagamentos'!$E$766:$E$836,A73,'03_Eventos_pagamentos'!$O$766:$O$836) | D73: =COUNTIF('03_Eventos_pagamentos'!$E$702:$E$763,'04_TOTALIZADORA'!A73) | E73: =SUMIF('03_Eventos_pagamentos'!$E$702:$E$763,A73,'03_Eventos_pagamentos'!$O$702:$O$763) | F73: =C73+E73+F72 | G73: =C73+E73-M73 | H73: =SUMIF('03_Eventos_pagamentos'!$E$702:$E$763,F73,'03_Eventos_pagamentos'!$O$702:$O$763) | I73: =G73-H73 | J73: =I73+M73 | K73: =SUMIF('03_Eventos_pagamentos'!$P$11:$P$843,A74,'03_Eventos_pagamentos'!$Q$11:$Q$843) | L73: =K73+L72 | M73: =SUMIFS( '03_Eventos_pagamentos'!$O$11:$O$843,'03_Eventos_pagamentos'!$E$11:$E$843,A73,'03_Eventos_pagamentos'!$I$11:$I$843,"FAT. DIRETO") | N73: =K73+M73+N72 | P73: =O73+P72 | R73: =R72+Q73
A74: 61 | B74: =SUM(COUNTIF('03_Eventos_pagamentos'!$E$11:$E$697,'04_TOTALIZADORA'!A74)+COUNTIF('03_Eventos_pagamentos'!$E$766:$E$836,'04_TOTALIZADORA'!A74)) | C74: =SUMIF('03_Eventos_pagamentos'!$E$11:$E$699,A74,'03_Eventos_pagamentos'!$O$11:$O$697)+SUMIF('03_Eventos_pagamentos'!$E$766:$E$836,A74,'03_Eventos_pagamentos'!$O$766:$O$836) | D74: =COUNTIF('03_Eventos_pagamentos'!$E$702:$E$763,'04_TOTALIZADORA'!A74) | E74: =SUMIF('03_Eventos_pagamentos'!$E$702:$E$763,A74,'03_Eventos_pagamentos'!$O$702:$O$763) | F74: =C74+E74+F73 | G74: =C74+E74-M74 | H74: =SUMIF('03_Eventos_pagamentos'!$E$702:$E$763,F74,'03_Eventos_pagamentos'!$O$702:$O$763) | I74: =G74-H74 | J74: =I74+M74 | K74: =SUMIF('03_Eventos_pagamentos'!$P$11:$P$843,A75,'03_Eventos_pagamentos'!$Q$11:$Q$843) | L74: =K74+L73 | M74: =SUMIFS( '03_Eventos_pagamentos'!$O$11:$O$843,'03_Eventos_pagamentos'!$E$11:$E$843,A74,'03_Eventos_pagamentos'!$I$11:$I$843,"FAT. DIRETO") | N74: =K74+M74+N73 | P74: =O74+P73 | R74: =R73+Q74
A75: 62 | B75: =SUM(COUNTIF('03_Eventos_pagamentos'!$E$11:$E$697,'04_TOTALIZADORA'!A75)+COUNTIF('03_Eventos_pagamentos'!$E$766:$E$836,'04_TOTALIZADORA'!A75)) | C75: =SUMIF('03_Eventos_pagamentos'!$E$11:$E$699,A75,'03_Eventos_pagamentos'!$O$11:$O$697)+SUMIF('03_Eventos_pagamentos'!$E$766:$E$836,A75,'03_Eventos_pagamentos'!$O$766:$O$836) | D75: =COUNTIF('03_Eventos_pagamentos'!$E$702:$E$763,'04_TOTALIZADORA'!A75) | E75: =SUMIF('03_Eventos_pagamentos'!$E$702:$E$763,A75,'03_Eventos_pagamentos'!$O$702:$O$763) | F75: =C75+E75+F74 | G75: =C75+E75-M75 | H75: =SUMIF('03_Eventos_pagamentos'!$E$702:$E$763,F75,'03_Eventos_pagamentos'!$O$702:$O$763) | I75: =G75-H75 | J75: =I75+M75 | K75: =SUMIF('03_Eventos_pagamentos'!$P$11:$P$843,A76,'03_Eventos_pagamentos'!$Q$11:$Q$843) | L75: =K75+L74 | M75: =SUMIFS( '03_Eventos_pagamentos'!$O$11:$O$843,'03_Eventos_pagamentos'!$E$11:$E$843,A75,'03_Eventos_pagamentos'!$I$11:$I$843,"FAT. DIRETO") | N75: =K75+M75+N74 | P75: =O75+P74 | R75: =R74+Q75
A76: 63 | B76: =SUM(COUNTIF('03_Eventos_pagamentos'!$E$11:$E$697,'04_TOTALIZADORA'!A76)+COUNTIF('03_Eventos_pagamentos'!$E$766:$E$836,'04_TOTALIZADORA'!A76)) | C76: =SUMIF('03_Eventos_pagamentos'!$E$11:$E$699,A76,'03_Eventos_pagamentos'!$O$11:$O$697)+SUMIF('03_Eventos_pagamentos'!$E$766:$E$836,A76,'03_Eventos_pagamentos'!$O$766:$O$836) | D76: =COUNTIF('03_Eventos_pagamentos'!$E$702:$E$763,'04_TOTALIZADORA'!A76) | E76: =SUMIF('03_Eventos_pagamentos'!$E$702:$E$763,A76,'03_Eventos_pagamentos'!$O$702:$O$763) | F76: =C76+E76+F75 | G76: =C76+E76-M76 | H76: =SUMIF('03_Eventos_pagamentos'!$E$702:$E$763,F76,'03_Eventos_pagamentos'!$O$702:$O$763) | I76: =G76-H76 | J76: =I76+M76 | K76: =SUMIF('03_Eventos_pagamentos'!$P$11:$P$843,A77,'03_Eventos_pagamentos'!$Q$11:$Q$843) | L76: =K76+L75 | M76: =SUMIFS( '03_Eventos_pagamentos'!$O$11:$O$843,'03_Eventos_pagamentos'!$E$11:$E$843,A76,'03_Eventos_pagamentos'!$I$11:$I$843,"FAT. DIRETO") | N76: =K76+M76+N75 | P76: =O76+P75 | R76: =R75+Q76
A77: 64 | B77: =SUM(COUNTIF('03_Eventos_pagamentos'!$E$11:$E$697,'04_TOTALIZADORA'!A77)+COUNTIF('03_Eventos_pagamentos'!$E$766:$E$836,'04_TOTALIZADORA'!A77)) | C77: =SUMIF('03_Eventos_pagamentos'!$E$11:$E$699,A77,'03_Eventos_pagamentos'!$O$11:$O$697)+SUMIF('03_Eventos_pagamentos'!$E$766:$E$836,A77,'03_Eventos_pagamentos'!$O$766:$O$836) | D77: =COUNTIF('03_Eventos_pagamentos'!$E$702:$E$763,'04_TOTALIZADORA'!A77) | E77: =SUMIF('03_Eventos_pagamentos'!$E$702:$E$763,A77,'03_Eventos_pagamentos'!$O$702:$O$763) | F77: =C77+E77+F76 | G77: =C77+E77-M77 | H77: =SUMIF('03_Eventos_pagamentos'!$E$702:$E$763,F77,'03_Eventos_pagamentos'!$O$702:$O$763) | I77: =G77-H77 | J77: =I77+M77 | K77: =SUMIF('03_Eventos_pagamentos'!$P$11:$P$843,A78,'03_Eventos_pagamentos'!$Q$11:$Q$843) | L77: =K77+L76 | M77: =SUMIFS( '03_Eventos_pagamentos'!$O$11:$O$843,'03_Eventos_pagamentos'!$E$11:$E$843,A77,'03_Eventos_pagamentos'!$I$11:$I$843,"FAT. DIRETO") | N77: =K77+M77+N76 | P77: =O77+P76 | R77: =R76+Q77
A78: 65 | B78: =SUM(COUNTIF('03_Eventos_pagamentos'!$E$11:$E$697,'04_TOTALIZADORA'!A78)+COUNTIF('03_Eventos_pagamentos'!$E$766:$E$836,'04_TOTALIZADORA'!A78)) | C78: =SUMIF('03_Eventos_pagamentos'!$E$11:$E$699,A78,'03_Eventos_pagamentos'!$O$11:$O$697)+SUMIF('03_Eventos_pagamentos'!$E$766:$E$836,A78,'03_Eventos_pagamentos'!$O$766:$O$836) | D78: =COUNTIF('03_Eventos_pagamentos'!$E$702:$E$763,'04_TOTALIZADORA'!A78) | E78: =SUMIF('03_Eventos_pagamentos'!$E$702:$E$763,A78,'03_Eventos_pagamentos'!$O$702:$O$763) | F78: =C78+E78+F77 | G78: =C78+E78-M78 | H78: =SUMIF('03_Eventos_pagamentos'!$E$702:$E$763,F78,'03_Eventos_pagamentos'!$O$702:$O$763) | I78: =G78-H78 | J78: =I78+M78 | K78: =SUMIF('03_Eventos_pagamentos'!$P$11:$P$843,A79,'03_Eventos_pagamentos'!$Q$11:$Q$843) | L78: =K78+L77 | M78: =SUMIFS( '03_Eventos_pagamentos'!$O$11:$O$843,'03_Eventos_pagamentos'!$E$11:$E$843,A78,'03_Eventos_pagamentos'!$I$11:$I$843,"FAT. DIRETO") | N78: =K78+M78+N77 | P78: =O78+P77 | R78: =R77+Q78
A79: 66 | B79: =SUM(COUNTIF('03_Eventos_pagamentos'!$E$11:$E$697,'04_TOTALIZADORA'!A79)+COUNTIF('03_Eventos_pagamentos'!$E$766:$E$836,'04_TOTALIZADORA'!A79)) | C79: =SUMIF('03_Eventos_pagamentos'!$E$11:$E$699,A79,'03_Eventos_pagamentos'!$O$11:$O$697)+SUMIF('03_Eventos_pagamentos'!$E$766:$E$836,A79,'03_Eventos_pagamentos'!$O$766:$O$836) | D79: =COUNTIF('03_Eventos_pagamentos'!$E$702:$E$763,'04_TOTALIZADORA'!A79) | E79: =SUMIF('03_Eventos_pagamentos'!$E$702:$E$763,A79,'03_Eventos_pagamentos'!$O$702:$O$763) | F79: =C79+E79+F78 | G79: =C79+E79-M79 | H79: =SUMIF('03_Eventos_pagamentos'!$E$702:$E$763,F79,'03_Eventos_pagamentos'!$O$702:$O$763) | I79: =G79-H79 | J79: =I79+M79 | K79: =SUMIF('03_Eventos_pagamentos'!$P$11:$P$843,A80,'03_Eventos_pagamentos'!$Q$11:$Q$843) | L79: =K79+L78 | M79: =SUMIFS( '03_Eventos_pagamentos'!$O$11:$O$843,'03_Eventos_pagamentos'!$E$11:$E$843,A79,'03_Eventos_pagamentos'!$I$11:$I$843,"FAT. DIRETO") | N79: =K79+M79+N78 | P79: =O79+P78 | R79: =R78+Q79 | W79: VALOR AMORTIZADO | X79: =(SUM(O28,O30,O32)/0.85)*0.15
A80: 67 | B80: =SUM(COUNTIF('03_Eventos_pagamentos'!$E$11:$E$697,'04_TOTALIZADORA'!A80)+COUNTIF('03_Eventos_pagamentos'!$E$766:$E$836,'04_TOTALIZADORA'!A80)) | C80: =SUMIF('03_Eventos_pagamentos'!$E$11:$E$699,A80,'03_Eventos_pagamentos'!$O$11:$O$697)+SUMIF('03_Eventos_pagamentos'!$E$766:$E$836,A80,'03_Eventos_pagamentos'!$O$766:$O$836) | D80: =COUNTIF('03_Eventos_pagamentos'!$E$702:$E$763,'04_TOTALIZADORA'!A80) | E80: =SUMIF('03_Eventos_pagamentos'!$E$702:$E$763,A80,'03_Eventos_pagamentos'!$O$702:$O$763) | F80: =C80+E80+F79 | G80: =C80+E80-M80 | H80: =SUMIF('03_Eventos_pagamentos'!$E$702:$E$763,F80,'03_Eventos_pagamentos'!$O$702:$O$763) | I80: =G80-H80 | J80: =I80+M80 | K80: =SUMIF('03_Eventos_pagamentos'!$P$11:$P$843,A81,'03_Eventos_pagamentos'!$Q$11:$Q$843) | L80: =K80+L79 | M80: =SUMIFS( '03_Eventos_pagamentos'!$O$11:$O$843,'03_Eventos_pagamentos'!$E$11:$E$843,A80,'03_Eventos_pagamentos'!$I$11:$I$843,"FAT. DIRETO") | N80: =K80+M80+N79 | P80: =O80+P79 | R80: =R79+Q80
A81: 68 | B81: =SUM(COUNTIF('03_Eventos_pagamentos'!$E$11:$E$697,'04_TOTALIZADORA'!A81)+COUNTIF('03_Eventos_pagamentos'!$E$766:$E$836,'04_TOTALIZADORA'!A81)) | C81: =SUMIF('03_Eventos_pagamentos'!$E$11:$E$699,A81,'03_Eventos_pagamentos'!$O$11:$O$697)+SUMIF('03_Eventos_pagamentos'!$E$766:$E$836,A81,'03_Eventos_pagamentos'!$O$766:$O$836) | D81: =COUNTIF('03_Eventos_pagamentos'!$E$702:$E$763,'04_TOTALIZADORA'!A81) | E81: =SUMIF('03_Eventos_pagamentos'!$E$702:$E$763,A81,'03_Eventos_pagamentos'!$O$702:$O$763) | F81: =C81+E81+F80 | G81: =C81+E81-M81 | H81: =SUMIF('03_Eventos_pagamentos'!$E$702:$E$763,F81,'03_Eventos_pagamentos'!$O$702:$O$763) | I81: =G81-H81 | J81: =I81+M81 | K81: =SUMIF('03_Eventos_pagamentos'!$P$11:$P$843,A82,'03_Eventos_pagamentos'!$Q$11:$Q$843) | L81: =K81+L80 | M81: =SUMIFS( '03_Eventos_pagamentos'!$O$11:$O$843,'03_Eventos_pagamentos'!$E$11:$E$843,A81,'03_Eventos_pagamentos'!$I$11:$I$843,"FAT. DIRETO") | N81: =K81+M81+N80 | P81: =O81+P80 | R81: =R80+Q81
A82: 69 | B82: =SUM(COUNTIF('03_Eventos_pagamentos'!$E$11:$E$697,'04_TOTALIZADORA'!A82)+COUNTIF('03_Eventos_pagamentos'!$E$766:$E$836,'04_TOTALIZADORA'!A82)) | C82: =SUMIF('03_Eventos_pagamentos'!$E$11:$E$699,A82,'03_Eventos_pagamentos'!$O$11:$O$697)+SUMIF('03_Eventos_pagamentos'!$E$766:$E$836,A82,'03_Eventos_pagamentos'!$O$766:$O$836) | D82: =COUNTIF('03_Eventos_pagamentos'!$E$702:$E$763,'04_TOTALIZADORA'!A82) | E82: =SUMIF('03_Eventos_pagamentos'!$E$702:$E$763,A82,'03_Eventos_pagamentos'!$O$702:$O$763) | F82: =C82+E82+F81 | G82: =C82+E82-M82 | H82: =SUMIF('03_Eventos_pagamentos'!$E$702:$E$763,F82,'03_Eventos_pagamentos'!$O$702:$O$763) | I82: =G82-H82 | J82: =I82+M82 | K82: =SUMIF('03_Eventos_pagamentos'!$P$11:$P$843,A83,'03_Eventos_pagamentos'!$Q$11:$Q$843) | L82: =K82+L81 | M82: =SUMIFS( '03_Eventos_pagamentos'!$O$11:$O$843,'03_Eventos_pagamentos'!$E$11:$E$843,A82,'03_Eventos_pagamentos'!$I$11:$I$843,"FAT. DIRETO") | N82: =K82+M82+N81 | P82: =O82+P81 | R82: =R81+Q82
A83: Meses | B83: EVENTOS | C83: =B12 | D83: EVENTOS | E83: =D12 | F83: VALOR TOTAL | G83: VALOR TOTAL | H83: VALOR TOTAL | I83: VALOR TOTAL | J83: VALOR TOTAL | L83: VALOR TOTAL | M83: VALOR TOTAL | N83: VALOR TOTAL | P83: VALOR TOTAL | R83: VALOR TOTAL | S83: TOTAL EVENTOS | T83: PREÇO GLOBAL | U83: =SUM(C14:C82,E14:E82) | W83: VALOR ANTECIPAÇÃO SOLICITADA | X83: =S9
A84: 70 | B84: =SUM(B14:B82) | C84: =SUM(C14:C82) | D84: =SUM(D14:D82) | E84: =SUM(E14:E82) | F84: =SUM(C84,E84) | G84: =SUM(G14:G82) | H84: =SUM(H14:H82) | I84: =SUM(I14:I82) | J84: =SUM(J14:J82) | L84: =L82 | M84: =SUM(M14:M82) | N84: =N82 | P84: =P82 | R84: =R82 | S84: =SUM(B84,D84)
A86: Nota: Preencher somente a célula em destaque amarelo, campo de ANTECIPAÇÃO SOLICITADA, com o valor percentual referênte a solicitação de antecipação, de acordo com as regras do edital e limitado a 5% do VALOR GLOBAL da proposta, demais campos são de preenchimento automático, meramente ilustrativos, pois seguirão as disposições descritas na Minuta de Contrato.

Sheet BDI
B1: ATENÇÃO: SEGUE ABAIXO COMO EXEMPLO, TABELA DE BDI MERAMENTE ILUSTRATIVA. A PROPONENTE DEVE APRESENTAR A SUA COMPOSIÇÃO DE BDI.
B2: PLANILHA DE PREÇOS E EVENTOGRAMAS EXECUÇÃO DAS OBRAS DE REFORMA E MODERNIZAÇÃO DA UHE SALTO GRANDE E MODERNIZAÇÃO E DIGITALIZAÇÃO DA SE UHE SALTO GRANDE – ATIVOS CEMIG D
B3: GUIA COM INFORMAÇÕES DA COMPOSIÇÃO DO BDI
B5: ='01_Preço'!A4 | E5: =_xlfn.CONCAT('01_Preço'!M4," ",'01_Preço'!O4)
B6: NOME EMPRESA PROPONENTE: | D6: ='01_Preço'!C5
B7: Nº CNPJ: | C7: 14.162.225/0001-59 | D7: Nº INSCRIÇÃO ESTADUAL: | E7: ='01_Preço'!Q5
B8: REPRESENTANTE LEGAL: | C8: ='01_Preço'!C6
B9: Nº CPF: | C9: ='01_Preço'!L6 | D9: Nº DA IDENTIDADE: | E9: ='01_Preço'!Q6
B10: DATA DE EMISSÃO: | C10: ='01_Preço'!V5 | D10: BASE ECONÔMICA TRIBUTÁRIA: | E10: ='01_Preço'!V4
B11: ASSINATURA DO REPRESENTANTE LEGAL DA EMPRESA: | D11: ='01_Preço'!K7
C12: BONIFICAÇÕES E DESPESAS INDIRETAS - BDI - %
C13: DESCRIÇÃO DO ITEM | D13: %
C14: Administração Central | D14: 0.05
C15: Risco/Margem de incerteza | D15: 0.0127
C16: Seguros | D16: 0.0025
C17: Garantias | D17: 0.0025
C18: Despesas Financeiras | D18: 0.01
C19: Lucro | D19: 0.0615
C20: PIS | D20: 0.0065
C21: COFINS | D21: 0.03
C22: Simples Nacional
C23: Encargos Sociais
C24: Contribuição Previdenciária sobre a Receita Bruta (CPRB) | D24: 0.045
C25: TOTAL 1 | D25: =SUM(D14:D24)
C26: Outras Despesas:
C30: TOTAL 2 | D30: =SUM(D27:D29)
C31: TOTAL DO BDI | D31: =SUM(D25,D30)

Sheet 02_Sobressalent_Especif_CEMIG_D
B2: TABELA DE SOBRESSALENTES ESPECIFICADOS - CEMIG D
B3: ='01_Preço'!A4 | F3: BASE ECONÔMICA TRIBUTÁRIA | H3: ='01_Preço'!V4
F4: DATA DE EMISSÃO | H4: ='01_Preço'!V5
B5: EMPRESA PROPONENTE: | E5: ='01_Preço'!C5 | F5: Nº CNPJ: | H5: ='01_Preço'!L5
F6: Nº INSC ESTADUAL: | H6: ='01_Preço'!Q5
B7: REPRESENTANTE LEGAL: | E7: ='01_Preço'!C6 | F7: Nº CPF: | H7: ='01_Preço'!L6
F8: Nº IDENTIDADE: | H8: ='01_Preço'!Q6
B9: ASSINATURA REPRESENTANTE LEGAL EMPRESA: | E9: LOCAL PARA ASSINATURA OU INSERÇÃO DE ASSINATURA ELETRÔNICA | I9: Classif. Fiscal (NCM) | J9: Revenda (Sim/Não) | K9: II (%) | L9: IPI (%) | M9: CIDADE/ESTADO Origem do ICMS | N9: ICMS Origem (%) | O9: CIDADE/ESTADO Destino do ICMS | P9: ICMS Destino (%) | Q9: ICMS Substit. Tributaria (%) | R9: Identificação do Fornecedor País de origem | S9: CNAE
B10: ITEM | C10: EQUIPAMENTO/SISTEMA PRINCIPAL | E10: SOBRESSALENTES ESPECIFICADOS | F10: QTDE. | G10: UNID. | H10: VALOR TOTAL DO ITEM (R$) (com todos os Impostos, já incluso o ICMS a ser recolhido no Estado de destino.)
B11: 1 | C11: DISJUNTORES DE ALTA TENSÃO | D11: 376280 | E11: DISJUNTOR,SF6, 2000A,40kAEF,145kV,60Hz,230/550/-kV,TRIPOLAR,C/MOTOR 125VCC/125VCA, TENSÃO CONTROLE 125VCC,EXTERNO. ET-02118-CEMIG-275, 20000-PE/LS-202. | F11: 1 | G11: PÇ | H11: =229620+28380 | T11: =133952
B12: 2 | D12: 906447 | E12: PÓLO,COMPLETO,P/DISJUNTOR,TRIPOLAR,SF6, 3150A,40kA, 145kV,EXTERNO. ET-02118-CEMIG-275 | F12: 1 | G12: PÇ | H12: 39651.28 | T12: 66976
B13: 3 | D13: 379344 | E13: MECANISMO,OPERAÇÃO,COMPLETO,P/DISJUNTOR,TRIPOLAR,SF6,145kV,2000A,50kA,EXTERNO. ET-02118-CEMIG-275. | F13: 1 | G13: PÇ | H13: 28974.84 | T13: 66976
B14: 4 | D14: 906446 | E14: PÓLO,COMPLETO,P/DISJUNTOR TRIPOLAR,SF6, 72,5kV,2000A, EXTERNO. ET-02118-CEMIG-275 | F14: 1 | G14: PÇ | H14: 25416.62 | T14: =123019*0.5
B15: 5 | D15: 379193 | E15: MECANISMO,OPERAÇÃO,COMPLETO,P/DISJUNTOR TRIPOLAR,SF6, 72,5kV,EXTERNO. ET-02118-CEMIG-275. | F15: 1 | G15: PÇ | H15: 23633.95 | T15: 61509.5
B16: 6 | D16: 384082 | E16: DENSÍMETRO,MEDIDOR VOLUME GÁS SF6,P/DISJUNTOR,USO EXTERNO. ET-02111-CEMIG-275. | F16: 1 | G16: CJ | H16: 16513.95 | T16: 2966
B17: 7 | C17: SECIONADORES DE AT | D17: 273102 | E17: SECCIONADOR,TRIPOLAR,145kV,1250A,60Hz,230/550/-kV,IT20kAef,ID 50kAcr,MONTAGEM HORIZONTAL PÓLOS PARALELOS,SUPORTE POC-2 ABERTURA CENTRAL,MECANISMO OPERAÇÃO INDIRETO, S/LÂMINA ATERRAMENTO. DES 02118-CEMIG-55. ET-02118-CEMIG-277. | F17: 1 | G17: PÇ | H17: 116590
B18: 8 | D18: 292797 | E18: SECCIONADOR,TRIPOLAR,145kV,1250A,60Hz,230/550/-kV,IT20kAef,ID 50kAcr,MONTAGEM HORIZONTAL PÓLOS PARALELOS,SUPORTE POC-2,ABERTURA CENTRAL,OPERAÇÃO MECANISMO DIRETO, C/LÂMINA TERRA. DES 02118-CEMIG-55. EB-20000-ER/SE-6005. ET-02118-CEMIG-277. | F18: 1 | G18: PÇ | H18: 126380
B19: 9 | D19: 376115 | E19: SECCIONADOR,TRIPOLAR,145kV,1250A,60Hz,230/550/-kV,It 20kAef,Id 50kAcr,MONTAGEM HORIZONTAL PÓLOS PARALELOS ESPAÇAMENTO ENTRE PÓLOS 3000mm,ABERTURA CENTRAL,OPERAÇÃO MOTORIZADA 125VCC, MECANISMO DIRETO,C/CAPACIDADE ABERTURA CORRENTE MAGNETIZAÇÃO 2,5A,DISPOSITIVO RESTRIÇÃO ARCOS. DES 02118-CEMIG-55. ET-02118-CEMIG-277. EB-20000-ER/SE-6005. | F19: 1 | G19: PÇ | H19: =129050+18950
B20: 10 | D20: 262352 | E20: SECCIONADOR,TRIPOLAR,145kV,1250A,60Hz,230/550/-kV,IT 20kAef,ID 50kAcr,MONTAGEM HORIZONTAL NORMAL, ABERTURA CENTRAL,OPERAÇÃO MOTORIZADA,MOTOR 125VCC,TENSÃO COMANDO 125VCC,S/LÂMINA TERRA. DES 02118-CEMIG-55. ET-02118-CEMIG-277. | F20: 1 | G20: PÇ | H20: =125490+22510
B21: 11 | D21: 384194 | E21: RELIGADOR,TRIFÁSICO,15kV,630A,12kA,60Hz,50/110/-kV,VÁCUO,ISOLAMENTO SÓLIDO MATERIAL POLIMÉRICO ORGÂNICO,C/ CONTROLE E PROTEÇÃO DIGITAIS FALTA FASE-FASE E FASE-TERRA, CONTROLE E SUPERVISÃO REMOTOS E LOCAIS, TENSÃO CONTROLE E AUXILIAR 125VCC,2 CONTATOS AUXILIARES REVERSÍVEIS, POSSIBILIDADE COMANDO REMOTO. ET-22000-PE/LS-5594. IEEE C37.60. IEC 62271-111. | F21: 1 | G21: PÇ | H21: 78320
B22: 12 | C22: RELIGADORES DE MT | D22: 380360 | E22: CONTROLE,MICROPROCESSADO,P/RELIGADOR,15, 27, 38kV,TENSÃO CONTROLE 125VCC,C/CABO INTERLIGAÇÃO,RELÉ FUNÇÃO DIRECIONAL SOBRECORRENTE,RELÉ FALTA À TERRA, FALTA SENSÍVEL À TERRA,RELÉAUTORELIGAMENTO,MEDIÇÃO INSTANTÂNEA,REGISTRO EVENTOS. ET-22000-PE/LS-5594. | F22: 1 | G22: PÇ | H22: 43165
B23: 13 | C23: TRANSFORMADOR DE CORRENTE DE MT | D23: 387341 | E23: TRANSFORMADOR,CORRENTE,15kV,1500-5A,60Hz,34/110/-kV,EXATIDÃO 2X100VA 10P20, FT 1,5,IT 12,5kA/1s, ID 31,25kA,ISOLAÇÃO SÓLIDA,EXTERNO,TRANSMISSÃO. ET-02118-CEMIG-301. | F23: 1 | G23: PÇ | H23: 21360
B24: 14 | C24: CABOS ISOLADOS | D24: 388487 | E24: CABO,CONDUTOR,1X500mm²,CLASSE 2,ALUMÍNIO COMPACTADO, BLOQUEIO NO CONDUTOR E ISOLAÇÃO,C/CAMADA SEMICONDUTORA INTERNA, ISOLAÇÃO EPR OU XLPE OU TR XLPE,CAMADA SEMICONDUTORA EXTERNA,BLINDAGEM METÁLICA FIOS COBRE,COBERTURA SHF1, 12/20kV. ET-02118-CEMIG-440 E ET 02.111-ED/ES-26. | F24: 200 | G24: m | H24: 106800
B25: 15 | C25: SISTEMA DE AUTOMAÇÃO DE SUBESTAÇÕES (SAS) | D25: 385629 | E25: DISPOSITIVO,SINCRONIZAÇÃO,VIA SATÉLITE (GPS). REF RT430,GE. | F25: 1 | G25: PÇ | H25: 45390
B26: 16 | D26: - | E26: MÓDULO, AUXILIAR, SUPERVISÃO, PARALELISMO, SÍNCRONO SPS, P/TRANSFORMADORES POTÊNCIA. ET-02111-OP/AP-198. | F26: 1 | G26: PÇ | H26: 26299.5
B27: 17 | D27: 384300 | E27: CONCENTRADOR,OSCILOGRAFIA,ALIMENTAÇÃO 125VCC,PROCESSADOR INTEL CELERON QUAD COREl J1900 OU SUPERIOR,MEMÓRIARAM MÍNIMA 4GB,HD SSD MÍNIMO 120GB,SISTEMA OPERACIONAL WINDOWS PORTUGUÊS,MÍNIMO 2 PORTAS ETHERNET 10/100/1000 MBPS,4 USB, VGA,C/SINCRONISMO SNTP,MONTAGEM RACK PADRÃO 19" OU TRILHO DIN. REF MOXA DA-682-C7,ADVANTECH UNO-2372G-J021AE. | F27: 1 | G27: PÇ | H27: 29863.95
B28: 18 | D28: 385387 | E28: RELÉ, DIFERENCIAL, LINHA 87, NUMÉRICO, TRIFÁSICO+NEUTRO FUNÇÕES ADICIONAIS 21/21N,67/67N,50BF,79, 25, 27, 59, 59N/64, 81 ESQUEMA TRANSFERÊNCIA DISPARO DIRETO E PERMISSÍVEL, FECHAMENTO SOB FALTA, OSCILOGRAFIA, SAÍDA SERIAL TRASEIRA E FRONTAL, AUTO-MONITORAMENTO, TEMPO OPERAÇÃO <=2 CICLOS, INTERFACE COMUNICAÇÃO ÓPTICA, MONTAGEM SEMI-EMBUTIDA PAINEL. ET 20000-PE/LS-5494. | F28: 1 | G28: PÇ | H28: 67900
B29: 19 | D29: 320721 | E29: RELÉ,DIFERENCIAL,87,NUMÉRICO,TRIFÁSICO,TRANSFORMADOR 3 ENROLAMENTOS, FUNÇÕES ADICIONAIS 87N,51, 51N1,51N2,81,50BF,59, 59N, ESTABILIZAÇÃO FALTAS EXTERNAS,CONTRA CORRENTES INRUSH, HARMÔNICA, COMPONENTE DC,SATURAÇÃO,OSCILOGRAFIA,SAÍDA SERIAL TRASEIRA E FRONTAL,AUTO-MONITORAMENTO,TEMPO OPERAÇÃO <(><<)=2 CICLOS,MONTAGEM SEMI-EMBUTIDAPAINEL. ET-22000-PELS-5494. | F29: 1 | G29: PÇ | H29: 67900
B30: 20 | D30: 378775 | E30: RELÉ,SOBRECORRENTE,DIRECIONAL,FUNÇÃO 67/67N,NUMÉRICO, TRIFÁSICO+ NEUTRO,FUNÇÕES ADICIONAIS 50/51N, 50BF, 79, 27, 59, 59N/64, 81, 61,LÓGICAS,FECHAMENTO SOB FALTA, OSCILOGRAFIA, SAÍDA SERIAL TRASEIRA E FRONTAL,AUTO-MONITORAMENTO,TEMPO OPERAÇÃO <(><<)>=3 CICLOS,MONTAGEM SEMI-EMBUTIDA PAINEL. ET-22000-PELS-5494. | F30: 1 | G30: PÇ | H30: 67900
B31: 21 | D31: 385763 | E31: SISTEMA,PROTEÇÃO DIFERENCIAL BARRAMENTO,SOLUÇÃO DISTRIBUÍDA OU CONCENTRADA, FORMADA P/RELÉS,FUNÇÃO PRINCIPAL 87B,FUNÇÃO ADICIONAL 50BF,NUMÉRICO,BAIXA IMPEDÂNCIA,MÍNIMO 12 VÃOS TRIFÁSICOS,4 ZONAS,PROTEÇÃO SELETIVA, LÓGICAS, OSCILOGRAFIAS,SAÍDA SERIAL,AUTO-MONITORAMENTO,TEMPO OPERAÇÃO <=2 CICLOS, INTERFACE COMUNICAÇÃO ÓPTICA,MONTAGEM SEMI-EMBUTIDA PAINEL. ET-20000-PE/LS-5494. | F31: 1 | G31: CJ | H31: 62980
B32: 22 | D32: 385519 | E32: CONTROLADOR AUTOMÁTICO BANCO CAPACITOR OU REATOR,CONTROLES INDIVIDUAIS TIPO TENSÃO, CORRENTE,POTÊNCIA REATIVA, FATOR POTÊNCIA,DATA E HORÁRIO. NORMA IEC61850. ET-02111-OPAP-ET-001. | F32: 1 | G32: PÇ | H32: 22842.74
B33: 23 | D33: 378779 | E33: MÓDULO,16 ENTRADAS DIGITAIS,P/UNIDADE CENTRAL CONTROLE (UCC). ET-02111-0P/AP-198, ET-22000-ER/SE-6044. | F33: 1 | G33: PÇ | H33: 22250
B34: 24 | D34: 378780 | E34: MÓDULO,8 ENTRADAS ANALÓGICAS,P/UNIDADE CENTRAL CONTROLE (UCC). ET-02111-0P/AP-198, ET-22000-ER/SE-6044. | F34: 1 | G34: PÇ | H34: 22250
B35: 25 | D35: 378781 | E35: MÓDULO,16 SAÍDAS DIGITAIS,P/UNIDADE CENTRAL CONTROLE (UCC). ET-02111-0P/AP-198, ET-22000-ER/SE-6044. | F35: 1 | G35: PÇ | H35: 22250
B36: 26 | D36: 385356 | E36: INTERFACE,HOMEM MÁQUINA,IHM,P/SISTEMA DE PROTEÇÃO,CONTROLE E AUTOMAÇÃO, P/OPERAÇÃO LOCAL SUBESTAÇÕES. ET-02111-AD/ES-ET-024. | F36: 1 | G36: PÇ | H36: 26700
B37: 27 | D37: 385393 | E37: UNIDADE CENTRAL CONTROLE (UCC),COMPLETA,C/ED,SD E EA, FONTE ALIMENTAÇÃO,PORTAS COMUNICAÇÃO. ET-02111-0P/AP-198, ET-22000-ER/SE-6044. | F37: 1 | G37: PÇ | H37: 44500
B38: 28 | D38: 385762 | E38: SWITCH,ROBUSTO, FONTES REDUNDANTES EM 125VCC, MONTAGEM RACK 19". CERTIFICAÇÕES IEC-61850-3 E IEEE 1613. ET-02111-OP/AP-198. | F38: 1 | G38: PÇ | H38: 21150
B39: 29 | D39: 384310 | E39: CONVERSOR,INTERFACE SERIAL RS-232,P/ETHERNET FIBRA MULTIMODO,CONETOR SC,600bps A 230kbps,INDUSTRIAL,TEMPERATURA OPERAÇÃO 0° A 60°C,ALIMENTAÇÃO 12-48VCC. ET-02111-OP/AP-190. | F39: 1 | G39: PÇ | H39: 26700
B40: PREÇO TOTAL | H40: =SUM(H11:H39)
E41: PERCENTUAL DO VALOR TOTAL DOS SOBRESSANTES QUE FARÁ PARTE DO PREÇO GLOBAL: | G41: 0.9 | H41: =G41*H40
B43: Notas: 1) Os PROPONENTES devem preencher os valores totais de cada linha da coluna "H" em função dos seus respectivos quantitativos indicados. Ex.: Onde consta 200 (duzentos) metros, preencher com o valor total dos 200 (duzentos) metros.

Sheet 04_TOTALIZADORA (3)
A1: ='01_Preço'!A1
A2: TABELA TOTALIZADORA DOS PREÇOS DOS MATERIAIS E SERVIÇOS DA REFORMA E MODERNIZAÇÃO DA UHE SALTO GRANDE E MODERNIZAÇÃO E DIGITALIZAÇÃO DA SE UHE SALTO GRANDE – ATIVOS CEMIG D
A4: OBJETO: CONTRATAÇÃO DE SERVIÇOS PARA EXECUÇÃO DA MODERNIZAÇÃO DA UHE SALTO GRANDE | AB4: =_xlfn.CONCAT('01_Preço'!M4," ",'01_Preço'!O4) | AD4: BASE ECONÔMICA TRIBUTÁRIA: | AE4: ='01_Preço'!V4
A5: NOME EMPRESA PROPONENTE: | E5: ='01_Preço'!C5 | AB5: Nº CNPJ: | AC5: ='01_Preço'!L5 | AD5: Nº INSC ESTADUAL: | AE5: ='01_Preço'!Q5
A6: NOME REPRESENTANTE LEGAL: | E6: ='01_Preço'!C6 | AB6: Nº CPF: | AC6: ='01_Preço'!L6 | AD6: Nº IDENTIDADE: | AE6: ='01_Preço'!Q6
A7: ASSINATURA DO REPRESENTANTE LEGAL DA EMPRESA: | F7: ='01_Preço'!E7 | AD7: DATA DE EMISSÃO: | AE7: ='01_Preço'!V5
A9: % DA ANTECIPAÇÃO SOLICITADA | E9: 0.05 | F9: VALOR ANTECIPAÇÃO SOLICITADA | K9: Amortização | L9: =SUM(L14:L82) | Z9: =E9*AD9 | AB9: PREÇO GLOBAL | AD9: =AB83
K10: Entrada | L10: =V15
A12: MÊS | B12: EVENTOS NO MÊS | C12: ESCOPO CEMIG GT | E12: ESCOPO CEMIG D | G12: RECEITA MENSAL PREVISTA | H12: RECEITA TOTAL PREVISTA | J12: RECEITA ACUMULADA INSIGHT | P12: INSIGHT | R12: DESEMBOLSO INSIGHT MENSAL PREVISTO | S12: FAT. DIRETO MENSAL PREVISTO | T12: FAT. DIRETO ACUMULADO PREVISTO | U12: DESEMBOLSO INSIGHT ACUMULADO | V12: FATURAMENTO REALIZADO | W12: FATURAMENTO ACUMULADO | X12: PROGRAMAÇÃO DE PEDIDOS REALIZADOS | Y12: PROGRAMAÇÃO ACUMULADA DE PEDIDOS REALIZADOS | Z12: PREÇO DA REFORMA E MODERNIZAÇÃO DA UHE SALTO GRANDE | AD12: =D84
C13: EVENTOS NO MÊS | D13: VALOR TOTAL MENSAL (com todos os impostos) (R$) | E13: EVENTOS NO MÊS | F13: VALOR TOTAL MENSAL (com todos os impostos) (R$) | I13: RECEITA INSIGHT MENSAL | K13: VALOR DA MEDIÇÃO PELA INSIGHT | L13: VALOR A AMORTIZAR | M13: VALOR PARA ENTRAR EM CAIXA DA INSIGHT | N13: VALOR A RECEBER (INSIGHT + DIRETO) | O13: RECEITA LÍQUIDA INSIGHT | P13: DESEMBOLSO MENSAL INSIGHT PREVISTO | Z13: PREÇO DA MODERNIZAÇÃO E DIGITALIZAÇÃO DA SE UHE SALTO GRANDE - ATIVO CEMIG D | AD13: =F84
A14: 1 | B14: 45474 | C14: =SUM(COUNTIF('03_Eventos_pagamentos'!$E$11:$E$697,'04_TOTALIZADORA (3)'!A14)+COUNTIF('03_Eventos_pagamentos'!$E$766:$E$836,'04_TOTALIZADORA (3)'!A14)) | D14: =SUMIF('03_Eventos_pagamentos'!$E$11:$E$699,A14,'03_Eventos_pagamentos'!$O$11:$O$697)+SUMIF('03_Eventos_pagamentos'!$E$766:$E$836,A14,'03_Eventos_pagamentos'!$O$766:$O$836) | E14: =COUNTIF('03_Eventos_pagamentos'!$E$702:$E$763,'04_TOTALIZADORA (3)'!A14) | F14: =SUMIF('03_Eventos_pagamentos'!$E$702:$E$763,A14,'03_Eventos_pagamentos'!$O$702:$O$763) | G14: =D14+F14 | H14: =D14+F14 | I14: =G14-S14 | J14: =H14-T14 | K14: =SUMIF('03_Eventos_pagamentos'!$E$11:$E$699,H14,'03_Eventos_pagamentos'!$O$11:$O$697)+SUMIF('03_Eventos_pagamentos'!$E$766:$E$836,H14,'03_Eventos_pagamentos'!$O$766:$O$836) | L14: =SUMIF('03_Eventos_pagamentos'!$E$702:$E$763,H14,'03_Eventos_pagamentos'!$O$702:$O$763) | M14: =L10 | N14: =M14+S14 | O14: =I14-R14 | P14: =SUMIF('03_Eventos_pagamentos'!$P$11:$P$843,A15,'03_Eventos_pagamentos'!$Q$11:$Q$843) | Q14: 100000 | R14: =P14+Q14 | S14: =SUMIFS( '03_Eventos_pagamentos'!$O$11:$O$843,'03_Eventos_pagamentos'!$E$11:$E$843,A14,'03_Eventos_pagamentos'!$I$11:$I$843,"FAT. DIRETO") | T14: =S14 | U14: =R14+S14 | V14: 0 | W14: =V14 | X14: 9546933.1 | Y14: =X14
A15: 2 | B15: 45505 | C15: =SUM(COUNTIF('03_Eventos_pagamentos'!$E$11:$E$697,'04_TOTALIZADORA (3)'!A15)+COUNTIF('03_Eventos_pagamentos'!$E$766:$E$836,'04_TOTALIZADORA (3)'!A15)) | D15: =SUMIF('03_Eventos_pagamentos'!$E$11:$E$699,A15,'03_Eventos_pagamentos'!$O$11:$O$697)+SUMIF('03_Eventos_pagamentos'!$E$766:$E$836,A15,'03_Eventos_pagamentos'!$O$766:$O$836) | E15: =COUNTIF('03_Eventos_pagamentos'!$E$702:$E$763,'04_TOTALIZADORA (3)'!A15) | F15: =SUMIF('03_Eventos_pagamentos'!$E$702:$E$763,A15,'03_Eventos_pagamentos'!$O$702:$O$763) | G15: =D15+F15 | H15: =D15+F15+H14 | I15: =G15-S15 | J15: =H15-T15 | L15: =SUMIF('03_Eventos_pagamentos'!$E$702:$E$763,H15,'03_Eventos_pagamentos'!$O$702:$O$763) | M15: =K15-L15 | N15: =M15+S15 | O15: =I15-R15 | P15: =SUMIF('03_Eventos_pagamentos'!$P$11:$P$843,A16,'03_Eventos_pagamentos'!$Q$11:$Q$843) | Q15: 100000 | R15: =P15+Q15 | S15: =SUMIFS( '03_Eventos_pagamentos'!$O$11:$O$843,'03_Eventos_pagamentos'!$E$11:$E$843,A15,'03_Eventos_pagamentos'!$I$11:$I$843,"FAT. DIRETO") | T15: =S15+T14 | U15: =P15+S15+U14 | V15: =AE83 | W15: =V15+W14
A16: 3 | B16: 45536 | C16: =SUM(COUNTIF('03_Eventos_pagamentos'!$E$11:$E$697,'04_TOTALIZADORA (3)'!A16)+COUNTIF('03_Eventos_pagamentos'!$E$766:$E$836,'04_TOTALIZADORA (3)'!A16)) | D16: =SUMIF('03_Eventos_pagamentos'!$E$11:$E$699,A16,'03_Eventos_pagamentos'!$O$11:$O$697)+SUMIF('03_Eventos_pagamentos'!$E$766:$E$836,A16,'03_Eventos_pagamentos'!$O$766:$O$836) | E16: =COUNTIF('03_Eventos_pagamentos'!$E$702:$E$763,'04_TOTALIZADORA (3)'!A16) | F16: =SUMIF('03_Eventos_pagamentos'!$E$702:$E$763,A16,'03_Eventos_pagamentos'!$O$702:$O$763) | G16: =D16+F16 | H16: =D16+F16+H15 | I16: =G16-S16 | J16: =H16-T16 | K16: =D16+F16-S16 | L16: =SUMIF('03_Eventos_pagamentos'!$E$702:$E$763,H16,'03_Eventos_pagamentos'!$O$702:$O$763) | M16: =K16-L16 | N16: =M16+S16 | O16: =I16-R16 | P16: =SUMIF('03_Eventos_pagamentos'!$P$11:$P$843,A17,'03_Eventos_pagamentos'!$Q$11:$Q$843) | Q16: 100000 | R16: =P16+Q16 | S16: =SUMIFS( '03_Eventos_pagamentos'!$O$11:$O$843,'03_Eventos_pagamentos'!$E$11:$E$843,A16,'03_Eventos_pagamentos'!$I$11:$I$843,"FAT. DIRETO") | T16: =S16+T15 | U16: =P16+S16+U15 | W16: =V16+W15
A17: 4 | B17: 45566 | C17: =SUM(COUNTIF('03_Eventos_pagamentos'!$E$11:$E$697,'04_TOTALIZADORA (3)'!A17)+COUNTIF('03_Eventos_pagamentos'!$E$766:$E$836,'04_TOTALIZADORA (3)'!A17)) | D17: =SUMIF('03_Eventos_pagamentos'!$E$11:$E$699,A17,'03_Eventos_pagamentos'!$O$11:$O$697)+SUMIF('03_Eventos_pagamentos'!$E$766:$E$836,A17,'03_Eventos_pagamentos'!$O$766:$O$836) | E17: =COUNTIF('03_Eventos_pagamentos'!$E$702:$E$763,'04_TOTALIZADORA (3)'!A17) | F17: =SUMIF('03_Eventos_pagamentos'!$E$702:$E$763,A17,'03_Eventos_pagamentos'!$O$702:$O$763) | G17: =D17+F17 | H17: =D17+F17+H16 | I17: =G17-S17 | J17: =H17-T17 | K17: =D17+F17-S17 | L17: =SUMIF('03_Eventos_pagamentos'!$E$702:$E$763,H17,'03_Eventos_pagamentos'!$O$702:$O$763) | M17: =K17-L17 | N17: =M17+S17 | O17: =I17-R17 | P17: =SUMIF('03_Eventos_pagamentos'!$P$11:$P$843,A18,'03_Eventos_pagamentos'!$Q$11:$Q$843) | Q17: 100000 | R17: =P17+Q17 | S17: =SUMIFS( '03_Eventos_pagamentos'!$O$11:$O$843,'03_Eventos_pagamentos'!$E$11:$E$843,A17,'03_Eventos_pagamentos'!$I$11:$I$843,"FAT. DIRETO") | T17: =S17+T16 | U17: =P17+S17+U16 | W17: =V17+W16
A18: 5 | B18: 45597 | C18: =SUM(COUNTIF('03_Eventos_pagamentos'!$E$11:$E$697,'04_TOTALIZADORA (3)'!A18)+COUNTIF('03_Eventos_pagamentos'!$E$766:$E$836,'04_TOTALIZADORA (3)'!A18)) | D18: =SUMIF('03_Eventos_pagamentos'!$E$11:$E$699,A18,'03_Eventos_pagamentos'!$O$11:$O$697)+SUMIF('03_Eventos_pagamentos'!$E$766:$E$836,A18,'03_Eventos_pagamentos'!$O$766:$O$836) | E18: =COUNTIF('03_Eventos_pagamentos'!$E$702:$E$763,'04_TOTALIZADORA (3)'!A18) | F18: =SUMIF('03_Eventos_pagamentos'!$E$702:$E$763,A18,'03_Eventos_pagamentos'!$O$702:$O$763) | G18: =D18+F18 | H18: =D18+F18+H17 | I18: =G18-S18 | J18: =H18-T18 | K18: =D18+F18-S18 | L18: =SUMIF('03_Eventos_pagamentos'!$E$702:$E$763,H18,'03_Eventos_pagamentos'!$O$702:$O$763) | M18: =K18-L18 | N18: =M18+S18 | O18: =I18-R18 | P18: =SUMIF('03_Eventos_pagamentos'!$P$11:$P$843,A19,'03_Eventos_pagamentos'!$Q$11:$Q$843) | Q18: 100000 | R18: =P18+Q18 | S18: =SUMIFS( '03_Eventos_pagamentos'!$O$11:$O$843,'03_Eventos_pagamentos'!$E$11:$E$843,A18,'03_Eventos_pagamentos'!$I$11:$I$843,"FAT. DIRETO") | T18: =S18+T17 | U18: =P18+S18+U17 | W18: =V18+W17
A19: 6 | B19: 45627 | C19: =SUM(COUNTIF('03_Eventos_pagamentos'!$E$11:$E$697,'04_TOTALIZADORA (3)'!A19)+COUNTIF('03_Eventos_pagamentos'!$E$766:$E$836,'04_TOTALIZADORA (3)'!A19)) | D19: =SUMIF('03_Eventos_pagamentos'!$E$11:$E$699,A19,'03_Eventos_pagamentos'!$O$11:$O$697)+SUMIF('03_Eventos_pagamentos'!$E$766:$E$836,A19,'03_Eventos_pagamentos'!$O$766:$O$836) | E19: =COUNTIF('03_Eventos_pagamentos'!$E$702:$E$763,'04_TOTALIZADORA (3)'!A19) | F19: =SUMIF('03_Eventos_pagamentos'!$E$702:$E$763,A19,'03_Eventos_pagamentos'!$O$702:$O$763) | G19: =D19+F19 | H19: =D19+F19+H18 | I19: =G19-S19 | J19: =H19-T19 | K19: =D19+F19-S19 | L19: =SUMIF('03_Eventos_pagamentos'!$E$702:$E$763,H19,'03_Eventos_pagamentos'!$O$702:$O$763) | M19: =K19-L19 | N19: =M19+S19 | O19: =I19-R19 | P19: =SUMIF('03_Eventos_pagamentos'!$P$11:$P$843,A20,'03_Eventos_pagamentos'!$Q$11:$Q$843) | Q19: 100000 | R19: =P19+Q19 | S19: =SUMIFS( '03_Eventos_pagamentos'!$O$11:$O$843,'03_Eventos_pagamentos'!$E$11:$E$843,A19,'03_Eventos_pagamentos'!$I$11:$I$843,"FAT. DIRETO") | T19: =S19+T18 | U19: =P19+S19+U18 | W19: =V19+W18
A20: 7 | B20: 45658 | C20: =SUM(COUNTIF('03_Eventos_pagamentos'!$E$11:$E$697,'04_TOTALIZADORA (3)'!A20)+COUNTIF('03_Eventos_pagamentos'!$E$766:$E$836,'04_TOTALIZADORA (3)'!A20)) | D20: =SUMIF('03_Eventos_pagamentos'!$E$11:$E$699,A20,'03_Eventos_pagamentos'!$O$11:$O$697)+SUMIF('03_Eventos_pagamentos'!$E$766:$E$836,A20,'03_Eventos_pagamentos'!$O$766:$O$836) | E20: =COUNTIF('03_Eventos_pagamentos'!$E$702:$E$763,'04_TOTALIZADORA (3)'!A20) | F20: =SUMIF('03_Eventos_pagamentos'!$E$702:$E$763,A20,'03_Eventos_pagamentos'!$O$702:$O$763) | G20: =D20+F20 | H20: =D20+F20+H19 | I20: =G20-S20 | J20: =H20-T20 | K20: =D20+F20-S20 | L20: =SUMIF('03_Eventos_pagamentos'!$E$702:$E$763,H20,'03_Eventos_pagamentos'!$O$702:$O$763) | M20: =K20-L20 | N20: =M20+S20 | O20: =I20-R20 | P20: =SUMIF('03_Eventos_pagamentos'!$P$11:$P$843,A21,'03_Eventos_pagamentos'!$Q$11:$Q$843) | Q20: 100000 | R20: =P20+Q20 | S20: =SUMIFS( '03_Eventos_pagamentos'!$O$11:$O$843,'03_Eventos_pagamentos'!$E$11:$E$843,A20,'03_Eventos_pagamentos'!$I$11:$I$843,"FAT. DIRETO") | T20: =S20+T19 | U20: =P20+S20+U19 | W20: =V20+W19
A21: 8 | B21: 45689 | C21: =SUM(COUNTIF('03_Eventos_pagamentos'!$E$11:$E$697,'04_TOTALIZADORA (3)'!A21)+COUNTIF('03_Eventos_pagamentos'!$E$766:$E$836,'04_TOTALIZADORA (3)'!A21)) | D21: =SUMIF('03_Eventos_pagamentos'!$E$11:$E$699,A21,'03_Eventos_pagamentos'!$O$11:$O$697)+SUMIF('03_Eventos_pagamentos'!$E$766:$E$836,A21,'03_Eventos_pagamentos'!$O$766:$O$836) | E21: =COUNTIF('03_Eventos_pagamentos'!$E$702:$E$763,'04_TOTALIZADORA (3)'!A21) | F21: =SUMIF('03_Eventos_pagamentos'!$E$702:$E$763,A21,'03_Eventos_pagamentos'!$O$702:$O$763) | G21: =D21+F21 | H21: =D21+F21+H20 | I21: =G21-S21 | J21: =H21-T21 | K21: =D21+F21-S21 | L21: =SUMIF('03_Eventos_pagamentos'!$E$702:$E$763,H21,'03_Eventos_pagamentos'!$O$702:$O$763) | M21: =K21-L21 | N21: =M21+S21 | O21: =I21-R21 | P21: =SUMIF('03_Eventos_pagamentos'!$P$11:$P$843,A22,'03_Eventos_pagamentos'!$Q$11:$Q$843) | Q21: 100000 | R21: =P21+Q21 | S21: =SUMIFS( '03_Eventos_pagamentos'!$O$11:$O$843,'03_Eventos_pagamentos'!$E$11:$E$843,A21,'03_Eventos_pagamentos'!$I$11:$I$843,"FAT. DIRETO") | T21: =S21+T20 | U21: =P21+S21+U20 | W21: =V21+W20
A22: 9 | B22: 45717 | C22: =SUM(COUNTIF('03_Eventos_pagamentos'!$E$11:$E$697,'04_TOTALIZADORA (3)'!A22)+COUNTIF('03_Eventos_pagamentos'!$E$766:$E$836,'04_TOTALIZADORA (3)'!A22)) | D22: =SUMIF('03_Eventos_pagamentos'!$E$11:$E$699,A22,'03_Eventos_pagamentos'!$O$11:$O$697)+SUMIF('03_Eventos_pagamentos'!$E$766:$E$836,A22,'03_Eventos_pagamentos'!$O$766:$O$836) | E22: =COUNTIF('03_Eventos_pagamentos'!$E$702:$E$763,'04_TOTALIZADORA (3)'!A22) | F22: =SUMIF('03_Eventos_pagamentos'!$E$702:$E$763,A22,'03_Eventos_pagamentos'!$O$702:$O$763) | G22: =D22+F22 | H22: =D22+F22+H21 | I22: =G22-S22 | J22: =H22-T22 | K22: =D22+F22-S22 | L22: =SUMIF('03_Eventos_pagamentos'!$E$702:$E$763,H22,'03_Eventos_pagamentos'!$O$702:$O$763) | M22: =K22-L22 | N22: =M22+S22 | O22: =I22-R22 | P22: =SUMIF('03_Eventos_pagamentos'!$P$11:$P$843,A23,'03_Eventos_pagamentos'!$Q$11:$Q$843) | Q22: 100000 | R22: =P22+Q22 | S22: =SUMIFS( '03_Eventos_pagamentos'!$O$11:$O$843,'03_Eventos_pagamentos'!$E$11:$E$843,A22,'03_Eventos_pagamentos'!$I$11:$I$843,"FAT. DIRETO") | T22: =S22+T21 | U22: =P22+S22+U21 | W22: =V22+W21
A23: 10 | B23: 45748 | C23: =SUM(COUNTIF('03_Eventos_pagamentos'!$E$11:$E$697,'04_TOTALIZADORA (3)'!A23)+COUNTIF('03_Eventos_pagamentos'!$E$766:$E$836,'04_TOTALIZADORA (3)'!A23)) | D23: =SUMIF('03_Eventos_pagamentos'!$E$11:$E$699,A23,'03_Eventos_pagamentos'!$O$11:$O$697)+SUMIF('03_Eventos_pagamentos'!$E$766:$E$836,A23,'03_Eventos_pagamentos'!$O$766:$O$836) | E23: =COUNTIF('03_Eventos_pagamentos'!$E$702:$E$763,'04_TOTALIZADORA (3)'!A23) | F23: =SUMIF('03_Eventos_pagamentos'!$E$702:$E$763,A23,'03_Eventos_pagamentos'!$O$702:$O$763) | G23: =D23+F23 | H23: =D23+F23+H22 | I23: =G23-S23 | J23: =H23-T23 | K23: =D23+F23-S23 | L23: =SUMIF('03_Eventos_pagamentos'!$E$702:$E$763,H23,'03_Eventos_pagamentos'!$O$702:$O$763) | M23: =K23-L23 | N23: =M23+S23 | O23: =I23-R23 | P23: =SUMIF('03_Eventos_pagamentos'!$P$11:$P$843,A24,'03_Eventos_pagamentos'!$Q$11:$Q$843) | Q23: 100000 | R23: =P23+Q23 | S23: =SUMIFS( '03_Eventos_pagamentos'!$O$11:$O$843,'03_Eventos_pagamentos'!$E$11:$E$843,A23,'03_Eventos_pagamentos'!$I$11:$I$843,"FAT. DIRETO") | T23: =S23+T22 | U23: =P23+S23+U22 | W23: =V23+W22
A24: 11 | B24: 45778 | C24: =SUM(COUNTIF('03_Eventos_pagamentos'!$E$11:$E$697,'04_TOTALIZADORA (3)'!A24)+COUNTIF('03_Eventos_pagamentos'!$E$766:$E$836,'04_TOTALIZADORA (3)'!A24)) | D24: =SUMIF('03_Eventos_pagamentos'!$E$11:$E$699,A24,'03_Eventos_pagamentos'!$O$11:$O$697)+SUMIF('03_Eventos_pagamentos'!$E$766:$E$836,A24,'03_Eventos_pagamentos'!$O$766:$O$836) | E24: =COUNTIF('03_Eventos_pagamentos'!$E$702:$E$763,'04_TOTALIZADORA (3)'!A24) | F24: =SUMIF('03_Eventos_pagamentos'!$E$702:$E$763,A24,'03_Eventos_pagamentos'!$O$702:$O$763) | G24: =D24+F24 | H24: =D24+F24+H23 | I24: =G24-S24 | J24: =H24-T24 | K24: =D24+F24-S24 | L24: =SUMIF('03_Eventos_pagamentos'!$E$702:$E$763,H24,'03_Eventos_pagamentos'!$O$702:$O$763) | M24: =K24-L24 | N24: =M24+S24 | O24: =I24-R24 | P24: =SUMIF('03_Eventos_pagamentos'!$P$11:$P$843,A25,'03_Eventos_pagamentos'!$Q$11:$Q$843) | Q24: 100000 | R24: =P24+Q24 | S24: =SUMIFS( '03_Eventos_pagamentos'!$O$11:$O$843,'03_Eventos_pagamentos'!$E$11:$E$843,A24,'03_Eventos_pagamentos'!$I$11:$I$843,"FAT. DIRETO") | T24: =S24+T23 | U24: =P24+S24+U23 | W24: =V24+W23
A25: 12 | B25: 45809 | C25: =SUM(COUNTIF('03_Eventos_pagamentos'!$E$11:$E$697,'04_TOTALIZADORA (3)'!A25)+COUNTIF('03_Eventos_pagamentos'!$E$766:$E$836,'04_TOTALIZADORA (3)'!A25)) | D25: =SUMIF('03_Eventos_pagamentos'!$E$11:$E$699,A25,'03_Eventos_pagamentos'!$O$11:$O$697)+SUMIF('03_Eventos_pagamentos'!$E$766:$E$836,A25,'03_Eventos_pagamentos'!$O$766:$O$836) | E25: =COUNTIF('03_Eventos_pagamentos'!$E$702:$E$763,'04_TOTALIZADORA (3)'!A25) | F25: =SUMIF('03_Eventos_pagamentos'!$E$702:$E$763,A25,'03_Eventos_pagamentos'!$O$702:$O$763) | G25: =D25+F25 | H25: =D25+F25+H24 | I25: =G25-S25 | J25: =H25-T25 | K25: =D25+F25-S25 | L25: =SUMIF('03_Eventos_pagamentos'!$E$702:$E$763,H25,'03_Eventos_pagamentos'!$O$702:$O$763) | M25: =K25-L25 | N25: =M25+S25 | O25: =I25-R25 | P25: =SUMIF('03_Eventos_pagamentos'!$P$11:$P$843,A26,'03_Eventos_pagamentos'!$Q$11:$Q$843) | Q25: 100000 | R25: =P25+Q25 | S25: =SUMIFS( '03_Eventos_pagamentos'!$O$11:$O$843,'03_Eventos_pagamentos'!$E$11:$E$843,A25,'03_Eventos_pagamentos'!$I$11:$I$843,"FAT. DIRETO") | T25: =S25+T24 | U25: =P25+S25+U24 | W25: =V25+W24
A26: 13 | B26: 45839 | C26: =SUM(COUNTIF('03_Eventos_pagamentos'!$E$11:$E$697,'04_TOTALIZADORA (3)'!A26)+COUNTIF('03_Eventos_pagamentos'!$E$766:$E$836,'04_TOTALIZADORA (3)'!A26)) | D26: =SUMIF('03_Eventos_pagamentos'!$E$11:$E$699,A26,'03_Eventos_pagamentos'!$O$11:$O$697)+SUMIF('03_Eventos_pagamentos'!$E$766:$E$836,A26,'03_Eventos_pagamentos'!$O$766:$O$836) | E26: =COUNTIF('03_Eventos_pagamentos'!$E$702:$E$763,'04_TOTALIZADORA (3)'!A26) | F26: =SUMIF('03_Eventos_pagamentos'!$E$702:$E$763,A26,'03_Eventos_pagamentos'!$O$702:$O$763) | G26: =D26+F26 | H26: =D26+F26+H25 | I26: =G26-S26 | J26: =H26-T26 | K26: =D26+F26-S26 | L26: =SUMIF('03_Eventos_pagamentos'!$E$702:$E$763,H26,'03_Eventos_pagamentos'!$O$702:$O$763) | M26: =K26-L26 | N26: =M26+S26 | O26: =I26-R26 | P26: =SUMIF('03_Eventos_pagamentos'!$P$11:$P$843,A27,'03_Eventos_pagamentos'!$Q$11:$Q$843) | Q26: 100000 | R26: =P26+Q26 | S26: =SUMIFS( '03_Eventos_pagamentos'!$O$11:$O$843,'03_Eventos_pagamentos'!$E$11:$E$843,A26,'03_Eventos_pagamentos'!$I$11:$I$843,"FAT. DIRETO") | T26: =S26+T25 | U26: =P26+S26+U25 | W26: =V26+W25
A27: 14 | B27: 45870 | C27: =SUM(COUNTIF('03_Eventos_pagamentos'!$E$11:$E$697,'04_TOTALIZADORA (3)'!A27)+COUNTIF('03_Eventos_pagamentos'!$E$766:$E$836,'04_TOTALIZADORA (3)'!A27)) | D27: =SUMIF('03_Eventos_pagamentos'!$E$11:$E$699,A27,'03_Eventos_pagamentos'!$O$11:$O$697)+SUMIF('03_Eventos_pagamentos'!$E$766:$E$836,A27,'03_Eventos_pagamentos'!$O$766:$O$836) | E27: =COUNTIF('03_Eventos_pagamentos'!$E$702:$E$763,'04_TOTALIZADORA (3)'!A27) | F27: =SUMIF('03_Eventos_pagamentos'!$E$702:$E$763,A27,'03_Eventos_pagamentos'!$O$702:$O$763) | G27: =D27+F27 | H27: =D27+F27+H26 | I27: =G27-S27 | J27: =H27-T27 | K27: =D27+F27-S27 | L27: =SUMIF('03_Eventos_pagamentos'!$E$702:$E$763,H27,'03_Eventos_pagamentos'!$O$702:$O$763) | M27: =K27-L27 | N27: =M27+S27 | O27: =I27-R27 | P27: =SUMIF('03_Eventos_pagamentos'!$P$11:$P$843,A28,'03_Eventos_pagamentos'!$Q$11:$Q$843) | Q27: 100000 | R27: =P27+Q27 | S27: =SUMIFS( '03_Eventos_pagamentos'!$O$11:$O$843,'03_Eventos_pagamentos'!$E$11:$E$843,A27,'03_Eventos_pagamentos'!$I$11:$I$843,"FAT. DIRETO") | T27: =S27+T26 | U27: =P27+S27+U26 | W27: =V27+W26
A28: 15 | B28: 45901 | C28: =SUM(COUNTIF('03_Eventos_pagamentos'!$E$11:$E$697,'04_TOTALIZADORA (3)'!A28)+COUNTIF('03_Eventos_pagamentos'!$E$766:$E$836,'04_TOTALIZADORA (3)'!A28)) | D28: =SUMIF('03_Eventos_pagamentos'!$E$11:$E$699,A28,'03_Eventos_pagamentos'!$O$11:$O$697)+SUMIF('03_Eventos_pagamentos'!$E$766:$E$836,A28,'03_Eventos_pagamentos'!$O$766:$O$836) | E28: =COUNTIF('03_Eventos_pagamentos'!$E$702:$E$763,'04_TOTALIZADORA (3)'!A28) | F28: =SUMIF('03_Eventos_pagamentos'!$E$702:$E$763,A28,'03_Eventos_pagamentos'!$O$702:$O$763) | G28: =D28+F28 | H28: =D28+F28+H27 | I28: =G28-S28 | J28: =H28-T28 | K28: =D28+F28-S28 | L28: =SUMIF('03_Eventos_pagamentos'!$E$702:$E$763,H28,'03_Eventos_pagamentos'!$O$702:$O$763) | M28: =K28-L28 | N28: =M28+S28 | O28: =I28-R28 | P28: =SUMIF('03_Eventos_pagamentos'!$P$11:$P$843,A29,'03_Eventos_pagamentos'!$Q$11:$Q$843) | Q28: 100000 | R28: =P28+Q28 | S28: =SUMIFS( '03_Eventos_pagamentos'!$O$11:$O$843,'03_Eventos_pagamentos'!$E$11:$E$843,A28,'03_Eventos_pagamentos'!$I$11:$I$843,"FAT. DIRETO") | T28: =S28+T27 | U28: =P28+S28+U27 | V28: =0.85*412245.2 | W28: =V28+W27
A29: 16 | B29: 45931 | C29: =SUM(COUNTIF('03_Eventos_pagamentos'!$E$11:$E$697,'04_TOTALIZADORA (3)'!A29)+COUNTIF('03_Eventos_pagamentos'!$E$766:$E$836,'04_TOTALIZADORA (3)'!A29)) | D29: =SUMIF('03_Eventos_pagamentos'!$E$11:$E$699,A29,'03_Eventos_pagamentos'!$O$11:$O$697)+SUMIF('03_Eventos_pagamentos'!$E$766:$E$836,A29,'03_Eventos_pagamentos'!$O$766:$O$836) | E29: =COUNTIF('03_Eventos_pagamentos'!$E$702:$E$763,'04_TOTALIZADORA (3)'!A29) | F29: =SUMIF('03_Eventos_pagamentos'!$E$702:$E$763,A29,'03_Eventos_pagamentos'!$O$702:$O$763) | G29: =D29+F29 | H29: =D29+F29+H28 | I29: =G29-S29 | J29: =H29-T29 | K29: =D29+F29-S29 | L29: =K29*0.15 | M29: =K29-L29 | N29: =M29+S29 | O29: =I29-R29 | P29: =SUMIF('03_Eventos_pagamentos'!$P$11:$P$843,A30,'03_Eventos_pagamentos'!$Q$11:$Q$843) | Q29: 100000 | R29: =P29+Q29 | S29: =SUMIFS( '03_Eventos_pagamentos'!$O$11:$O$843,'03_Eventos_pagamentos'!$E$11:$E$843,A29,'03_Eventos_pagamentos'!$I$11:$I$843,"FAT. DIRETO") | T29: =S29+T28 | U29: =P29+S29+U28 | W29: =V29+W28
A30: 17 | B30: 45962 | C30: =SUM(COUNTIF('03_Eventos_pagamentos'!$E$11:$E$697,'04_TOTALIZADORA (3)'!A30)+COUNTIF('03_Eventos_pagamentos'!$E$766:$E$836,'04_TOTALIZADORA (3)'!A30)) | D30: =SUMIF('03_Eventos_pagamentos'!$E$11:$E$699,A30,'03_Eventos_pagamentos'!$O$11:$O$697)+SUMIF('03_Eventos_pagamentos'!$E$766:$E$836,A30,'03_Eventos_pagamentos'!$O$766:$O$836) | E30: =COUNTIF('03_Eventos_pagamentos'!$E$702:$E$763,'04_TOTALIZADORA (3)'!A30) | F30: =SUMIF('03_Eventos_pagamentos'!$E$702:$E$763,A30,'03_Eventos_pagamentos'!$O$702:$O$763) | G30: =D30+F30 | H30: =D30+F30+H29 | I30: =G30-S30 | J30: =H30-T30 | K30: =D30+F30-S30 | L30: =K30*0.15 | M30: =K30-L30 | N30: =M30+S30 | O30: =I30-R30 | P30: =SUMIF('03_Eventos_pagamentos'!$P$11:$P$843,A31,'03_Eventos_pagamentos'!$Q$11:$Q$843) | Q30: 100000 | R30: =P30+Q30 | S30: =SUMIFS( '03_Eventos_pagamentos'!$O$11:$O$843,'03_Eventos_pagamentos'!$E$11:$E$843,A30,'03_Eventos_pagamentos'!$I$11:$I$843,"FAT. DIRETO") | T30: =S30+T29 | U30: =P30+S30+U29 | V30: =0.85*800224.32 | W30: =V30+W29 | X30: 1724103.7 | Y30: =Y14+X30
A31: 18 | B31: 45992 | C31: =SUM(COUNTIF('03_Eventos_pagamentos'!$E$11:$E$697,'04_TOTALIZADORA (3)'!A31)+COUNTIF('03_Eventos_pagamentos'!$E$766:$E$836,'04_TOTALIZADORA (3)'!A31)) | D31: =SUMIF('03_Eventos_pagamentos'!$E$11:$E$699,A31,'03_Eventos_pagamentos'!$O$11:$O$697)+SUMIF('03_Eventos_pagamentos'!$E$766:$E$836,A31,'03_Eventos_pagamentos'!$O$766:$O$836) | E31: =COUNTIF('03_Eventos_pagamentos'!$E$702:$E$763,'04_TOTALIZADORA (3)'!A31) | F31: =SUMIF('03_Eventos_pagamentos'!$E$702:$E$763,A31,'03_Eventos_pagamentos'!$O$702:$O$763) | G31: =D31+F31 | H31: =D31+F31+H30 | I31: =G31-S31 | J31: =H31-T31 | K31: =D31+F31-S31 | L31: =K31*0.15 | M31: =K31-L31 | N31: =M31+S31 | O31: =I31-R31 | P31: =SUMIF('03_Eventos_pagamentos'!$P$11:$P$843,A32,'03_Eventos_pagamentos'!$Q$11:$Q$843) | Q31: 100000 | R31: =P31+Q31 | S31: =SUMIFS( '03_Eventos_pagamentos'!$O$11:$O$843,'03_Eventos_pagamentos'!$E$11:$E$843,A31,'03_Eventos_pagamentos'!$I$11:$I$843,"FAT. DIRETO") | T31: =S31+T30 | U31: =P31+S31+U30 | W31: =V31+W30 | X31: 996943.88 | Y31: =Y30+X31
A32: 19 | B32: 46023 | C32: =SUM(COUNTIF('03_Eventos_pagamentos'!$E$11:$E$697,'04_TOTALIZADORA (3)'!A32)+COUNTIF('03_Eventos_pagamentos'!$E$766:$E$836,'04_TOTALIZADORA (3)'!A32)) | D32: =SUMIF('03_Eventos_pagamentos'!$E$11:$E$699,A32,'03_Eventos_pagamentos'!$O$11:$O$697)+SUMIF('03_Eventos_pagamentos'!$E$766:$E$836,A32,'03_Eventos_pagamentos'!$O$766:$O$836) | E32: =COUNTIF('03_Eventos_pagamentos'!$E$702:$E$763,'04_TOTALIZADORA (3)'!A32) | F32: =SUMIF('03_Eventos_pagamentos'!$E$702:$E$763,A32,'03_Eventos_pagamentos'!$O$702:$O$763) | G32: =D32+F32 | H32: =D32+F32+H31 | I32: =G32-S32 | J32: =H32-T32 | K32: =D32+F32-S32 | L32: =K32*0.15 | M32: =K32-L32 | N32: =M32+S32 | O32: =I32-R32 | P32: =SUMIF('03_Eventos_pagamentos'!$P$11:$P$843,A33,'03_Eventos_pagamentos'!$Q$11:$Q$843) | Q32: 100000 | R32: =P32+Q32 | S32: =SUMIFS( '03_Eventos_pagamentos'!$O$11:$O$843,'03_Eventos_pagamentos'!$E$11:$E$843,A32,'03_Eventos_pagamentos'!$I$11:$I$843,"FAT. DIRETO") | T32: =S32+T31 | U32: =P32+S32+U31 | V32: =0.85*213547.66 | W32: =V32+W31 | X32: 900062.68 | Y32: =Y31+X32
A33: 20 | B33: 46054 | C33: =SUM(COUNTIF('03_Eventos_pagamentos'!$E$11:$E$697,'04_TOTALIZADORA (3)'!A33)+COUNTIF('03_Eventos_pagamentos'!$E$766:$E$836,'04_TOTALIZADORA (3)'!A33)) | D33: =SUMIF('03_Eventos_pagamentos'!$E$11:$E$699,A33,'03_Eventos_pagamentos'!$O$11:$O$697)+SUMIF('03_Eventos_pagamentos'!$E$766:$E$836,A33,'03_Eventos_pagamentos'!$O$766:$O$836) | E33: =COUNTIF('03_Eventos_pagamentos'!$E$702:$E$763,'04_TOTALIZADORA (3)'!A33) | F33: =SUMIF('03_Eventos_pagamentos'!$E$702:$E$763,A33,'03_Eventos_pagamentos'!$O$702:$O$763) | G33: =D33+F33 | H33: =D33+F33+H32 | I33: =G33-S33 | J33: =H33-T33 | K33: =D33+F33-S33 | L33: =K33*0.15 | M33: =K33-L33 | N33: =M33+S33 | O33: =I33-R33 | P33: =SUMIF('03_Eventos_pagamentos'!$P$11:$P$843,A34,'03_Eventos_pagamentos'!$Q$11:$Q$843) | Q33: 100000 | R33: =P33+Q33 | S33: =SUMIFS( '03_Eventos_pagamentos'!$O$11:$O$843,'03_Eventos_pagamentos'!$E$11:$E$843,A33,'03_Eventos_pagamentos'!$I$11:$I$843,"FAT. DIRETO") | T33: =S33+T32 | U33: =P33+S33+U32 | W33: =V33+W32 | X33: 623444.52 | Y33: =Y32+X33
A34: 21 | B34: 46082 | C34: =SUM(COUNTIF('03_Eventos_pagamentos'!$E$11:$E$697,'04_TOTALIZADORA (3)'!A34)+COUNTIF('03_Eventos_pagamentos'!$E$766:$E$836,'04_TOTALIZADORA (3)'!A34)) | D34: =SUMIF('03_Eventos_pagamentos'!$E$11:$E$699,A34,'03_Eventos_pagamentos'!$O$11:$O$697)+SUMIF('03_Eventos_pagamentos'!$E$766:$E$836,A34,'03_Eventos_pagamentos'!$O$766:$O$836) | E34: =COUNTIF('03_Eventos_pagamentos'!$E$702:$E$763,'04_TOTALIZADORA (3)'!A34) | F34: =SUMIF('03_Eventos_pagamentos'!$E$702:$E$763,A34,'03_Eventos_pagamentos'!$O$702:$O$763) | G34: =D34+F34 | H34: =D34+F34+H33 | I34: =G34-S34 | J34: =H34-T34 | K34: =D34+F34-S34 | L34: =K34*0.15 | M34: =K34-L34 | N34: =M34+S34 | O34: =I34-R34 | P34: =SUMIF('03_Eventos_pagamentos'!$P$11:$P$843,A35,'03_Eventos_pagamentos'!$Q$11:$Q$843) | Q34: 100000 | R34: =P34+Q34 | S34: =SUMIFS( '03_Eventos_pagamentos'!$O$11:$O$843,'03_Eventos_pagamentos'!$E$11:$E$843,A34,'03_Eventos_pagamentos'!$I$11:$I$843,"FAT. DIRETO") | T34: =S34+T33 | U34: =P34+S34+U33 | W34: =V34+W33 | X34: 628101.5 | Y34: =Y33+X34
A35: 22 | B35: 46113 | C35: =SUM(COUNTIF('03_Eventos_pagamentos'!$E$11:$E$697,'04_TOTALIZADORA (3)'!A35)+COUNTIF('03_Eventos_pagamentos'!$E$766:$E$836,'04_TOTALIZADORA (3)'!A35)) | D35: =SUMIF('03_Eventos_pagamentos'!$E$11:$E$699,A35,'03_Eventos_pagamentos'!$O$11:$O$697)+SUMIF('03_Eventos_pagamentos'!$E$766:$E$836,A35,'03_Eventos_pagamentos'!$O$766:$O$836) | E35: =COUNTIF('03_Eventos_pagamentos'!$E$702:$E$763,'04_TOTALIZADORA (3)'!A35) | F35: =SUMIF('03_Eventos_pagamentos'!$E$702:$E$763,A35,'03_Eventos_pagamentos'!$O$702:$O$763) | G35: =D35+F35 | H35: =D35+F35+H34 | I35: =G35-S35 | J35: =H35-T35 | K35: =D35+F35-S35 | L35: =K35*0.15 | M35: =K35-L35 | N35: =M35+S35 | O35: =I35-R35 | P35: =SUMIF('03_Eventos_pagamentos'!$P$11:$P$843,A36,'03_Eventos_pagamentos'!$Q$11:$Q$843) | Q35: 100000 | R35: =P35+Q35 | S35: =SUMIFS( '03_Eventos_pagamentos'!$O$11:$O$843,'03_Eventos_pagamentos'!$E$11:$E$843,A35,'03_Eventos_pagamentos'!$I$11:$I$843,"FAT. DIRETO") | T35: =S35+T34 | U35: =P35+S35+U34 | W35: =V35+W34 | X35: 899398.5 | Y35: =Y34+X35
A36: 23 | B36: 46143 | C36: =SUM(COUNTIF('03_Eventos_pagamentos'!$E$11:$E$697,'04_TOTALIZADORA (3)'!A36)+COUNTIF('03_Eventos_pagamentos'!$E$766:$E$836,'04_TOTALIZADORA (3)'!A36)) | D36: =SUMIF('03_Eventos_pagamentos'!$E$11:$E$699,A36,'03_Eventos_pagamentos'!$O$11:$O$697)+SUMIF('03_Eventos_pagamentos'!$E$766:$E$836,A36,'03_Eventos_pagamentos'!$O$766:$O$836) | E36: =COUNTIF('03_Eventos_pagamentos'!$E$702:$E$763,'04_TOTALIZADORA (3)'!A36) | F36: =SUMIF('03_Eventos_pagamentos'!$E$702:$E$763,A36,'03_Eventos_pagamentos'!$O$702:$O$763) | G36: =D36+F36 | H36: =D36+F36+H35 | I36: =G36-S36 | J36: =H36-T36 | K36: =D36+F36-S36 | L36: =K36*0.15 | M36: =K36-L36 | N36: =M36+S36 | O36: =I36-R36 | P36: =SUMIF('03_Eventos_pagamentos'!$P$11:$P$843,A37,'03_Eventos_pagamentos'!$Q$11:$Q$843) | Q36: 100000 | R36: =P36+Q36 | S36: =SUMIFS( '03_Eventos_pagamentos'!$O$11:$O$843,'03_Eventos_pagamentos'!$E$11:$E$843,A36,'03_Eventos_pagamentos'!$I$11:$I$843,"FAT. DIRETO") | T36: =S36+T35 | U36: =P36+S36+U35 | W36: =V36+W35 | X36: 849378.18 | Y36: =Y35+X36
A37: 24 | B37: 46174 | C37: =SUM(COUNTIF('03_Eventos_pagamentos'!$E$11:$E$697,'04_TOTALIZADORA (3)'!A37)+COUNTIF('03_Eventos_pagamentos'!$E$766:$E$836,'04_TOTALIZADORA (3)'!A37)) | D37: =SUMIF('03_Eventos_pagamentos'!$E$11:$E$699,A37,'03_Eventos_pagamentos'!$O$11:$O$697)+SUMIF('03_Eventos_pagamentos'!$E$766:$E$836,A37,'03_Eventos_pagamentos'!$O$766:$O$836) | E37: =COUNTIF('03_Eventos_pagamentos'!$E$702:$E$763,'04_TOTALIZADORA (3)'!A37) | F37: =SUMIF('03_Eventos_pagamentos'!$E$702:$E$763,A37,'03_Eventos_pagamentos'!$O$702:$O$763) | G37: =D37+F37 | H37: =D37+F37+H36 | I37: =G37-S37 | J37: =H37-T37 | K37: =D37+F37-S37 | L37: =K37*0.15 | M37: =K37-L37 | N37: =M37+S37 | O37: =I37-R37 | P37: =SUMIF('03_Eventos_pagamentos'!$P$11:$P$843,A38,'03_Eventos_pagamentos'!$Q$11:$Q$843) | Q37: 100000 | R37: =P37+Q37 | S37: =SUMIFS( '03_Eventos_pagamentos'!$O$11:$O$843,'03_Eventos_pagamentos'!$E$11:$E$843,A37,'03_Eventos_pagamentos'!$I$11:$I$843,"FAT. DIRETO") | T37: =S37+T36 | U37: =P37+S37+U36 | W37: =V37+W36 | X37: 186000 | Y37: =Y36+X37
A38: 25 | B38: 46204 | C38: =SUM(COUNTIF('03_Eventos_pagamentos'!$E$11:$E$697,'04_TOTALIZADORA (3)'!A38)+COUNTIF('03_Eventos_pagamentos'!$E$766:$E$836,'04_TOTALIZADORA (3)'!A38)) | D38: =SUMIF('03_Eventos_pagamentos'!$E$11:$E$699,A38,'03_Eventos_pagamentos'!$O$11:$O$697)+SUMIF('03_Eventos_pagamentos'!$E$766:$E$836,A38,'03_Eventos_pagamentos'!$O$766:$O$836) | E38: =COUNTIF('03_Eventos_pagamentos'!$E$702:$E$763,'04_TOTALIZADORA (3)'!A38) | F38: =SUMIF('03_Eventos_pagamentos'!$E$702:$E$763,A38,'03_Eventos_pagamentos'!$O$702:$O$763) | G38: =D38+F38 | H38: =D38+F38+H37 | I38: =G38-S38 | J38: =H38-T38 | K38: =D38+F38-S38 | L38: =K38*0.15 | M38: =K38-L38 | N38: =M38+S38 | O38: =I38-R38 | P38: =SUMIF('03_Eventos_pagamentos'!$P$11:$P$843,A39,'03_Eventos_pagamentos'!$Q$11:$Q$843) | Q38: 100000 | R38: =P38+Q38 | S38: =SUMIFS( '03_Eventos_pagamentos'!$O$11:$O$843,'03_Eventos_pagamentos'!$E$11:$E$843,A38,'03_Eventos_pagamentos'!$I$11:$I$843,"FAT. DIRETO") | T38: =S38+T37 | U38: =P38+S38+U37 | W38: =V38+W37 | X38: 569901.22 | Y38: =Y37+X38
A39: 26 | B39: 46235 | C39: =SUM(COUNTIF('03_Eventos_pagamentos'!$E$11:$E$697,'04_TOTALIZADORA (3)'!A39)+COUNTIF('03_Eventos_pagamentos'!$E$766:$E$836,'04_TOTALIZADORA (3)'!A39)) | D39: =SUMIF('03_Eventos_pagamentos'!$E$11:$E$699,A39,'03_Eventos_pagamentos'!$O$11:$O$697)+SUMIF('03_Eventos_pagamentos'!$E$766:$E$836,A39,'03_Eventos_pagamentos'!$O$766:$O$836) | E39: =COUNTIF('03_Eventos_pagamentos'!$E$702:$E$763,'04_TOTALIZADORA (3)'!A39) | F39: =SUMIF('03_Eventos_pagamentos'!$E$702:$E$763,A39,'03_Eventos_pagamentos'!$O$702:$O$763) | G39: =D39+F39 | H39: =D39+F39+H38 | I39: =G39-S39 | J39: =H39-T39 | K39: =D39+F39-S39 | L39: =K39*0.15 | M39: =K39-L39 | N39: =M39+S39 | O39: =I39-R39 | P39: =SUMIF('03_Eventos_pagamentos'!$P$11:$P$843,A40,'03_Eventos_pagamentos'!$Q$11:$Q$843) | Q39: 100000 | R39: =P39+Q39 | S39: =SUMIFS( '03_Eventos_pagamentos'!$O$11:$O$843,'03_Eventos_pagamentos'!$E$11:$E$843,A39,'03_Eventos_pagamentos'!$I$11:$I$843,"FAT. DIRETO") | T39: =S39+T38 | U39: =P39+S39+U38 | W39: =V39+W38 | Y39: =Y38+X39
A40: 27 | B40: 46266 | C40: =SUM(COUNTIF('03_Eventos_pagamentos'!$E$11:$E$697,'04_TOTALIZADORA (3)'!A40)+COUNTIF('03_Eventos_pagamentos'!$E$766:$E$836,'04_TOTALIZADORA (3)'!A40)) | D40: =SUMIF('03_Eventos_pagamentos'!$E$11:$E$699,A40,'03_Eventos_pagamentos'!$O$11:$O$697)+SUMIF('03_Eventos_pagamentos'!$E$766:$E$836,A40,'03_Eventos_pagamentos'!$O$766:$O$836) | E40: =COUNTIF('03_Eventos_pagamentos'!$E$702:$E$763,'04_TOTALIZADORA (3)'!A40) | F40: =SUMIF('03_Eventos_pagamentos'!$E$702:$E$763,A40,'03_Eventos_pagamentos'!$O$702:$O$763) | G40: =D40+F40 | H40: =D40+F40+H39 | I40: =G40-S40 | J40: =H40-T40 | K40: =D40+F40-S40 | L40: =K40*0.15 | M40: =K40-L40 | N40: =M40+S40 | O40: =I40-R40 | P40: =SUMIF('03_Eventos_pagamentos'!$P$11:$P$843,A41,'03_Eventos_pagamentos'!$Q$11:$Q$843) | Q40: 100000 | R40: =P40+Q40 | S40: =SUMIFS( '03_Eventos_pagamentos'!$O$11:$O$843,'03_Eventos_pagamentos'!$E$11:$E$843,A40,'03_Eventos_pagamentos'!$I$11:$I$843,"FAT. DIRETO") | T40: =S40+T39 | U40: =P40+S40+U39 | W40: =V40+W39 | Y40: =Y39+X40
A41: 28 | B41: 46296 | C41: =SUM(COUNTIF('03_Eventos_pagamentos'!$E$11:$E$697,'04_TOTALIZADORA (3)'!A41)+COUNTIF('03_Eventos_pagamentos'!$E$766:$E$836,'04_TOTALIZADORA (3)'!A41)) | D41: =SUMIF('03_Eventos_pagamentos'!$E$11:$E$699,A41,'03_Eventos_pagamentos'!$O$11:$O$697)+SUMIF('03_Eventos_pagamentos'!$E$766:$E$836,A41,'03_Eventos_pagamentos'!$O$766:$O$836) | E41: =COUNTIF('03_Eventos_pagamentos'!$E$702:$E$763,'04_TOTALIZADORA (3)'!A41) | F41: =SUMIF('03_Eventos_pagamentos'!$E$702:$E$763,A41,'03_Eventos_pagamentos'!$O$702:$O$763) | G41: =D41+F41 | H41: =D41+F41+H40 | I41: =G41-S41 | J41: =H41-T41 | K41: =D41+F41-S41 | L41: =K41*0.15 | M41: =K41-L41 | N41: =M41+S41 | O41: =I41-R41 | P41: =SUMIF('03_Eventos_pagamentos'!$P$11:$P$843,A42,'03_Eventos_pagamentos'!$Q$11:$Q$843) | Q41: 100000 | R41: =P41+Q41 | S41: =SUMIFS( '03_Eventos_pagamentos'!$O$11:$O$843,'03_Eventos_pagamentos'!$E$11:$E$843,A41,'03_Eventos_pagamentos'!$I$11:$I$843,"FAT. DIRETO") | T41: =S41+T40 | U41: =P41+S41+U40 | W41: =V41+W40 | Y41: =Y40+X41
A42: 29 | B42: 46327 | C42: =SUM(COUNTIF('03_Eventos_pagamentos'!$E$11:$E$697,'04_TOTALIZADORA (3)'!A42)+COUNTIF('03_Eventos_pagamentos'!$E$766:$E$836,'04_TOTALIZADORA (3)'!A42)) | D42: =SUMIF('03_Eventos_pagamentos'!$E$11:$E$699,A42,'03_Eventos_pagamentos'!$O$11:$O$697)+SUMIF('03_Eventos_pagamentos'!$E$766:$E$836,A42,'03_Eventos_pagamentos'!$O$766:$O$836) | E42: =COUNTIF('03_Eventos_pagamentos'!$E$702:$E$763,'04_TOTALIZADORA (3)'!A42) | F42: =SUMIF('03_Eventos_pagamentos'!$E$702:$E$763,A42,'03_Eventos_pagamentos'!$O$702:$O$763) | G42: =D42+F42 | H42: =D42+F42+H41 | I42: =G42-S42 | J42: =H42-T42 | K42: =D42+F42-S42 | L42: =K42*0.15 | M42: =K42-L42 | N42: =M42+S42 | O42: =I42-R42 | P42: =SUMIF('03_Eventos_pagamentos'!$P$11:$P$843,A43,'03_Eventos_pagamentos'!$Q$11:$Q$843) | Q42: 100000 | R42: =P42+Q42 | S42: =SUMIFS( '03_Eventos_pagamentos'!$O$11:$O$843,'03_Eventos_pagamentos'!$E$11:$E$843,A42,'03_Eventos_pagamentos'!$I$11:$I$843,"FAT. DIRETO") | T42: =S42+T41 | U42: =P42+S42+U41 | W42: =V42+W41 | Y42: =Y41+X42
A43: 30 | B43: 46357 | C43: =SUM(COUNTIF('03_Eventos_pagamentos'!$E$11:$E$697,'04_TOTALIZADORA (3)'!A43)+COUNTIF('03_Eventos_pagamentos'!$E$766:$E$836,'04_TOTALIZADORA (3)'!A43)) | D43: =SUMIF('03_Eventos_pagamentos'!$E$11:$E$699,A43,'03_Eventos_pagamentos'!$O$11:$O$697)+SUMIF('03_Eventos_pagamentos'!$E$766:$E$836,A43,'03_Eventos_pagamentos'!$O$766:$O$836) | E43: =COUNTIF('03_Eventos_pagamentos'!$E$702:$E$763,'04_TOTALIZADORA (3)'!A43) | F43: =SUMIF('03_Eventos_pagamentos'!$E$702:$E$763,A43,'03_Eventos_pagamentos'!$O$702:$O$763) | G43: =D43+F43 | H43: =D43+F43+H42 | I43: =G43-S43 | J43: =H43-T43 | K43: =D43+F43-S43 | L43: =K43*0.15 | M43: =K43-L43 | N43: =M43+S43 | O43: =I43-R43 | P43: =SUMIF('03_Eventos_pagamentos'!$P$11:$P$843,A44,'03_Eventos_pagamentos'!$Q$11:$Q$843) | Q43: 100000 | R43: =P43+Q43 | S43: =SUMIFS( '03_Eventos_pagamentos'!$O$11:$O$843,'03_Eventos_pagamentos'!$E$11:$E$843,A43,'03_Eventos_pagamentos'!$I$11:$I$843,"FAT. DIRETO") | T43: =S43+T42 | U43: =P43+S43+U42 | W43: =V43+W42 | Y43: =Y42+X43
